Workbook

Sheet 📋 Documentation
A1: LIIMRA NATURALS — UNIT ECONOMICS MODEL | FY 2026-27
A2: Model Documentation, Methodology & Glossary
A4: PURPOSE
A5: Scope | B5: This workbook models SKU-level unit economics for Liimra Naturals' Flipkart marketplace business for FY 2026-27. It is built on FY 2024-25 actuals (COGS, return rates, per-unit OpEx) layered with new selling prices and a +20% volume growth assumption.
A6: Sheets in this workbook | B6: 📋 Documentation | 📊 FY2627 Actuals | 🎛 What-If Model | 🏪 Marketplace UE
A8: MODEL ASSUMPTIONS
A9: Volume growth | B9: +20% on FY 2024-25 gross units ordered, rounded to whole units (blue hardcoded inputs)
A10: Selling prices | B10: Updated selling prices sourced from sku.xlsx (10 SKUs updated; remainder carried forward)
A11: COGS | B11: Carried forward from FY 2024-25 actuals — includes product cost + packing material
A12: Return rate | B12: 8.00% flat across all SKUs (FY 2024-25 observed rate)
A13: Ad spend | B13: ₹17,702 total held constant at FY 2024-25 level; allocated pro-rata by SKU net revenue share
A14: Fixed overheads | B14: ₹30,000/month (Warehousing ₹10k + Salary ₹15k + Misc ₹5k) = ₹3,60,000/year
A15: TCS | B15: 1% of Net Selling Price (collected by Flipkart, remittable on filing)
A16: TDS | B16: 0.1% of Net Revenue (deducted by Flipkart, recoverable against advance tax)
A17: GST on MP fees | B17: 18% on Flipkart fixed fee + collection fee
A19: METRIC DEFINITIONS
A20: Gross Units Ordered | B20: Total orders placed by customers before returns
A21: Net Units Sold | B21: Gross Units − Returns
A22: Net Selling Price (NSP) | B22: Listing price net of customer returns. Equals listing price since return-adjusted.
A23: Gross Revenue | B23: Gross Units × Listing Price
A24: Net Revenue | B24: Gross Revenue − Returns & Refunds value
A25: COGS incl. Packing | B25: Direct product cost + packing per unit, carried from actuals
A26: Gross Profit | B26: Net Revenue − Total COGS
A27: Gross Margin % | B27: Gross Profit ÷ Net Revenue
A28: Marketplace Fees | B28: Flipkart fixed fee per unit (weight/category-based) + collection fee
A29: Logistics — Returns | B29: Reverse shipping cost per returned unit, allocated to net units
A30: Ad Spend Allocated | B30: SKU's share of total ad spend, pro-rated by net revenue
A31: TCS | B31: Tax Collected at Source: 1% of NSP, collected by Flipkart, remitted by seller to tax dept
... A43: Net Profit after Fixed OH | B43: Net Profit − Fixed Overhead Allocated
A45: COLOUR CODING
A46: Blue text | B46: Hardcoded input values (do not overwrite with formulas)
A47: Black text | B47: Formula-derived values
A48: Green text | B48: Cross-sheet links
A49: Yellow background | B49: Key assumption cells — review before running scenarios
A51: MARKETPLACE SHEET NOTES
A52: Purpose | B52: Standalone unit economics calculator for any marketplace (Flipkart, Amazon, JioMart, eBay). Enter the marketplace fee structure and product details to compute margins and BEP.
A53: Fee structures | B53: Amazon: Referral fee % + Closing fee + Weight handling; Flipkart: Fixed fee + Collection fee; JioMart/eBay: Commission %. All configured in the Marketplace UE sheet.
A55: WHAT-IF MODEL NOTES
A56: Purpose | B56: Sensitivity model — change price, volume, COGS, return rate, ad spend. All outputs auto-recalculate.
A57: Scenario toggle | B57: Choose Base / Bull / Bear scenario from dropdown. Each has its own assumption set.
A58: Key levers | B58: Selling price has highest impact on contribution margin. Volume growth unlocks fixed OH leverage.
A60: VERSION
A61: Model version | B61: v1.0 — FY 2026-27 Projection
A62: Data source | B62: FY 2024-25 actuals + sku.xlsx updated prices
A63: Prepared by | B63: Liimra Naturals Finance
A64: Date | B64: May 2026
A66: MONTHLY PLAN VS ACTUAL — NEW SHEETS ADDED
A67: ⚙ Config & Assumptions | B67: Master assumptions register. All blue cells are live inputs. Yellow = high-impact. Change seasonality, NSP, COGS, return rate, fixed OH, and current reporting month here. All other sheets update automatically.
A68: 📅 Monthly PvA | B68: Full 12-month Plan vs Actual grid. Columns: Plan | Actual (green — enter data here) | Var ₹ | Var %. Covers all 11 P&L sections. MTD and YTD columns auto-populate based on the current month set in Config. Conditional formatting highlights favourable/adverse variances.
A69: 📊 MTD Dashboard | B69: Single-page snapshot of MTD and YTD for 14 key metrics. Status column shows ✔ On/Above / ✘ Below / ~ Near based on variance thresholds in Config. All data pulls from PvA — no manual entry needed here.
A70: Configurable elements — full list | B70: See ⚙ Config & Assumptions sheet for the complete register with allowed ranges and impact notes. Key levers: Seasonality weights (12 cells), NSP, COGS, return rate, ad spend, fixed OH components, reporting month, variance thresholds.

Sheet ⚙ Config & Assumptions
A1: LIIMRA NATURALS | CONFIGURABLE ASSUMPTIONS REGISTER | FY 2026-27
A2: All BLUE cells are configurable inputs. Change them here and all linked sheets update automatically. Black = formula-derived. Yellow background = high-impact assumption — review before publishing.
A3: Parameter | B3: Current Value | C3: Allowed Range / Notes | D3: Impact & Description
A4: ◆ VOLUME & GROWTH
A5: Annual Gross Units Ordered (FY Plan) | B5: 1123 | C5: 500 – 5000 | D5: Total orders placed before returns. Drives all revenue & cost lines. +20% vs FY24-25.
A6: Volume Growth Rate vs Prior Year (%) | B6: 0.2 | C6: 0% – 100% | D6: Year-on-year gross unit growth assumption. Currently set to 20%.
A7: Monthly Seasonality — April | B7: 0.07 | C7: 0.01 – 0.20 | D7: Share of annual volume in April. All 12 months must sum to 1.0.
A8: Monthly Seasonality — May | B8: 0.075 | C8: 0.01 – 0.20 | D8: Share of annual volume in May.
A9: Monthly Seasonality — June | B9: 0.065 | C9: 0.01 – 0.20 | D9: Share of annual volume in June.
A10: Monthly Seasonality — July | B10: 0.075 | C10: 0.01 – 0.20 | D10: Share of annual volume in July.
A11: Monthly Seasonality — August | B11: 0.09 | C11: 0.01 – 0.20 | D11: Festive ramp-up begins. Raksha Bandhan / Independence Day spike.
A12: Monthly Seasonality — September | B12: 0.095 | C12: 0.01 – 0.20 | D12: Navratri / Onam. Peak health-food demand.
A13: Monthly Seasonality — October | B13: 0.1 | C13: 0.01 – 0.20 | D13: Dussehra / Dhanteras. Highest month — gifting + wellness spend.
A14: Monthly Seasonality — November | B14: 0.095 | C14: 0.01 – 0.20 | D14: Diwali / post-festive. Still elevated.
A15: Monthly Seasonality — December | B15: 0.09 | C15: 0.01 – 0.20 | D15: Year-end / Christmas. Moderate.
A16: Monthly Seasonality — January | B16: 0.09 | C16: 0.01 – 0.20 | D16: New Year resolution health wave.
... A18: Monthly Seasonality — March | B18: 0.07 | C18: 0.01 – 0.20 | D18: Year-end slowdown before new FY.
A19: Seasonality Sum (must = 1.00) | B19: =SUM(B6:B17) -> 1.13 | C19: Must equal 1.00 | D19: Auto-checks. If not 1.00, monthly plans will not match annual total.
A20: ◆ PRICING & RETURNS
A21: Blended Average NSP (₹/unit) | B21: 155.64 | C21: 100 – 300 | D21: Weighted average net selling price across all SKUs. Update if mix shifts.
A22: Return Rate — Blended (%) | B22: 0.0793 | C22: 0% – 20% | D22: FY24-25 observed blended return rate (7.93%). Changes here flow through to net units.
A23: ◆ COST STRUCTURE
A24: Blended COGS incl. Packing (₹/unit) | B24: 91.65 | C24: 60 – 150 | D24: Weighted average COGS. Update if product mix or input costs change.
A25: Blended Marketplace Fee (₹/unit) | B25: 9.06 | C25: 7 – 15 | D25: Weighted avg FK fixed fee. Increases with heavier/higher-value SKUs.
A26: Blended Reverse Logistics (₹/net unit) | B26: 4.46 | C26: 0 – 25 | D26: Weighted avg reverse shipping cost. Allocated to net units sold.
A27: ◆ ADVERTISING
A28: Total Annual Ad Spend (₹) | B28: 17702 | C28: 5000 – 100000 | D28: Held constant from FY24-25. Increase to test volume uplift scenarios.
A29: Ad Spend Monthly Distribution | B29: Equal (1/12) | C29: Equal or seasonal | D29: Currently split equally across months. Can be made seasonal in Config sheet.
A30: ◆ TAXES & COMPLIANCE
A31: TCS Rate (%) | B31: 0.01 | C31: 1% (statutory) | D31: Tax Collected at Source by Flipkart. Statutory — do not change.
A32: TDS Rate (%) | B32: 0.001 | C32: 0.1% (statutory) | D32: Tax Deducted at Source by Flipkart. Recoverable. Statutory — do not change.
A33: GST on Marketplace Fees (%) | B33: 0.18 | C33: 18% (statutory) | D33: GST on platform fees paid by seller. Statutory — do not change.
A34: ◆ FIXED OVERHEADS
A35: Monthly Warehousing Cost (₹) | B35: 10000 | C35: 5000 – 50000 | D35: Current: single warehouse location. Update if storage needs expand.
A36: Monthly Salary Cost (₹) | B36: 15000 | C36: 10000 – 100000 | D36: Currently 1 FTE. Update on headcount addition.
A37: Monthly Miscellaneous (₹) | B37: 5000 | C37: 1000 – 20000 | D37: Packaging consumables, utilities, software subscriptions.
A38: Total Monthly Fixed Overheads (₹) | B38: =B31+B32+B33 -> 0.191 | C38: Target < ₹50,000/month | D38: Sum of above. ₹30,000/month = ₹3,60,000 annually.
A39: Total Annual Fixed Overheads (₹) | B39: =B34*12 -> 0 | C39: — | D39: Annualised. Allocated pro-rata by net revenue share across SKUs.
A40: ◆ PLAN VS ACTUAL
A41: Current Reporting Month (1=Apr … 12=Mar) | B41: 1 | C41: 1 – 12 | D41: Set this to current month number. Controls MTD & YTD calculations in PvA sheet.
A42: Variance Alert Threshold — Favourable (%) | B42: 0.05 | C42: 1% – 20% | D42: Green highlight if actual exceeds plan by more than this %.
A43: Variance Alert Threshold — Adverse (%) | B43: -0.05 | C43: -20% – -1% | D43: Red highlight if actual is below plan by more than this %.
A45: ⚡ Yellow background = HIGH IMPACT assumption — change with care. Blue background = standard configurable input.

Sheet 🏪 Marketplace UE
A1: LIIMRA NATURALS | MARKETPLACE-DRIVEN UNIT ECONOMICS | FY 2026-27
A2: Calculate and compare unit economics across Flipkart, Amazon India, JioMart & eBay India. Blue cells = inputs. Change any value to see live recalculation.
A4: Parameter / Metric | B4: Flipkart | C4: Amazon India | D4: JioMart | E4: eBay India
A5: ── PRODUCT (same across all platforms)
A6: MRP / Listing Price (₹/unit) | B6: 164 | C6: 164 | D6: 164 | E6: 164
A7: COGS incl. Packing (₹/unit) | B7: 92.35 | C7: 92.35 | D7: 92.35 | E7: 92.35
A8: Monthly Volume (Units, net sold) | B8: 66 | C8: 25 | D8: 15 | E8: 5
A9: Return Rate (%) | B9: 0.08 | C9: 0.12 | D9: 0.05 | E9: 0.03
A11: ── MARKETPLACE FEE STRUCTURE
A12: Referral / Commission (%) | B12: 0 | C12: 0.05 | D12: 0.06 | E12: 0.09
A13: Fixed Fee per Order (₹) | B13: 9 | C13: 0 | D13: 0 | E13: 0
A14: Closing / Weight Handling Fee (₹) | B14: 0 | C14: 25 | D14: 0 | E14: 0
A15: Shipping charged to seller (₹/unit) | B15: 0 | C15: 45 | D15: 0 | E15: 0
A16: Reverse Logistics per return (₹) | B16: 3.35 | C16: 55 | D16: 0 | E16: 0
A17: GST on platform fees (%) | B17: 0.18 | C17: 0.18 | D17: 0.18 | E17: 0
A19: ── TAXES
A20: TCS Rate (%) | B20: 0.01 | C20: 0.01 | D20: 0 | E20: 0
A21: TDS Rate (%) | B21: 0.001 | C21: 0.001 | D21: 0 | E21: 0
A23: ── ADVERTISING
A24: Monthly Ad Spend (₹) | B24: 1475 | C24: 800 | D24: 0 | E24: 0
A26: COMPUTED UNIT ECONOMICS (Monthly Basis)
A27: ── REVENUE (Monthly)
A28: Gross Units | B28: =ROUND(B8/(1-B9),0) -> 72 | C28: =ROUND(C8/(1-C9),0) -> 28 | D28: =ROUND(D8/(1-D9),0) -> 16 | E28: =ROUND(E8/(1-E9),0) -> 5
A29: Net Units Sold | B29: =B8 -> 66 | C29: =C8 -> 25 | D29: =D8 -> 15 | E29: =E8 -> 5
A30: Gross Revenue (₹) | B30: =ROUND(B8/(1-B9)*B6,0) -> 11765 | C30: =ROUND(C8/(1-C9)*C6,0) -> 4659 | D30: =ROUND(D8/(1-D9)*D6,0) -> 2589 | E30: =ROUND(E8/(1-E9)*E6,0) -> 845
A31: Refund Value (₹) | B31: =ROUND((B8/(1-B9)-B8)*B6,0) -> 941 | C31: =ROUND((C8/(1-C9)-C8)*C6,0) -> 559 | D31: =ROUND((D8/(1-D9)-D8)*D6,0) -> 129 | E31: =ROUND((E8/(1-E9)-E8)*E6,0) -> 25
A32: Net Revenue (₹) | B32: =B8*B6 -> 10824 | C32: =C8*C6 -> 4100 | D32: =D8*D6 -> 2460 | E32: =E8*E6 -> 820
A34: ── COSTS (Monthly)
A35: COGS Total (₹) | B35: =B8*B7 -> 6095.1 | C35: =C8*C7 -> 2308.75 | D35: =D8*D7 -> 1385.25 | E35: =E8*E7 -> 461.75
A36: Platform Commission (₹) | B36: =ROUND(B8*B6*B12,0) -> 0 | C36: =ROUND(C8*C6*C12,0) -> 205 | D36: =ROUND(D8*D6*D12,0) -> 148 | E36: =ROUND(E8*E6*E12,0) -> 74
A37: Fixed Fee Total (₹) | B37: =B8*B13 -> 594 | C37: =C8*C13 -> 0 | D37: =D8*D13 -> 0 | E37: =E8*E13 -> 0
A38: Closing / Weight Handling (₹) | B38: =B8*B14 -> 0 | C38: =C8*C14 -> 625 | D38: =D8*D14 -> 0 | E38: =E8*E14 -> 0
A39: Outbound Shipping (₹) | B39: =B8*B15 -> 0 | C39: =C8*C15 -> 1125 | D39: =D8*D15 -> 0 | E39: =E8*E15 -> 0
A40: Reverse Logistics (₹) | B40: =ROUND((B8/(1-B9)-B8)*B16,0) -> 19 | C40: =ROUND((C8/(1-C9)-C8)*C16,0) -> 188 | D40: =ROUND((D8/(1-D9)-D8)*D16,0) -> 0 | E40: =ROUND((E8/(1-E9)-E8)*E16,0) -> 0
A41: GST on Platform Fees (₹) | B41: =ROUND((B8*B6*B12+B8*B13+B8*B14)*B17,0) -> 107 | C41: =ROUND((C8*C6*C12+C8*C13+C8*C14)*C17,0) -> 149 | D41: =ROUND((D8*D6*D12+D8*D13+D8*D14)*D17,0) -> 27 | E41: =ROUND((E8*E6*E12+E8*E13+E8*E14)*E17,0) -> 0
A42: TCS (₹) | B42: =ROUND(B8*B6*B20,0) -> 108 | C42: =ROUND(C8*C6*C20,0) -> 41 | D42: =ROUND(D8*D6*D20,0) -> 0 | E42: =ROUND(E8*E6*E20,0) -> 0
A43: TDS (₹) [recoverable] | B43: =ROUND(B8*B6*B21,0) -> 11 | C43: =ROUND(C8*C6*C21,0) -> 4 | D43: =ROUND(D8*D6*D21,0) -> 0 | E43: =ROUND(E8*E6*E21,0) -> 0
A44: Ad Spend (₹) | B44: =B24 -> 1475 | C44: =C24 -> 800 | D44: =D24 -> 0 | E44: =E24 -> 0
A46: ── P&L SUMMARY (Monthly)
A47: Gross Profit (₹) | B47: =B32-B35 -> 4728.9 | C47: =C32-C35 -> 1791.25 | D47: =D32-D35 -> 1074.75 | E47: =E32-E35 -> 358.25
A48: Gross Margin (%) | B48: =IF(B32=0,0,(B32-B35)/B32) -> 0.43689024 | C48: =IF(C32=0,0,(C32-C35)/C32) -> 0.43689024 | D48: =IF(D32=0,0,(D32-D35)/D32) -> 0.43689024 | E48: =IF(E32=0,0,(E32-E35)/E32) -> 0.43689024
A49: Total Platform Cost (₹) | B49: =B36+B37+B38+B39+B40+B41+B42+B44 -> 2303 | C49: =C36+C37+C38+C39+C40+C41+C42+C44 -> 3133 | D49: =D36+D37+D38+D39+D40+D41+D42+D44 -> 175 | E49: =E36+E37+E38+E39+E40+E41+E42+E44 -> 74
A50: Operating Profit (₹) | B50: =B47-B49 -> 2425.9 | C50: =C47-C49 -> -1341.75 | D50: =D47-D49 -> 899.75 | E50: =E47-E49 -> 284.25
A51: Operating Margin (%) | B51: =IF(B32=0,0,B50/B32) -> 0.22412232 | C51: =IF(C32=0,0,C50/C32) -> -0.3272561 | D51: =IF(D32=0,0,D50/D32) -> 0.36575203 | E51: =IF(E32=0,0,E50/E32) -> 0.34664634
A52: Net Profit (₹) | B52: =B50-B43 -> 2414.9 | C52: =C50-C43 -> -1345.75 | D52: =D50-D43 -> 899.75 | E52: =E50-E43 -> 284.25
A53: Net Margin (%) | B53: =IF(B32=0,0,B52/B32) -> 0.22310606 | C53: =IF(C32=0,0,C52/C32) -> -0.32823171 | D53: =IF(D32=0,0,D52/D32) -> 0.36575203 | E53: =IF(E32=0,0,E52/E32) -> 0.34664634
A55: ── PER UNIT (Net Sold)
A56: Revenue per Unit (₹) | B56: =B6 -> 164 | C56: =C6 -> 164 | D56: =D6 -> 164 | E56: =E6 -> 164
A57: COGS per Unit (₹) | B57: =B7 -> 92.35 | C57: =C7 -> 92.35 | D57: =D7 -> 92.35 | E57: =E7 -> 92.35
A58: Platform Fees per Unit (₹) | B58: =IF(B29=0,0,B49/B29) -> 34.893939 | C58: =IF(C29=0,0,C49/C29) -> 125.32 | D58: =IF(D29=0,0,D49/D29) -> 11.666667 | E58: =IF(E29=0,0,E49/E29) -> 14.8
A59: Net Profit per Unit (₹) | B59: =IF(B29=0,0,B52/B29) -> 36.589394 | C59: =IF(C29=0,0,C52/C29) -> -53.83 | D59: =IF(D29=0,0,D52/D29) -> 59.983333 | E59: =IF(E29=0,0,E52/E29) -> 56.85
A60: Contribution per Unit (₹) | B60: =B56-B57-IF(B29=0,0,(B36+B37+B38+B39+B40+B41+B42)/B29) -> 59.104545 | C60: =C56-C57-IF(C29=0,0,(C36+C37+C38+C39+C40+C41+C42)/C29) -> -21.67 | D60: =D56-D57-IF(D29=0,0,(D36+D37+D38+D39+D40+D41+D42)/D29) -> 59.983333 | E60: =E56-E57-IF(E29=0,0,(E36+E37+E38+E39+E40+E41+E42)/E29) -> 56.85
A61: Contribution Margin (%) | B61: =IF(B56=0,0,B60/B56) -> 0.36039357 | C61: =IF(C56=0,0,C60/C56) -> -0.13213415 | D61: =IF(D56=0,0,D60/D56) -> 0.36575203 | E61: =IF(E56=0,0,E60/E56) -> 0.34664634
A62: BEP (units to cover ad spend) | B62: =IF(B60<=0,"N/A",CEILING(B44/B60,1)) -> 25 | C62: =IF(C60<=0,"N/A",CEILING(C44/C60,1)) -> N/A | D62: =IF(D60<=0,"N/A",CEILING(D44/D60,1)) -> 0 | E62: =IF(E60<=0,"N/A",CEILING(E44/E60,1)) -> 0
A63: Break-even Revenue (₹) | B63: =IF(B60<=0,"N/A",B62*B56) -> 4100 | C63: =IF(C60<=0,"N/A",C62*C56) -> N/A | D63: =IF(D60<=0,"N/A",D62*D56) -> 0 | E63: =IF(E60<=0,"N/A",E62*E56) -> 0
A66: CROSS-PLATFORM COMPARISON SUMMARY (Monthly)
A67: Metric | B67: Flipkart | C67: Amazon India | D67: JioMart | E67: eBay India
A68: Net Revenue (₹) | B68: =B32 -> 10824 | C68: =C32 -> 4100 | D68: =D32 -> 2460 | E68: =E32 -> 820
A69: Gross Profit (₹) | B69: =B47 -> 4728.9 | C69: =C47 -> 1791.25 | D69: =D47 -> 1074.75 | E69: =E47 -> 358.25
A70: Gross Margin (%) | B70: =B48 -> 0.43689024 | C70: =C48 -> 0.43689024 | D70: =D48 -> 0.43689024 | E70: =E48 -> 0.43689024
A71: Net Profit (₹) | B71: =B52 -> 2414.9 | C71: =C52 -> -1345.75 | D71: =D52 -> 899.75 | E71: =E52 -> 284.25
A72: Net Margin (%) | B72: =B53 -> 0.22310606 | C72: =C53 -> -0.32823171 | D72: =D53 -> 0.36575203 | E72: =E53 -> 0.34664634
A73: Contribution/Unit | B73: =B60 -> 59.104545 | C73: =C60 -> -21.67 | D73: =D60 -> 59.983333 | E73: =E60 -> 56.85

Sheet 🎛 What-If Model
A1: LIIMRA NATURALS | WHAT-IF SCENARIO MODEL | FY 2026-27
A2: Adjust assumptions in the BLUE cells. All metrics auto-recalculate. Three scenario columns: Base (actuals) | Bull (+) | Bear (−)
A4: Assumption | B4: Base Case (FY2627 Plan) | C4: Bull Case (Upside) | D4: Bear Case (Downside)
A5: ── VOLUME & PRICE
A6: Annual Gross Units | B6: 1123 | C6: 1400 | D6: 850
A7: Return Rate (%) | B7: 0.08 | C7: 0.06 | D7: 0.12
A8: Avg Net Selling Price (₹/unit) | B8: 155.64 | C8: 170 | D8: 140
A10: ── COST STRUCTURE
A11: Avg COGS incl. Packing (₹/unit) | B11: 91.65 | C11: 88 | D11: 95
A12: Avg Marketplace Fee (₹/unit) | B12: 9.06 | C12: 9.06 | D12: 10
A13: Avg Reverse Logistics (₹/unit) | B13: 4.46 | C13: 3.5 | D13: 6
A15: ── ADVERTISING
A16: Total Ad Spend (₹) | B16: 17702 | C16: 17702 | D16: 22000
A18: ── TAXES & COMPLIANCE
A19: TCS Rate (%) | B19: 0.01 | C19: 0.01 | D19: 0.01
A20: GST on MP Fees Rate (%) | B20: 0.18 | C20: 0.18 | D20: 0.18
A21: TDS Rate (%) | B21: 0.001 | C21: 0.001 | D21: 0.001
A23: ── FIXED OVERHEADS
A24: Annual Fixed Overheads (₹) | B24: 360000 | C24: 360000 | D24: 420000
A26: COMPUTED OUTPUTS — all values in ₹ unless stated
A27: Metric | B27: Base Case | C27: Bull Case | D27: Bear Case
A28: ── VOLUME
A29: Net Units Sold | B29: =ROUND(B6*(1-B7),0) -> 1033 | C29: =ROUND(C6*(1-C7),0) -> 1316 | D29: =ROUND(D6*(1-D7),0) -> 748
A30: Returns (Units) | B30: =ROUND(B6*B7,0) -> 90 | C30: =ROUND(C6*C7,0) -> 84 | D30: =ROUND(D6*D7,0) -> 102
A32: ── REVENUE
A33: Gross Revenue (₹) | B33: =B6*B8 -> 174783.72 | C33: =C6*C8 -> 238000 | D33: =D6*D8 -> 119000
A34: Net Revenue (₹) | B34: =ROUND(B6*(1-B7)*B8,0) -> 160801 | C34: =ROUND(C6*(1-C7)*C8,0) -> 223720 | D34: =ROUND(D6*(1-D7)*D8,0) -> 104720
A36: ── COST & PROFIT
A37: Total COGS (₹) | B37: =ROUND(B6*(1-B7)*B11,0) -> 94689 | C37: =ROUND(C6*(1-C7)*C11,0) -> 115808 | D37: =ROUND(D6*(1-D7)*D11,0) -> 71060
A38: Gross Profit (₹) | B38: =ROUND(B6*(1-B7)*B8,0)-ROUND(B6*(1-B7)*B11,0) -> 66112 | C38: =ROUND(C6*(1-C7)*C8,0)-ROUND(C6*(1-C7)*C11,0) -> 107912 | D38: =ROUND(D6*(1-D7)*D8,0)-ROUND(D6*(1-D7)*D11,0) -> 33660
A39: Gross Margin (%) | B39: =(ROUND(B6*(1-B7)*B8,0)-ROUND(B6*(1-B7)*B11,0))/ROUND(B6*(1-B7)*B8,0) -> 0.41114172 | C39: =(ROUND(C6*(1-C7)*C8,0)-ROUND(C6*(1-C7)*C11,0))/ROUND(C6*(1-C7)*C8,0) -> 0.48235294 | D39: =(ROUND(D6*(1-D7)*D8,0)-ROUND(D6*(1-D7)*D11,0))/ROUND(D6*(1-D7)*D8,0) -> 0.32142857
A41: ── OPERATING EXPENSES
A42: Total Marketplace Fees (₹) | B42: =ROUND(B6*(1-B7)*B12,0) -> 9360 | C42: =ROUND(C6*(1-C7)*C12,0) -> 11923 | D42: =ROUND(D6*(1-D7)*D12,0) -> 7480
A43: Total Logistics (₹) | B43: =ROUND(B6*(1-B7)*B13,0) -> 4608 | C43: =ROUND(C6*(1-C7)*C13,0) -> 4606 | D43: =ROUND(D6*(1-D7)*D13,0) -> 4488
A44: Ad Spend (₹) | B44: =B16 -> 17702 | C44: =C16 -> 17702 | D44: =D16 -> 22000
A45: Total Taxes — TCS+GST (₹) | B45: =ROUND(B6*(1-B7)*(B8*B19+B12*B20),0) -> 3293 | C45: =ROUND(C6*(1-C7)*(C8*C19+C12*C20),0) -> 4383 | D45: =ROUND(D6*(1-D7)*(D8*D19+D12*D20),0) -> 2394
A47: ── BOTTOM LINE
A48: Operating Profit (₹) | B48: =ROUND(B6*(1-B7)*B8,0)-ROUND(B6*(1-B7)*B11,0)-ROUND(B6*(1-B7)*B12,0)-ROUND(B6*(1-B7)*B13,0)-B16-ROUND(B6*(1-B7)*(B8*B19+B12*B20),0) -> 31149 | C48: =ROUND(C6*(1-C7)*C8,0)-ROUND(C6*(1-C7)*C11,0)-ROUND(C6*(1-C7)*C12,0)-ROUND(C6*(1-C7)*C13,0)-C16-ROUND(C6*(1-C7)*(C8*C19+C12*C20),0) -> 69298 | D48: =ROUND(D6*(1-D7)*D8,0)-ROUND(D6*(1-D7)*D11,0)-ROUND(D6*(1-D7)*D12,0)-ROUND(D6*(1-D7)*D13,0)-D16-ROUND(D6*(1-D7)*(D8*D19+D12*D20),0) -> -2702
A49: Operating Margin (%) | B49: =IF(B34=0,0,B48/B34) -> 0.19371148 | C49: =IF(C34=0,0,C48/C34) -> 0.30975326 | D49: =IF(D34=0,0,D48/D34) -> -0.025802139
A50: TDS (₹) [recoverable] | B50: =ROUND(B6*(1-B7)*B8*B21,0) -> 161 | C50: =ROUND(C6*(1-C7)*C8*C21,0) -> 224 | D50: =ROUND(D6*(1-D7)*D8*D21,0) -> 105
A51: Net Profit pre-Fixed OH (₹) | B51: =B48-B50 -> 30988 | C51: =C48-C50 -> 69074 | D51: =D48-D50 -> -2807
A52: Net Margin pre-Fixed OH (%) | B52: =IF(B34=0,0,B51/B34) -> 0.19271024 | C52: =IF(C34=0,0,C51/C34) -> 0.30875201 | D52: =IF(D34=0,0,D51/D34) -> -0.026804813
A53: Fixed Overheads (₹) | B53: =B24 -> 360000 | C53: =C24 -> 360000 | D53: =D24 -> 420000
A54: Net Profit after Fixed OH (₹) | B54: =B51-B53 -> -329012 | C54: =C51-C53 -> -290926 | D54: =D51-D53 -> -422807
A55: Net Margin after Fixed OH (%) | B55: =IF(B34=0,0,B54/B34) -> -2.0460818 | C55: =IF(C34=0,0,C54/C34) -> -1.3004023 | D55: =IF(D34=0,0,D54/D34) -> -4.0375
A57: ── PER UNIT ECONOMICS
A58: Contribution per Unit (₹) | B58: =B8-B11-B12-B13-B8*B19-B12*B20 -> 47.2828 | C58: =C8-C11-C12-C13-C8*C19-C12*C20 -> 66.1092 | D58: =D8-D11-D12-D13-D8*D19-D12*D20 -> 25.8
A59: Contribution Margin (%) | B59: =(B8-B11-B12-B13-B8*B19-B12*B20)/B8 -> 0.30379594 | C59: =(C8-C11-C12-C13-C8*C19-C12*C20)/C8 -> 0.38887765 | D59: =(D8-D11-D12-D13-D8*D19-D12*D20)/D8 -> 0.18428571
A60: BEP — Units to cover Ad Spend | B60: =IF((B8-B11-B12-B13-B8*B19-B12*B20)<=0,"N/A",ROUND(B16/(B8-B11-B12-B13-B8*B19-B12*B20),0)) -> 374 | C60: =IF((C8-C11-C12-C13-C8*C19-C12*C20)<=0,"N/A",ROUND(C16/(C8-C11-C12-C13-C8*C19-C12*C20),0)) -> 268 | D60: =IF((D8-D11-D12-D13-D8*D19-D12*D20)<=0,"N/A",ROUND(D16/(D8-D11-D12-D13-D8*D19-D12*D20),0)) -> 853
A61: Units needed to cover Fixed OH | B61: =IF((B8-B11-B12-B13-B8*B19-B12*B20)<=0,"N/A",CEILING((B16+B24)/(B8-B11-B12-B13-B8*B19-B12*B20),1)) -> 7989 | C61: =IF((C8-C11-C12-C13-C8*C19-C12*C20)<=0,"N/A",CEILING((C16+C24)/(C8-C11-C12-C13-C8*C19-C12*C20),1)) -> 5714 | D61: =IF((D8-D11-D12-D13-D8*D19-D12*D20)<=0,"N/A",CEILING((D16+D24)/(D8-D11-D12-D13-D8*D19-D12*D20),1)) -> 17132
A64: SENSITIVITY TABLE — Net Profit pre-Fixed OH vs Selling Price × Volume (Base Case COGS, Fees, Ad Spend)
A65: ↓ Volume | Price → | B65: ₹130 | C65: ₹140 | D65: ₹150 | E65: ₹155 | F65: ₹160 | G65: ₹170 | H65: ₹180 | I65: ₹200
A66: 700 | B66: -3683 | C66: 2687 | D66: 9056 | E66: 12240 | F66: 15425 | G66: 21794 | H66: 28163 | I66: 40901
A67: 850 | B67: -678 | C67: 7055 | D67: 14789 | E67: 18656 | F67: 22523 | G67: 30257 | H67: 37991 | I67: 53459
A68: 1000 | B68: 2326 | C68: 11424 | D68: 20523 | E68: 25073 | F68: 29622 | G68: 38721 | H68: 47820 | I68: 66017
A69: 1123 | B69: 4789 | C69: 15007 | D69: 25225 | E69: 30334 | F69: 35443 | G69: 45661 | H69: 55879 | I69: 76315
A70: 1300 | B70: 8334 | C70: 20162 | D70: 31991 | E70: 37905 | F70: 43819 | G70: 55648 | H70: 67476 | I70: 91133
A71: 1500 | B71: 12339 | C71: 25988 | D71: 39636 | E71: 46460 | F71: 53284 | G71: 66932 | H71: 80580 | I71: 107877
A72: 1800 | B72: 18348 | C72: 34726 | D72: 51103 | E72: 59292 | F72: 67481 | G72: 83859 | H72: 100237 | I72: 132993

Sheet 📊 FY2627 Actuals
A1: LIIMRA NATURALS | FY 2026-27 | SKU-wise Unit Economics (Projected)
A2: Blue = hardcoded inputs · Black = formulas · Green = cross-sheet links · COGS & per-unit OpEx rates from FY24-25 actuals · Ad Spend total held constant · Gross Units +20%
A4: Section | B4: Metric | C4: Combo 250×3 | D4: Combo 250×6 | E4: Ragi 250g | F4: Bajra 250g | G4: Jowar 250g | H4: Kagni 250g | I4: Kutki 250g | J4: Kodo 250g | K4: Ragi 500g | L4: Jowar 500g | M4: Bajra 500g | N4: Kangni 500g | O4: Kutki 500g | P4: Kodo 500g | Q4: Ragi 1kg | R4: Jowar 1kg | S4: Bajra 1kg | T4: Indrayani | U4: Total / Wtd Avg
A6: ① VOLUME (Full Year Units)
A7: ① Volume | B7: Gross Units Ordered | C7: 868 | D7: 61 | E7: 1 | F7: 1 | G7: 1 | H7: 1 | I7: 1 | J7: 1 | K7: 53 | L7: 16 | M7: 4 | N7: 20 | O7: 7 | P7: 1 | Q7: 1 | R7: 8 | S7: 77 | T7: 1 | U7: 1123
B8: Return Rate (%) | C8: 0.08 | D8: 0.08 | E8: 0.08 | F8: 0.08 | G8: 0.08 | H8: 0.08 | I8: 0.08 | J8: 0.08 | K8: 0.08 | L8: 0.08 | M8: 0.08 | N8: 0.08 | O8: 0.08 | P8: 0.08 | Q8: 0.08 | R8: 0.08 | S8: 0.08 | T8: 0.08 | U8: 0.079252004
B9: Returns (Units) | C9: 69 | D9: 5 | E9: 0 | F9: 0 | G9: 0 | H9: 0 | I9: 0 | J9: 0 | K9: 4 | L9: 1 | M9: 0 | N9: 2 | O9: 1 | P9: 0 | Q9: 0 | R9: 1 | S9: 6 | T9: 0 | U9: 89
B10: Net Units Sold | C10: 799 | D10: 56 | E10: 1 | F10: 1 | G10: 1 | H10: 1 | I10: 1 | J10: 1 | K10: 49 | L10: 15 | M10: 4 | N10: 18 | O10: 6 | P10: 1 | Q10: 1 | R10: 7 | S10: 71 | T10: 1 | U10: 1034
A11: ② REVENUE
A12: ② Revenue | B12: New Selling Price (₹/unit) | C12: 164 | D12: 250 | E12: 87 | F12: 78 | G12: 85 | H12: 71 | I12: 83 | J12: 85 | K12: 71 | L12: 70 | M12: 71 | N12: 88 | O12: 108 | P12: 130 | Q12: 110 | R12: 105 | S12: 102 | T12: 168
B13: Gross Revenue (₹) | C13: 142352 | D13: 15250 | E13: 87 | F13: 78 | G13: 85 | H13: 71 | I13: 83 | J13: 85 | K13: 3763 | L13: 1120 | M13: 284 | N13: 1760 | O13: 756 | P13: 130 | Q13: 110 | R13: 840 | S13: 7854 | T13: 168 | U13: 174876
B14: (−) Returns & Refunds (₹) | C14: 11316 | D14: 1250 | E14: 0 | F14: 0 | G14: 0 | H14: 0 | I14: 0 | J14: 0 | K14: 284 | L14: 70 | M14: 0 | N14: 176 | O14: 108 | P14: 0 | Q14: 0 | R14: 105 | S14: 612 | T14: 0 | U14: 13921
B15: Net Revenue (₹) | C15: 131036 | D15: 14000 | E15: 87 | F15: 78 | G15: 85 | H15: 71 | I15: 83 | J15: 85 | K15: 3479 | L15: 1050 | M15: 284 | N15: 1584 | O15: 648 | P15: 130 | Q15: 110 | R15: 735 | S15: 7242 | T15: 168 | U15: 160955
B16: Net Selling Price (₹/net unit) | C16: 164 | D16: 250 | E16: 87 | F16: 78 | G16: 85 | H16: 71 | I16: 83 | J16: 85 | K16: 71 | L16: 70 | M16: 71 | N16: 88 | O16: 108 | P16: 130 | Q16: 110 | R16: 105 | S16: 102 | T16: 168 | U16: 155.66
A17: ③ COST OF GOODS SOLD
A18: ③ COGS | B18: COGS incl. Packing (₹/unit) | C18: 92.35 | D18: 184.7 | E18: 32.5 | F18: 29.4 | G18: 30.44 | H18: 31.2 | I18: 32.5 | J18: 46.92 | K18: 49.99 | L18: 45.87 | M18: 43.81 | N18: 47.42 | O18: 49.99 | P18: 94 | Q18: 84.98 | R18: 76.74 | S18: 72.62 | T18: 87
B19: Total COGS (₹) | C19: 73787.65 | D19: 10343.2 | E19: 32.5 | F19: 29.4 | G19: 30.44 | H19: 31.2 | I19: 32.5 | J19: 46.92 | K19: 2449.51 | L19: 688.05 | M19: 175.24 | N19: 853.56 | O19: 299.94 | P19: 94 | Q19: 84.98 | R19: 537.18 | S19: 5156.02 | T19: 87 | U19: 94759.29
A20: ④ GROSS PROFIT
A21: ④ GP | B21: Gross Profit (₹) | C21: 57248.35 | D21: 3656.8 | E21: 54.5 | F21: 48.6 | G21: 54.56 | H21: 39.8 | I21: 50.5 | J21: 38.08 | K21: 1029.49 | L21: 361.95 | M21: 108.76 | N21: 730.44 | O21: 348.06 | P21: 36 | Q21: 25.02 | R21: 197.82 | S21: 2085.98 | T21: 81 | U21: 66195.71
B22: Gross Profit per Net Unit (₹) | C22: 71.65 | D22: 65.3 | E22: 54.5 | F22: 48.6 | G22: 54.56 | H22: 39.8 | I22: 50.5 | J22: 38.08 | K22: 21.01 | L22: 24.13 | M22: 27.19 | N22: 40.58 | O22: 58.01 | P22: 36 | Q22: 25.02 | R22: 28.26 | S22: 29.38 | T22: 81 | U22: 64.02
B23: Gross Margin (%) | C23: 0.437 | D23: 0.261 | E23: 0.626 | F23: 0.623 | G23: 0.642 | H23: 0.561 | I23: 0.608 | J23: 0.448 | K23: 0.296 | L23: 0.345 | M23: 0.383 | N23: 0.461 | O23: 0.537 | P23: 0.277 | Q23: 0.227 | R23: 0.269 | S23: 0.288 | T23: 0.482 | U23: 0.411
A24: ⑤ OPERATING EXPENSES
A25: ⑤ OpEx | B25: FK Fixed Fee (₹/net unit) | C25: 9 | D25: 12 | E25: 7 | F25: 7 | G25: 7 | H25: 7 | I25: 7 | J25: 7 | K25: 8 | L25: 8 | M25: 7 | N25: 8 | O25: 9 | P25: 8 | Q25: 8 | R25: 9 | S25: 9 | T25: 9
B26: Total Marketplace Fees (₹) | C26: 7191 | D26: 672 | E26: 7 | F26: 7 | G26: 7 | H26: 7 | I26: 7 | J26: 7 | K26: 392 | L26: 120 | M26: 28 | N26: 144 | O26: 54 | P26: 8 | Q26: 8 | R26: 63 | S26: 639 | T26: 9 | U26: 9370
B27: Reverse Shipping (₹/net unit) | C27: 3.35 | D27: 22.46 | E27: 12.29 | F27: 12.29 | G27: 12.29 | H27: 12.29 | I27: 12.29 | J27: 12.29 | K27: 12.29 | L27: 0 | M27: 0 | N27: 0 | O27: 0 | P27: 0 | Q27: 0 | R27: 0 | S27: 0 | T27: 0
B28: Total Logistics (₹) | C28: 2676.65 | D28: 1257.76 | E28: 12.29 | F28: 12.29 | G28: 12.29 | H28: 12.29 | I28: 12.29 | J28: 12.29 | K28: 602.21 | L28: 0 | M28: 0 | N28: 0 | O28: 0 | P28: 0 | Q28: 0 | R28: 0 | S28: 0 | T28: 0 | U28: 4610.36
B29: Ad Spend Allocated (₹) | C29: 14427.93 | D29: 1541.49 | E29: 8.26 | F29: 8.59 | G29: 9.36 | H29: 7.82 | I29: 9.14 | J29: 9.36 | K29: 383.06 | L29: 115.61 | M29: 31.27 | N29: 174.41 | O29: 71.35 | P29: 14.31 | Q29: 12.11 | R29: 80.93 | S29: 797.39 | T29: 18.5 | U29: 17720.89
B30: TCS (₹/net unit) [1% of NSP] | C30: 1.64 | D30: 2.5 | E30: 0.75 | F30: 0.78 | G30: 0.85 | H30: 0.71 | I30: 0.83 | J30: 0.85 | K30: 0.71 | L30: 0.7 | M30: 0.71 | N30: 0.88 | O30: 1.08 | P30: 1.3 | Q30: 1.1 | R30: 1.05 | S30: 1.02 | T30: 1.68 | U30: 1.56
B31: GST on MP Fees (₹/net unit) [18%] | C31: 1.62 | D31: 2.16 | E31: 1.26 | F31: 1.26 | G31: 1.26 | H31: 1.26 | I31: 1.26 | J31: 1.26 | K31: 1.44 | L31: 1.44 | M31: 1.26 | N31: 1.44 | O31: 1.62 | P31: 1.44 | Q31: 1.44 | R31: 1.62 | S31: 1.62 | T31: 1.62 | U31: 1.63
B32: Total Taxes (₹) | C32: 2604.74 | D32: 260.96 | E32: 2.01 | F32: 2.04 | G32: 2.11 | H32: 1.97 | I32: 2.09 | J32: 2.11 | K32: 105.35 | L32: 32.1 | M32: 7.88 | N32: 41.76 | O32: 16.2 | P32: 2.74 | Q32: 2.54 | R32: 18.69 | S32: 187.44 | T32: 3.3 | U32: 3296.03
B33: ⇒ Total Variable Costs excl. COGS (₹) | C33: 26900.32 | D33: 3732.21 | E33: 29.56 | F33: 29.92 | G33: 30.76 | H33: 29.08 | I33: 30.52 | J33: 30.76 | K33: 1482.62 | L33: 267.71 | M33: 67.15 | N33: 360.17 | O33: 141.55 | P33: 25.05 | Q33: 22.65 | R33: 162.62 | S33: 1623.83 | T33: 30.8 | U33: 34997.28
B34: ⇒ Total Cost incl. COGS (₹) | C34: 100687.97 | D34: 14075.41 | E34: 62.06 | F34: 59.32 | G34: 61.2 | H34: 60.28 | I34: 63.02 | J34: 77.68 | K34: 3932.13 | L34: 955.76 | M34: 242.39 | N34: 1213.73 | O34: 441.49 | P34: 119.05 | Q34: 107.63 | R34: 699.8 | S34: 6779.85 | T34: 117.8 | U34: 129756.57
A35: ⑥ OPERATING PROFIT / (LOSS)
A36: ⑥ Op P&L | B36: Operating Profit / (Loss) (₹) | C36: 30348.03 | D36: -75.41 | E36: 24.94 | F36: 18.68 | G36: 23.8 | H36: 10.72 | I36: 19.98 | J36: 7.32 | K36: -453.13 | L36: 94.24 | M36: 41.61 | N36: 370.27 | O36: 206.51 | P36: 10.95 | Q36: 2.37 | R36: 35.2 | S36: 462.15 | T36: 50.2 | U36: 31198.43
B37: Op Profit per Net Unit (₹) | C37: 37.98 | D37: -1.35 | E37: 24.94 | F37: 18.68 | G37: 23.8 | H37: 10.72 | I37: 19.98 | J37: 7.32 | K37: -9.25 | L37: 6.28 | M37: 10.4 | N37: 20.57 | O37: 34.42 | P37: 10.95 | Q37: 2.37 | R37: 5.03 | S37: 6.51 | T37: 50.2 | U37: 30.17
B38: Operating Margin (%) | C38: 0.232 | D38: -0.005 | E38: 0.287 | F38: 0.239 | G38: 0.28 | H38: 0.151 | I38: 0.241 | J38: 0.086 | K38: -0.13 | L38: 0.09 | M38: 0.147 | N38: 0.234 | O38: 0.319 | P38: 0.084 | Q38: 0.022 | R38: 0.048 | S38: 0.064 | T38: 0.299 | U38: 0.194
A39: ⑦ TDS — Deducted by Flipkart (Recoverable)
A40: ⑦ TDS | B40: TDS (₹) [0.1% on Net Revenue] | C40: 131.04 | D40: 14 | E40: 0.09 | F40: 0.08 | G40: 0.09 | H40: 0.07 | I40: 0.08 | J40: 0.09 | K40: 3.48 | L40: 1.05 | M40: 0.28 | N40: 1.58 | O40: 0.65 | P40: 0.13 | Q40: 0.11 | R40: 0.73 | S40: 7.24 | T40: 0.17 | U40: 160.96
A41: ⑧ NET PROFIT / (LOSS)
A42: ⑧ Net P&L | B42: Net Profit / (Loss) (₹) | C42: 30216.99 | D42: -89.41 | E42: 24.85 | F42: 18.6 | G42: 23.72 | H42: 10.65 | I42: 19.9 | J42: 7.24 | K42: -456.61 | L42: 93.19 | M42: 41.33 | N42: 368.69 | O42: 205.86 | P42: 10.82 | Q42: 2.26 | R42: 34.47 | S42: 454.91 | T42: 50.03 | U42: 31037.48
B43: Net Profit per Net Unit (₹) | C43: 37.82 | D43: -1.6 | E43: 24.85 | F43: 18.6 | G43: 23.72 | H43: 10.65 | I43: 19.9 | J43: 7.24 | K43: -9.32 | L43: 6.21 | M43: 10.33 | N43: 20.48 | O43: 34.31 | P43: 10.82 | Q43: 2.26 | R43: 4.92 | S43: 6.41 | T43: 50.03 | U43: 30.02
B44: Net Margin (%) | C44: 0.231 | D44: -0.006 | E44: 0.286 | F44: 0.238 | G44: 0.279 | H44: 0.15 | I44: 0.24 | J44: 0.085 | K44: -0.131 | L44: 0.089 | M44: 0.146 | N44: 0.233 | O44: 0.318 | P44: 0.083 | Q44: 0.021 | R44: 0.047 | S44: 0.063 | T44: 0.298 | U44: 0.193
A45: ⑨ CONTRIBUTION MARGIN ANALYSIS
A46: ⑨ CM | B46: Contribution per Unit (₹) | C46: 56.04 | D46: 26.18 | E46: 33.2 | F46: 27.27 | G46: 33.16 | H46: 18.54 | I46: 29.12 | J46: 16.68 | K46: -1.43 | L46: 13.99 | M46: 18.22 | N46: 30.26 | O46: 46.31 | P46: 25.26 | Q46: 14.48 | R46: 16.59 | S46: 17.74 | T46: 68.7 | U46: 47.31
B47: Contribution Margin (%) | C47: 0.342 | D47: 0.105 | E47: 0.382 | F47: 0.35 | G47: 0.39 | H47: 0.261 | I47: 0.351 | J47: 0.196 | K47: -0.02 | L47: 0.2 | M47: 0.257 | N47: 0.344 | O47: 0.429 | P47: 0.194 | Q47: 0.132 | R47: 0.158 | S47: 0.174 | T47: 0.409 | U47: 0.304
B48: Break-Even Units (BEP) | C48: 257.5 | D48: 58.9 | E48: 0.2 | F48: 0.3 | G48: 0.3 | H48: 0.4 | I48: 0.3 | J48: 0.6 | K48: N/A | L48: 8.3 | M48: 1.7 | N48: 5.8 | O48: 1.5 | P48: 0.6 | Q48: 0.8 | R48: 4.9 | S48: 44.9 | T48: 0.3
A49: ⑩ BANK SETTLEMENT per Net Unit
A50: ⑩ Settle | B50: Listing Price (₹/unit) | C50: 164 | D50: 250 | E50: 87 | F50: 78 | G50: 85 | H50: 71 | I50: 83 | J50: 85 | K50: 71 | L50: 70 | M50: 71 | N50: 88 | O50: 108 | P50: 130 | Q50: 110 | R50: 105 | S50: 102 | T50: 168
B51: Bank Settlement (₹/net unit) | C51: 151.58 | D51: 233.09 | E51: 77.91 | F51: 68.88 | G51: 75.8 | H51: 61.96 | I51: 73.83 | J51: 75.8 | K51: 60.78 | L51: 59.79 | M51: 61.96 | N51: 77.59 | O51: 96.19 | P51: 119.13 | Q51: 99.35 | R51: 93.22 | S51: 90.26 | T51: 216.53 | U51: 143.32
B52: Memo: Bank Settlement Total (₹) | C52: 121112 | D52: 13053 | E52: 78 | F52: 69 | G52: 76 | H52: 62 | I52: 74 | J52: 76 | K52: 2978 | L52: 897 | M52: 248 | N52: 1397 | O52: 577 | P52: 119 | Q52: 99 | R52: 653 | S52: 6408 | T52: 217 | U52: 148192
B53: Settlement as % of Listing Price | C53: 0.924 | D53: 0.932 | E53: 0.896 | F53: 0.883 | G53: 0.892 | H53: 0.873 | I53: 0.89 | J53: 0.892 | K53: 0.856 | L53: 0.854 | M53: 0.873 | N53: 0.882 | O53: 0.891 | P53: 0.916 | Q53: 0.903 | R53: 0.888 | S53: 0.885 | T53: 1.289 | U53: 0.921
A54: ⑪ FIXED OVERHEADS (Annual allocation, pro-rata by net revenue)
A55: ⑪ Fixed OH | B55: Fixed OH Allocated (₹) | C55: 293410 | D55: 31348 | E55: 168 | F55: 175 | G55: 190 | H55: 159 | I55: 186 | J55: 190 | K55: 7790 | L55: 2351 | M55: 636 | N55: 3547 | O55: 1451 | P55: 291 | Q55: 246 | R55: 1646 | S55: 16216 | T55: 0 | U55: 360000
A56: ⑫ NET PROFIT AFTER FIXED OVERHEADS
A57: ⑫ Post-OH | B57: Net Profit after Fixed OH (₹) | C57: -263192.81 | D57: -31437.57 | E57: -143.09 | F57: -156.05 | G57: -166.62 | H57: -148.33 | I57: -165.95 | J57: -183.09 | K57: -8246.63 | L57: -2257.92 | M57: -594.59 | N57: -3178.13 | O57: -1245.11 | P57: -280.27 | Q57: -244.05 | R57: -1611.31 | S57: -15761.04 | T57: 50.03 | U57: -328962.53
B58: Net Margin after Fixed OH (%) | C58: -2.009 | D58: -2.246 | E58: -1.645 | F58: -2.001 | G58: -1.96 | H58: -2.089 | I58: -1.999 | J58: -2.154 | K58: -2.37 | L58: -2.15 | M58: -2.094 | N58: -2.006 | O58: -1.921 | P58: -2.156 | Q58: -2.219 | R58: -2.192 | S58: -2.176 | T58: 0.298 | U58: -2.044

Sheet 📊 MTD Dashboard
A1: LIIMRA NATURALS | MTD & YTD PERFORMANCE DASHBOARD | FY 2026-27
A2: Current reporting month driven by ⚙ Config sheet cell 'Current Reporting Month'. All metrics auto-populate from 📅 Monthly PvA sheet. Enter actuals there to see live variances here.
A3: =" Reporting Month: "&CHOOSE('⚙ Config & Assumptions'!B41,"April","May","June","July","August","September","October","November","December","January","February","March")&" | FY 2026-27" -> Reporting Month: April | FY 2026-27 | H3: YTD Summary (Apr → Current Month)
A4: Metric | B4: Plan | C4: Actual | D4: Var ₹ | E4: Var % | F4: Status | H4: Metric | I4: Plan | J4: Actual | K4: Var ₹ | L4: Var % | M4: Status
A5: Net Units Sold | B5: ='📅 Monthly PvA'!AX10 -> 72 | C5: ='📅 Monthly PvA'!AY10 | D5: ='📅 Monthly PvA'!AZ10 | E5: ='📅 Monthly PvA'!BA10 | F5: =IF('📅 Monthly PvA'!BA10="","—",IF('📅 Monthly PvA'!BA10>='⚙ Config & Assumptions'!B42,"✔ On/Above",IF('📅 Monthly PvA'!BA10<='⚙ Config & Assumptions'!B43,"✘ Below","~ Near"))) -> — | H5: Net Units Sold | I5: ='📅 Monthly PvA'!BB10 -> 72 | J5: ='📅 Monthly PvA'!BC10 -> 0 | K5: ='📅 Monthly PvA'!BD10 | L5: ='📅 Monthly PvA'!BE10 | M5: =IF('📅 Monthly PvA'!BE10="","—",IF('📅 Monthly PvA'!BE10>='⚙ Config & Assumptions'!B42,"✔ On/Above",IF('📅 Monthly PvA'!BE10<='⚙ Config & Assumptions'!B43,"✘ Below","~ Near"))) -> —
A6: Net Revenue (₹) | B6: ='📅 Monthly PvA'!AX14 -> 11265 | C6: ='📅 Monthly PvA'!AY14 | D6: ='📅 Monthly PvA'!AZ14 | E6: ='📅 Monthly PvA'!BA14 | F6: =IF('📅 Monthly PvA'!BA14="","—",IF('📅 Monthly PvA'!BA14>='⚙ Config & Assumptions'!B42,"✔ On/Above",IF('📅 Monthly PvA'!BA14<='⚙ Config & Assumptions'!B43,"✘ Below","~ Near"))) -> — | H6: Net Revenue (₹) | I6: ='📅 Monthly PvA'!BB14 -> 11265 | J6: ='📅 Monthly PvA'!BC14 -> 0 | K6: ='📅 Monthly PvA'!BD14 | L6: ='📅 Monthly PvA'!BE14 | M6: =IF('📅 Monthly PvA'!BE14="","—",IF('📅 Monthly PvA'!BE14>='⚙ Config & Assumptions'!B42,"✔ On/Above",IF('📅 Monthly PvA'!BE14<='⚙ Config & Assumptions'!B43,"✘ Below","~ Near"))) -> —
A7: Total COGS (₹) | B7: ='📅 Monthly PvA'!AX16 -> 6633 | C7: ='📅 Monthly PvA'!AY16 | D7: ='📅 Monthly PvA'!AZ16 | E7: ='📅 Monthly PvA'!BA16 | F7: =IF('📅 Monthly PvA'!BA16="","—",IF('📅 Monthly PvA'!BA16>='⚙ Config & Assumptions'!B42,"✔ On/Above",IF('📅 Monthly PvA'!BA16<='⚙ Config & Assumptions'!B43,"✘ Below","~ Near"))) -> — | H7: Total COGS (₹) | I7: ='📅 Monthly PvA'!BB16 -> 6633 | J7: ='📅 Monthly PvA'!BC16 -> 0 | K7: ='📅 Monthly PvA'!BD16 | L7: ='📅 Monthly PvA'!BE16 | M7: =IF('📅 Monthly PvA'!BE16="","—",IF('📅 Monthly PvA'!BE16>='⚙ Config & Assumptions'!B42,"✔ On/Above",IF('📅 Monthly PvA'!BE16<='⚙ Config & Assumptions'!B43,"✘ Below","~ Near"))) -> —
A8: Gross Profit (₹) | B8: ='📅 Monthly PvA'!AX18 -> 4631 | C8: ='📅 Monthly PvA'!AY18 | D8: ='📅 Monthly PvA'!AZ18 | E8: ='📅 Monthly PvA'!BA18 | F8: =IF('📅 Monthly PvA'!BA18="","—",IF('📅 Monthly PvA'!BA18>='⚙ Config & Assumptions'!B42,"✔ On/Above",IF('📅 Monthly PvA'!BA18<='⚙ Config & Assumptions'!B43,"✘ Below","~ Near"))) -> — | H8: Gross Profit (₹) | I8: ='📅 Monthly PvA'!BB18 -> 4631 | J8: ='📅 Monthly PvA'!BC18 -> 0 | K8: ='📅 Monthly PvA'!BD18 | L8: ='📅 Monthly PvA'!BE18 | M8: =IF('📅 Monthly PvA'!BE18="","—",IF('📅 Monthly PvA'!BE18>='⚙ Config & Assumptions'!B42,"✔ On/Above",IF('📅 Monthly PvA'!BE18<='⚙ Config & Assumptions'!B43,"✘ Below","~ Near"))) -> —
A9: Gross Margin (%) | B9: ='📅 Monthly PvA'!AX19 -> 0.41109632 | C9: ='📅 Monthly PvA'!AY19 | D9: ='📅 Monthly PvA'!AZ19 | E9: ='📅 Monthly PvA'!BA19 | F9: =IF('📅 Monthly PvA'!BA19="","—",IF('📅 Monthly PvA'!BA19>='⚙ Config & Assumptions'!B42,"✔ On/Above",IF('📅 Monthly PvA'!BA19<='⚙ Config & Assumptions'!B43,"✘ Below","~ Near"))) -> — | H9: Gross Margin (%) | I9: ='📅 Monthly PvA'!BB19 -> 0.41109632 | J9: ='📅 Monthly PvA'!BC19 -> 0 | K9: ='📅 Monthly PvA'!BD19 | L9: ='📅 Monthly PvA'!BE19 | M9: =IF('📅 Monthly PvA'!BE19="","—",IF('📅 Monthly PvA'!BE19>='⚙ Config & Assumptions'!B42,"✔ On/Above",IF('📅 Monthly PvA'!BE19<='⚙ Config & Assumptions'!B43,"✘ Below","~ Near"))) -> —
A10: Ad Spend (₹) | B10: ='📅 Monthly PvA'!AX23 -> 1475 | C10: ='📅 Monthly PvA'!AY23 | D10: ='📅 Monthly PvA'!AZ23 | E10: ='📅 Monthly PvA'!BA23 | F10: =IF('📅 Monthly PvA'!BA23="","—",IF('📅 Monthly PvA'!BA23>='⚙ Config & Assumptions'!B42,"✔ On/Above",IF('📅 Monthly PvA'!BA23<='⚙ Config & Assumptions'!B43,"✘ Below","~ Near"))) -> — | H10: Ad Spend (₹) | I10: ='📅 Monthly PvA'!BB23 -> 1475 | J10: ='📅 Monthly PvA'!BC23 -> 0 | K10: ='📅 Monthly PvA'!BD23 | L10: ='📅 Monthly PvA'!BE23 | M10: =IF('📅 Monthly PvA'!BE23="","—",IF('📅 Monthly PvA'!BE23>='⚙ Config & Assumptions'!B42,"✔ On/Above",IF('📅 Monthly PvA'!BE23<='⚙ Config & Assumptions'!B43,"✘ Below","~ Near"))) -> —
A11: Operating Profit / (Loss) (₹) | B11: ='📅 Monthly PvA'!AX27 -> 1946 | C11: ='📅 Monthly PvA'!AY27 | D11: ='📅 Monthly PvA'!AZ27 | E11: ='📅 Monthly PvA'!BA27 | F11: =IF('📅 Monthly PvA'!BA27="","—",IF('📅 Monthly PvA'!BA27>='⚙ Config & Assumptions'!B42,"✔ On/Above",IF('📅 Monthly PvA'!BA27<='⚙ Config & Assumptions'!B43,"✘ Below","~ Near"))) -> — | H11: Operating Profit / (Loss) (₹) | I11: ='📅 Monthly PvA'!BB27 -> 1946 | J11: ='📅 Monthly PvA'!BC27 -> 0 | K11: ='📅 Monthly PvA'!BD27 | L11: ='📅 Monthly PvA'!BE27 | M11: =IF('📅 Monthly PvA'!BE27="","—",IF('📅 Monthly PvA'!BE27>='⚙ Config & Assumptions'!B42,"✔ On/Above",IF('📅 Monthly PvA'!BE27<='⚙ Config & Assumptions'!B43,"✘ Below","~ Near"))) -> —
A12: Operating Margin (%) | B12: ='📅 Monthly PvA'!AX28 -> 0.17274745 | C12: ='📅 Monthly PvA'!AY28 | D12: ='📅 Monthly PvA'!AZ28 | E12: ='📅 Monthly PvA'!BA28 | F12: =IF('📅 Monthly PvA'!BA28="","—",IF('📅 Monthly PvA'!BA28>='⚙ Config & Assumptions'!B42,"✔ On/Above",IF('📅 Monthly PvA'!BA28<='⚙ Config & Assumptions'!B43,"✘ Below","~ Near"))) -> — | H12: Operating Margin (%) | I12: ='📅 Monthly PvA'!BB28 -> 0.17274745 | J12: ='📅 Monthly PvA'!BC28 -> 0 | K12: ='📅 Monthly PvA'!BD28 | L12: ='📅 Monthly PvA'!BE28 | M12: =IF('📅 Monthly PvA'!BE28="","—",IF('📅 Monthly PvA'!BE28>='⚙ Config & Assumptions'!B42,"✔ On/Above",IF('📅 Monthly PvA'!BE28<='⚙ Config & Assumptions'!B43,"✘ Below","~ Near"))) -> —
A13: Net Profit / (Loss) (₹) | B13: ='📅 Monthly PvA'!AX32 -> 1935 | C13: ='📅 Monthly PvA'!AY32 | D13: ='📅 Monthly PvA'!AZ32 | E13: ='📅 Monthly PvA'!BA32 | F13: =IF('📅 Monthly PvA'!BA32="","—",IF('📅 Monthly PvA'!BA32>='⚙ Config & Assumptions'!B42,"✔ On/Above",IF('📅 Monthly PvA'!BA32<='⚙ Config & Assumptions'!B43,"✘ Below","~ Near"))) -> — | H13: Net Profit / (Loss) (₹) | I13: ='📅 Monthly PvA'!BB32 -> 1935 | J13: ='📅 Monthly PvA'!BC32 -> 0 | K13: ='📅 Monthly PvA'!BD32 | L13: ='📅 Monthly PvA'!BE32 | M13: =IF('📅 Monthly PvA'!BE32="","—",IF('📅 Monthly PvA'!BE32>='⚙ Config & Assumptions'!B42,"✔ On/Above",IF('📅 Monthly PvA'!BE32<='⚙ Config & Assumptions'!B43,"✘ Below","~ Near"))) -> —
A14: Net Margin (%) | B14: ='📅 Monthly PvA'!AX33 -> 0.17177097 | C14: ='📅 Monthly PvA'!AY33 | D14: ='📅 Monthly PvA'!AZ33 | E14: ='📅 Monthly PvA'!BA33 | F14: =IF('📅 Monthly PvA'!BA33="","—",IF('📅 Monthly PvA'!BA33>='⚙ Config & Assumptions'!B42,"✔ On/Above",IF('📅 Monthly PvA'!BA33<='⚙ Config & Assumptions'!B43,"✘ Below","~ Near"))) -> — | H14: Net Margin (%) | I14: ='📅 Monthly PvA'!BB33 -> 0.17177097 | J14: ='📅 Monthly PvA'!BC33 -> 0 | K14: ='📅 Monthly PvA'!BD33 | L14: ='📅 Monthly PvA'!BE33 | M14: =IF('📅 Monthly PvA'!BE33="","—",IF('📅 Monthly PvA'!BE33>='⚙ Config & Assumptions'!B42,"✔ On/Above",IF('📅 Monthly PvA'!BE33<='⚙ Config & Assumptions'!B43,"✘ Below","~ Near"))) -> —
A15: Fixed Overheads (₹) | B15: ='📅 Monthly PvA'!AX35 -> 0 | C15: ='📅 Monthly PvA'!AY35 | D15: ='📅 Monthly PvA'!AZ35 | E15: ='📅 Monthly PvA'!BA35 | F15: =IF('📅 Monthly PvA'!BA35="","—",IF('📅 Monthly PvA'!BA35>='⚙ Config & Assumptions'!B42,"✔ On/Above",IF('📅 Monthly PvA'!BA35<='⚙ Config & Assumptions'!B43,"✘ Below","~ Near"))) -> — | H15: Fixed Overheads (₹) | I15: ='📅 Monthly PvA'!BB35 -> 0 | J15: ='📅 Monthly PvA'!BC35 -> 0 | K15: ='📅 Monthly PvA'!BD35 | L15: ='📅 Monthly PvA'!BE35 | M15: =IF('📅 Monthly PvA'!BE35="","—",IF('📅 Monthly PvA'!BE35>='⚙ Config & Assumptions'!B42,"✔ On/Above",IF('📅 Monthly PvA'!BE35<='⚙ Config & Assumptions'!B43,"✘ Below","~ Near"))) -> —
A16: Net Profit after Fixed OH (₹) | B16: ='📅 Monthly PvA'!AX36 -> 1935 | C16: ='📅 Monthly PvA'!AY36 | D16: ='📅 Monthly PvA'!AZ36 | E16: ='📅 Monthly PvA'!BA36 | F16: =IF('📅 Monthly PvA'!BA36="","—",IF('📅 Monthly PvA'!BA36>='⚙ Config & Assumptions'!B42,"✔ On/Above",IF('📅 Monthly PvA'!BA36<='⚙ Config & Assumptions'!B43,"✘ Below","~ Near"))) -> — | H16: Net Profit after Fixed OH (₹) | I16: ='📅 Monthly PvA'!BB36 -> 1935 | J16: ='📅 Monthly PvA'!BC36 -> 0 | K16: ='📅 Monthly PvA'!BD36 | L16: ='📅 Monthly PvA'!BE36 | M16: =IF('📅 Monthly PvA'!BE36="","—",IF('📅 Monthly PvA'!BE36>='⚙ Config & Assumptions'!B42,"✔ On/Above",IF('📅 Monthly PvA'!BE36<='⚙ Config & Assumptions'!B43,"✘ Below","~ Near"))) -> —
A17: Contribution per Unit (₹) | B17: ='📅 Monthly PvA'!AX39 -> 47.2828 | C17: ='📅 Monthly PvA'!AY39 | D17: ='📅 Monthly PvA'!AZ39 | E17: ='📅 Monthly PvA'!BA39 | F17: =IF('📅 Monthly PvA'!BA39="","—",IF('📅 Monthly PvA'!BA39>='⚙ Config & Assumptions'!B42,"✔ On/Above",IF('📅 Monthly PvA'!BA39<='⚙ Config & Assumptions'!B43,"✘ Below","~ Near"))) -> — | H17: Contribution per Unit (₹) | I17: ='📅 Monthly PvA'!BB39 -> 47.2828 | J17: ='📅 Monthly PvA'!BC39 -> 0 | K17: ='📅 Monthly PvA'!BD39 | L17: ='📅 Monthly PvA'!BE39 | M17: =IF('📅 Monthly PvA'!BE39="","—",IF('📅 Monthly PvA'!BE39>='⚙ Config & Assumptions'!B42,"✔ On/Above",IF('📅 Monthly PvA'!BE39<='⚙ Config & Assumptions'!B43,"✘ Below","~ Near"))) -> —
A18: Bank Settlement (₹) — Estimated | B18: ='📅 Monthly PvA'!AX42 -> 10367 | C18: ='📅 Monthly PvA'!AY42 | D18: ='📅 Monthly PvA'!AZ42 | E18: ='📅 Monthly PvA'!BA42 | F18: =IF('📅 Monthly PvA'!BA42="","—",IF('📅 Monthly PvA'!BA42>='⚙ Config & Assumptions'!B42,"✔ On/Above",IF('📅 Monthly PvA'!BA42<='⚙ Config & Assumptions'!B43,"✘ Below","~ Near"))) -> — | H18: Bank Settlement (₹) — Estimated | I18: ='📅 Monthly PvA'!BB42 -> 10367 | J18: ='📅 Monthly PvA'!BC42 -> 0 | K18: ='📅 Monthly PvA'!BD42 | L18: ='📅 Monthly PvA'!BE42 | M18: =IF('📅 Monthly PvA'!BE42="","—",IF('📅 Monthly PvA'!BE42>='⚙ Config & Assumptions'!B42,"✔ On/Above",IF('📅 Monthly PvA'!BE42<='⚙ Config & Assumptions'!B43,"✘ Below","~ Near"))) -> —

Sheet 📅 Monthly PvA
A1: LIIMRA NATURALS | MONTHLY PLAN vs ACTUAL | FY 2026-27 (Apr 2026 – Mar 2027)
A2: Plan = seasonality-weighted annual targets from ⚙ Config sheet · Actual = enter monthly data in GREEN cells · Variance = Actual − Plan · MTD & YTD driven by current reporting month in Config
A3: Metric | B3: April | F3: May | J3: June | N3: July | R3: August | V3: September | Z3: October | AD3: November | AH3: December | AL3: January | AP3: February | AT3: March | AX3: ◆ MTD | BB3: ◆ YTD
A4: Section / Metric | B4: Plan | C4: Actual | D4: Var ₹ | E4: Var % | F4: Plan | G4: Actual | H4: Var ₹ | I4: Var % | J4: Plan | K4: Actual | L4: Var ₹ | M4: Var % | N4: Plan | O4: Actual | P4: Var ₹ | Q4: Var % | R4: Plan | S4: Actual | T4: Var ₹ | U4: Var % | V4: Plan | W4: Actual | X4: Var ₹ | Y4: Var % | Z4: Plan | AA4: Actual | AB4: Var ₹ | AC4: Var % | AD4: Plan | AE4: Actual | AF4: Var ₹ | AG4: Var % | AH4: Plan | AI4: Actual | AJ4: Var ₹ | AK4: Var % | AL4: Plan | AM4: Actual | AN4: Var ₹ | AO4: Var % | AP4: Plan | AQ4: Actual | AR4: Var ₹ | AS4: Var % | AT4: Plan | AU4: Actual | AV4: Var ₹ | AW4: Var % | AX4: Plan | AY4: Actual | AZ4: Var ₹ | BA4: Var % | BB4: Plan | BC4: Actual | BD4: Var ₹ | BE4: Var %
A6: ① VOLUME
A7: Gross Units (Plan) | B7: =ROUND('⚙ Config & Assumptions'!B5*'⚙ Config & Assumptions'!B7,0) -> 79 | D7: =IF(C7="","",C7-B7) | E7: =IF(OR(C7="",B7=0),"",(C7-B7)/B7) | F7: =ROUND('⚙ Config & Assumptions'!B5*'⚙ Config & Assumptions'!B8,0) -> 84 | H7: =IF(G7="","",G7-F7) | I7: =IF(OR(G7="",F7=0),"",(G7-F7)/F7) | J7: =ROUND('⚙ Config & Assumptions'!B5*'⚙ Config & Assumptions'!B9,0) -> 73 | L7: =IF(K7="","",K7-J7) | M7: =IF(OR(K7="",J7=0),"",(K7-J7)/J7) | N7: =ROUND('⚙ Config & Assumptions'!B5*'⚙ Config & Assumptions'!B10,0) -> 84 | P7: =IF(O7="","",O7-N7) | Q7: =IF(OR(O7="",N7=0),"",(O7-N7)/N7) | R7: =ROUND('⚙ Config & Assumptions'!B5*'⚙ Config & Assumptions'!B11,0) -> 101 | T7: =IF(S7="","",S7-R7) | U7: =IF(OR(S7="",R7=0),"",(S7-R7)/R7) | V7: =ROUND('⚙ Config & Assumptions'!B5*'⚙ Config & Assumptions'!B12,0) -> 107 | X7: =IF(W7="","",W7-V7) | Y7: =IF(OR(W7="",V7=0),"",(W7-V7)/V7) | Z7: =ROUND('⚙ Config & Assumptions'!B5*'⚙ Config & Assumptions'!B13,0) -> 112 | AB7: =IF(AA7="","",AA7-Z7) | AC7: =IF(OR(AA7="",Z7=0),"",(AA7-Z7)/Z7) | AD7: =ROUND('⚙ Config & Assumptions'!B5*'⚙ Config & Assumptions'!B14,0) -> 107 | AF7: =IF(AE7="","",AE7-AD7) | AG7: =IF(OR(AE7="",AD7=0),"",(AE7-AD7)/AD7) | AH7: =ROUND('⚙ Config & Assumptions'!B5*'⚙ Config & Assumptions'!B15,0) -> 101 | AJ7: =IF(AI7="","",AI7-AH7) | AK7: =IF(OR(AI7="",AH7=0),"",(AI7-AH7)/AH7) | AL7: =ROUND('⚙ Config & Assumptions'!B5*'⚙ Config & Assumptions'!B16,0) -> 101 | AN7: =IF(AM7="","",AM7-AL7) | AO7: =IF(OR(AM7="",AL7=0),"",(AM7-AL7)/AL7) | AP7: =ROUND('⚙ Config & Assumptions'!B5*'⚙ Config & Assumptions'!B17,0) -> 95 | AR7: =IF(AQ7="","",AQ7-AP7) | AS7: =IF(OR(AQ7="",AP7=0),"",(AQ7-AP7)/AP7) | AT7: =ROUND('⚙ Config & Assumptions'!B5*'⚙ Config & Assumptions'!B18,0) -> 79 | AV7: =IF(AU7="","",AU7-AT7) | AW7: =IF(OR(AU7="",AT7=0),"",(AU7-AT7)/AT7) | AX7: =CHOOSE('⚙ Config & Assumptions'!B41,B7,F7,J7,N7,R7,V7,Z7,AD7,AH7,AL7,AP7,AT7) -> 79 | AY7: =IF(CHOOSE('⚙ Config & Assumptions'!B41,C7,G7,K7,O7,S7,W7,AA7,AE7,AI7,AM7,AQ7,AU7)="","",CHOOSE('⚙ Config & Assumptions'!B41,C7,G7,K7,O7,S7,W7,AA7,AE7,AI7,AM7,AQ7,AU7)) | AZ7: =IF(AY7="","",AY7-AX7) | BA7: =IF(OR(AY7="",AX7=0),"",(AY7-AX7)/AX7) | BB7: =IF('⚙ Config & Assumptions'!B41>=1,B7,0)+IF('⚙ Config & Assumptions'!B41>=2,F7,0)+IF('⚙ Config & Assumptions'!B41>=3,J7,0)+IF('⚙ Config & Assumptions'!B41>=4,N7,0)+IF('⚙ Config & Assumptions'!B41>=5,R7,0)+IF('⚙ Config & Assumptions'!B41>=6,V7,0)+IF('⚙ Config & Assumptions'!B41>=7,Z7,0)+IF('⚙ Config & Assumptions'!B41>=8,AD7,0)+IF('⚙ Config & Assumptions'!B41>=9,AH7,0)+IF('⚙ Config & Assumptions'!B41>=10,AL7,0)+IF('⚙ Config & Assumptions'!B41>=11,AP7,0)+IF('⚙ Config & Assumptions'!B41>=12,AT7,0) -> 79 | BC7: =IF(AND('⚙ Config & Assumptions'!B41>=1,C7<>""),C7,0)+IF(AND('⚙ Config & Assumptions'!B41>=2,G7<>""),G7,0)+IF(AND('⚙ Config & Assumptions'!B41>=3,K7<>""),K7,0)+IF(AND('⚙ Config & Assumptions'!B41>=4,O7<>""),O7,0)+IF(AND('⚙ Config & Assumptions'!B41>=5,S7<>""),S7,0)+IF(AND('⚙ Config & Assumptions'!B41>=6,W7<>""),W7,0)+IF(AND('⚙ Config & Assumptions'!B41>=7,AA7<>""),AA7,0)+IF(AND('⚙ Config & Assumptions'!B41>=8,AE7<>""),AE7,0)+IF(AND('⚙ Config & Assumptions'!B41>=9,AI7<>""),AI7,0)+IF(AND('⚙ Config & Assumptions'!B41>=10,AM7<>""),AM7,0)+IF(AND('⚙ Config & Assumptions'!B41>=11,AQ7<>""),AQ7,0)+IF(AND('⚙ Config & Assumptions'!B41>=12,AU7<>""),AU7,0) -> 0 | BD7: =IF(BC7=0,"",BC7-BB7) | BE7: =IF(OR(BC7=0,BB7=0),"",(BC7-BB7)/BB7)
A8: Return Rate (%) | B8: ='⚙ Config & Assumptions'!B22 -> 0.0793 | D8: =IF(C8="","",C8-B8) | E8: =IF(OR(C8="",B8=0),"",(C8-B8)/B8) | F8: ='⚙ Config & Assumptions'!B22 -> 0.0793 | H8: =IF(G8="","",G8-F8) | I8: =IF(OR(G8="",F8=0),"",(G8-F8)/F8) | J8: ='⚙ Config & Assumptions'!B22 -> 0.0793 | L8: =IF(K8="","",K8-J8) | M8: =IF(OR(K8="",J8=0),"",(K8-J8)/J8) | N8: ='⚙ Config & Assumptions'!B22 -> 0.0793 | P8: =IF(O8="","",O8-N8) | Q8: =IF(OR(O8="",N8=0),"",(O8-N8)/N8) | R8: ='⚙ Config & Assumptions'!B22 -> 0.0793 | T8: =IF(S8="","",S8-R8) | U8: =IF(OR(S8="",R8=0),"",(S8-R8)/R8) | V8: ='⚙ Config & Assumptions'!B22 -> 0.0793 | X8: =IF(W8="","",W8-V8) | Y8: =IF(OR(W8="",V8=0),"",(W8-V8)/V8) | Z8: ='⚙ Config & Assumptions'!B22 -> 0.0793 | AB8: =IF(AA8="","",AA8-Z8) | AC8: =IF(OR(AA8="",Z8=0),"",(AA8-Z8)/Z8) | AD8: ='⚙ Config & Assumptions'!B22 -> 0.0793 | AF8: =IF(AE8="","",AE8-AD8) | AG8: =IF(OR(AE8="",AD8=0),"",(AE8-AD8)/AD8) | AH8: ='⚙ Config & Assumptions'!B22 -> 0.0793 | AJ8: =IF(AI8="","",AI8-AH8) | AK8: =IF(OR(AI8="",AH8=0),"",(AI8-AH8)/AH8) | AL8: ='⚙ Config & Assumptions'!B22 -> 0.0793 | AN8: =IF(AM8="","",AM8-AL8) | AO8: =IF(OR(AM8="",AL8=0),"",(AM8-AL8)/AL8) | AP8: ='⚙ Config & Assumptions'!B22 -> 0.0793 | AR8: =IF(AQ8="","",AQ8-AP8) | AS8: =IF(OR(AQ8="",AP8=0),"",(AQ8-AP8)/AP8) | AT8: ='⚙ Config & Assumptions'!B22 -> 0.0793 | AV8: =IF(AU8="","",AU8-AT8) | AW8: =IF(OR(AU8="",AT8=0),"",(AU8-AT8)/AT8) | AX8: =CHOOSE('⚙ Config & Assumptions'!B41,B8,F8,J8,N8,R8,V8,Z8,AD8,AH8,AL8,AP8,AT8) -> 0.0793 | AY8: =IF(CHOOSE('⚙ Config & Assumptions'!B41,C8,G8,K8,O8,S8,W8,AA8,AE8,AI8,AM8,AQ8,AU8)="","",CHOOSE('⚙ Config & Assumptions'!B41,C8,G8,K8,O8,S8,W8,AA8,AE8,AI8,AM8,AQ8,AU8)) | AZ8: =IF(AY8="","",AY8-AX8) | BA8: =IF(OR(AY8="",AX8=0),"",(AY8-AX8)/AX8) | BB8: =IF('⚙ Config & Assumptions'!B41>=1,B8,0)+IF('⚙ Config & Assumptions'!B41>=2,F8,0)+IF('⚙ Config & Assumptions'!B41>=3,J8,0)+IF('⚙ Config & Assumptions'!B41>=4,N8,0)+IF('⚙ Config & Assumptions'!B41>=5,R8,0)+IF('⚙ Config & Assumptions'!B41>=6,V8,0)+IF('⚙ Config & Assumptions'!B41>=7,Z8,0)+IF('⚙ Config & Assumptions'!B41>=8,AD8,0)+IF('⚙ Config & Assumptions'!B41>=9,AH8,0)+IF('⚙ Config & Assumptions'!B41>=10,AL8,0)+IF('⚙ Config & Assumptions'!B41>=11,AP8,0)+IF('⚙ Config & Assumptions'!B41>=12,AT8,0) -> 0.0793 | BC8: =IF(AND('⚙ Config & Assumptions'!B41>=1,C8<>""),C8,0)+IF(AND('⚙ Config & Assumptions'!B41>=2,G8<>""),G8,0)+IF(AND('⚙ Config & Assumptions'!B41>=3,K8<>""),K8,0)+IF(AND('⚙ Config & Assumptions'!B41>=4,O8<>""),O8,0)+IF(AND('⚙ Config & Assumptions'!B41>=5,S8<>""),S8,0)+IF(AND('⚙ Config & Assumptions'!B41>=6,W8<>""),W8,0)+IF(AND('⚙ Config & Assumptions'!B41>=7,AA8<>""),AA8,0)+IF(AND('⚙ Config & Assumptions'!B41>=8,AE8<>""),AE8,0)+IF(AND('⚙ Config & Assumptions'!B41>=9,AI8<>""),AI8,0)+IF(AND('⚙ Config & Assumptions'!B41>=10,AM8<>""),AM8,0)+IF(AND('⚙ Config & Assumptions'!B41>=11,AQ8<>""),AQ8,0)+IF(AND('⚙ Config & Assumptions'!B41>=12,AU8<>""),AU8,0) -> 0 | BD8: =IF(BC8=0,"",BC8-BB8) | BE8: =IF(OR(BC8=0,BB8=0),"",(BC8-BB8)/BB8)
A9: Returns (Units) | B9: =ROUND('⚙ Config & Assumptions'!B5*'⚙ Config & Assumptions'!B7*'⚙ Config & Assumptions'!B22,0) -> 6 | D9: =IF(C9="","",C9-B9) | E9: =IF(OR(C9="",B9=0),"",(C9-B9)/B9) | F9: =ROUND('⚙ Config & Assumptions'!B5*'⚙ Config & Assumptions'!B8*'⚙ Config & Assumptions'!B22,0) -> 7 | H9: =IF(G9="","",G9-F9) | I9: =IF(OR(G9="",F9=0),"",(G9-F9)/F9) | J9: =ROUND('⚙ Config & Assumptions'!B5*'⚙ Config & Assumptions'!B9*'⚙ Config & Assumptions'!B22,0) -> 6 | L9: =IF(K9="","",K9-J9) | M9: =IF(OR(K9="",J9=0),"",(K9-J9)/J9) | N9: =ROUND('⚙ Config & Assumptions'!B5*'⚙ Config & Assumptions'!B10*'⚙ Config & Assumptions'!B22,0) -> 7 | P9: =IF(O9="","",O9-N9) | Q9: =IF(OR(O9="",N9=0),"",(O9-N9)/N9) | R9: =ROUND('⚙ Config & Assumptions'!B5*'⚙ Config & Assumptions'!B11*'⚙ Config & Assumptions'!B22,0) -> 8 | T9: =IF(S9="","",S9-R9) | U9: =IF(OR(S9="",R9=0),"",(S9-R9)/R9) | V9: =ROUND('⚙ Config & Assumptions'!B5*'⚙ Config & Assumptions'!B12*'⚙ Config & Assumptions'!B22,0) -> 8 | X9: =IF(W9="","",W9-V9) | Y9: =IF(OR(W9="",V9=0),"",(W9-V9)/V9) | Z9: =ROUND('⚙ Config & Assumptions'!B5*'⚙ Config & Assumptions'!B13*'⚙ Config & Assumptions'!B22,0) -> 9 | AB9: =IF(AA9="","",AA9-Z9) | AC9: =IF(OR(AA9="",Z9=0),"",(AA9-Z9)/Z9) | AD9: =ROUND('⚙ Config & Assumptions'!B5*'⚙ Config & Assumptions'!B14*'⚙ Config & Assumptions'!B22,0) -> 8 | AF9: =IF(AE9="","",AE9-AD9) | AG9: =IF(OR(AE9="",AD9=0),"",(AE9-AD9)/AD9) | AH9: =ROUND('⚙ Config & Assumptions'!B5*'⚙ Config & Assumptions'!B15*'⚙ Config & Assumptions'!B22,0) -> 8 | AJ9: =IF(AI9="","",AI9-AH9) | AK9: =IF(OR(AI9="",AH9=0),"",(AI9-AH9)/AH9) | AL9: =ROUND('⚙ Config & Assumptions'!B5*'⚙ Config & Assumptions'!B16*'⚙ Config & Assumptions'!B22,0) -> 8 | AN9: =IF(AM9="","",AM9-AL9) | AO9: =IF(OR(AM9="",AL9=0),"",(AM9-AL9)/AL9) | AP9: =ROUND('⚙ Config & Assumptions'!B5*'⚙ Config & Assumptions'!B17*'⚙ Config & Assumptions'!B22,0) -> 8 | AR9: =IF(AQ9="","",AQ9-AP9) | AS9: =IF(OR(AQ9="",AP9=0),"",(AQ9-AP9)/AP9) | AT9: =ROUND('⚙ Config & Assumptions'!B5*'⚙ Config & Assumptions'!B18*'⚙ Config & Assumptions'!B22,0) -> 6 | AV9: =IF(AU9="","",AU9-AT9) | AW9: =IF(OR(AU9="",AT9=0),"",(AU9-AT9)/AT9) | AX9: =CHOOSE('⚙ Config & Assumptions'!B41,B9,F9,J9,N9,R9,V9,Z9,AD9,AH9,AL9,AP9,AT9) -> 6 | AY9: =IF(CHOOSE('⚙ Config & Assumptions'!B41,C9,G9,K9,O9,S9,W9,AA9,AE9,AI9,AM9,AQ9,AU9)="","",CHOOSE('⚙ Config & Assumptions'!B41,C9,G9,K9,O9,S9,W9,AA9,AE9,AI9,AM9,AQ9,AU9)) | AZ9: =IF(AY9="","",AY9-AX9) | BA9: =IF(OR(AY9="",AX9=0),"",(AY9-AX9)/AX9) | BB9: =IF('⚙ Config & Assumptions'!B41>=1,B9,0)+IF('⚙ Config & Assumptions'!B41>=2,F9,0)+IF('⚙ Config & Assumptions'!B41>=3,J9,0)+IF('⚙ Config & Assumptions'!B41>=4,N9,0)+IF('⚙ Config & Assumptions'!B41>=5,R9,0)+IF('⚙ Config & Assumptions'!B41>=6,V9,0)+IF('⚙ Config & Assumptions'!B41>=7,Z9,0)+IF('⚙ Config & Assumptions'!B41>=8,AD9,0)+IF('⚙ Config & Assumptions'!B41>=9,AH9,0)+IF('⚙ Config & Assumptions'!B41>=10,AL9,0)+IF('⚙ Config & Assumptions'!B41>=11,AP9,0)+IF('⚙ Config & Assumptions'!B41>=12,AT9,0) -> 6 | BC9: =IF(AND('⚙ Config & Assumptions'!B41>=1,C9<>""),C9,0)+IF(AND('⚙ Config & Assumptions'!B41>=2,G9<>""),G9,0)+IF(AND('⚙ Config & Assumptions'!B41>=3,K9<>""),K9,0)+IF(AND('⚙ Config & Assumptions'!B41>=4,O9<>""),O9,0)+IF(AND('⚙ Config & Assumptions'!B41>=5,S9<>""),S9,0)+IF(AND('⚙ Config & Assumptions'!B41>=6,W9<>""),W9,0)+IF(AND('⚙ Config & Assumptions'!B41>=7,AA9<>""),AA9,0)+IF(AND('⚙ Config & Assumptions'!B41>=8,AE9<>""),AE9,0)+IF(AND('⚙ Config & Assumptions'!B41>=9,AI9<>""),AI9,0)+IF(AND('⚙ Config & Assumptions'!B41>=10,AM9<>""),AM9,0)+IF(AND('⚙ Config & Assumptions'!B41>=11,AQ9<>""),AQ9,0)+IF(AND('⚙ Config & Assumptions'!B41>=12,AU9<>""),AU9,0) -> 0 | BD9: =IF(BC9=0,"",BC9-BB9) | BE9: =IF(OR(BC9=0,BB9=0),"",(BC9-BB9)/BB9)
A10: ⇒ Net Units Sold | B10: =ROUND('⚙ Config & Assumptions'!B5*'⚙ Config & Assumptions'!B7*(1-'⚙ Config & Assumptions'!B22),0) -> 72 | D10: =IF(C10="","",C10-B10) | E10: =IF(OR(C10="",B10=0),"",(C10-B10)/B10) | F10: =ROUND('⚙ Config & Assumptions'!B5*'⚙ Config & Assumptions'!B8*(1-'⚙ Config & Assumptions'!B22),0) -> 78 | H10: =IF(G10="","",G10-F10) | I10: =IF(OR(G10="",F10=0),"",(G10-F10)/F10) | J10: =ROUND('⚙ Config & Assumptions'!B5*'⚙ Config & Assumptions'!B9*(1-'⚙ Config & Assumptions'!B22),0) -> 67 | L10: =IF(K10="","",K10-J10) | M10: =IF(OR(K10="",J10=0),"",(K10-J10)/J10) | N10: =ROUND('⚙ Config & Assumptions'!B5*'⚙ Config & Assumptions'!B10*(1-'⚙ Config & Assumptions'!B22),0) -> 78 | P10: =IF(O10="","",O10-N10) | Q10: =IF(OR(O10="",N10=0),"",(O10-N10)/N10) | R10: =ROUND('⚙ Config & Assumptions'!B5*'⚙ Config & Assumptions'!B11*(1-'⚙ Config & Assumptions'!B22),0) -> 93 | T10: =IF(S10="","",S10-R10) | U10: =IF(OR(S10="",R10=0),"",(S10-R10)/R10) | V10: =ROUND('⚙ Config & Assumptions'!B5*'⚙ Config & Assumptions'!B12*(1-'⚙ Config & Assumptions'!B22),0) -> 98 | X10: =IF(W10="","",W10-V10) | Y10: =IF(OR(W10="",V10=0),"",(W10-V10)/V10) | Z10: =ROUND('⚙ Config & Assumptions'!B5*'⚙ Config & Assumptions'!B13*(1-'⚙ Config & Assumptions'!B22),0) -> 103 | AB10: =IF(AA10="","",AA10-Z10) | AC10: =IF(OR(AA10="",Z10=0),"",(AA10-Z10)/Z10) | AD10: =ROUND('⚙ Config & Assumptions'!B5*'⚙ Config & Assumptions'!B14*(1-'⚙ Config & Assumptions'!B22),0) -> 98 | AF10: =IF(AE10="","",AE10-AD10) | AG10: =IF(OR(AE10="",AD10=0),"",(AE10-AD10)/AD10) | AH10: =ROUND('⚙ Config & Assumptions'!B5*'⚙ Config & Assumptions'!B15*(1-'⚙ Config & Assumptions'!B22),0) -> 93 | AJ10: =IF(AI10="","",AI10-AH10) | AK10: =IF(OR(AI10="",AH10=0),"",(AI10-AH10)/AH10) | AL10: =ROUND('⚙ Config & Assumptions'!B5*'⚙ Config & Assumptions'!B16*(1-'⚙ Config & Assumptions'!B22),0) -> 93 | AN10: =IF(AM10="","",AM10-AL10) | AO10: =IF(OR(AM10="",AL10=0),"",(AM10-AL10)/AL10) | AP10: =ROUND('⚙ Config & Assumptions'!B5*'⚙ Config & Assumptions'!B17*(1-'⚙ Config & Assumptions'!B22),0) -> 88 | AR10: =IF(AQ10="","",AQ10-AP10) | AS10: =IF(OR(AQ10="",AP10=0),"",(AQ10-AP10)/AP10) | AT10: =ROUND('⚙ Config & Assumptions'!B5*'⚙ Config & Assumptions'!B18*(1-'⚙ Config & Assumptions'!B22),0) -> 72 | AV10: =IF(AU10="","",AU10-AT10) | AW10: =IF(OR(AU10="",AT10=0),"",(AU10-AT10)/AT10) | AX10: =CHOOSE('⚙ Config & Assumptions'!B41,B10,F10,J10,N10,R10,V10,Z10,AD10,AH10,AL10,AP10,AT10) -> 72 | AY10: =IF(CHOOSE('⚙ Config & Assumptions'!B41,C10,G10,K10,O10,S10,W10,AA10,AE10,AI10,AM10,AQ10,AU10)="","",CHOOSE('⚙ Config & Assumptions'!B41,C10,G10,K10,O10,S10,W10,AA10,AE10,AI10,AM10,AQ10,AU10)) | AZ10: =IF(AY10="","",AY10-AX10) | BA10: =IF(OR(AY10="",AX10=0),"",(AY10-AX10)/AX10) | BB10: =IF('⚙ Config & Assumptions'!B41>=1,B10,0)+IF('⚙ Config & Assumptions'!B41>=2,F10,0)+IF('⚙ Config & Assumptions'!B41>=3,J10,0)+IF('⚙ Config & Assumptions'!B41>=4,N10,0)+IF('⚙ Config & Assumptions'!B41>=5,R10,0)+IF('⚙ Config & Assumptions'!B41>=6,V10,0)+IF('⚙ Config & Assumptions'!B41>=7,Z10,0)+IF('⚙ Config & Assumptions'!B41>=8,AD10,0)+IF('⚙ Config & Assumptions'!B41>=9,AH10,0)+IF('⚙ Config & Assumptions'!B41>=10,AL10,0)+IF('⚙ Config & Assumptions'!B41>=11,AP10,0)+IF('⚙ Config & Assumptions'!B41>=12,AT10,0) -> 72 | BC10: =IF(AND('⚙ Config & Assumptions'!B41>=1,C10<>""),C10,0)+IF(AND('⚙ Config & Assumptions'!B41>=2,G10<>""),G10,0)+IF(AND('⚙ Config & Assumptions'!B41>=3,K10<>""),K10,0)+IF(AND('⚙ Config & Assumptions'!B41>=4,O10<>""),O10,0)+IF(AND('⚙ Config & Assumptions'!B41>=5,S10<>""),S10,0)+IF(AND('⚙ Config & Assumptions'!B41>=6,W10<>""),W10,0)+IF(AND('⚙ Config & Assumptions'!B41>=7,AA10<>""),AA10,0)+IF(AND('⚙ Config & Assumptions'!B41>=8,AE10<>""),AE10,0)+IF(AND('⚙ Config & Assumptions'!B41>=9,AI10<>""),AI10,0)+IF(AND('⚙ Config & Assumptions'!B41>=10,AM10<>""),AM10,0)+IF(AND('⚙ Config & Assumptions'!B41>=11,AQ10<>""),AQ10,0)+IF(AND('⚙ Config & Assumptions'!B41>=12,AU10<>""),AU10,0) -> 0 | BD10: =IF(BC10=0,"",BC10-BB10) | BE10: =IF(OR(BC10=0,BB10=0),"",(BC10-BB10)/BB10)
A11: ② REVENUE
A12: Gross Revenue (₹) | B12: =ROUND('⚙ Config & Assumptions'!B5*'⚙ Config & Assumptions'!B7*'⚙ Config & Assumptions'!B21,0) -> 12235 | D12: =IF(C12="","",C12-B12) | E12: =IF(OR(C12="",B12=0),"",(C12-B12)/B12) | F12: =ROUND('⚙ Config & Assumptions'!B5*'⚙ Config & Assumptions'!B8*'⚙ Config & Assumptions'!B21,0) -> 13109 | H12: =IF(G12="","",G12-F12) | I12: =IF(OR(G12="",F12=0),"",(G12-F12)/F12) | J12: =ROUND('⚙ Config & Assumptions'!B5*'⚙ Config & Assumptions'!B9*'⚙ Config & Assumptions'!B21,0) -> 11361 | L12: =IF(K12="","",K12-J12) | M12: =IF(OR(K12="",J12=0),"",(K12-J12)/J12) | N12: =ROUND('⚙ Config & Assumptions'!B5*'⚙ Config & Assumptions'!B10*'⚙ Config & Assumptions'!B21,0) -> 13109 | P12: =IF(O12="","",O12-N12) | Q12: =IF(OR(O12="",N12=0),"",(O12-N12)/N12) | R12: =ROUND('⚙ Config & Assumptions'!B5*'⚙ Config & Assumptions'!B11*'⚙ Config & Assumptions'!B21,0) -> 15731 | T12: =IF(S12="","",S12-R12) | U12: =IF(OR(S12="",R12=0),"",(S12-R12)/R12) | V12: =ROUND('⚙ Config & Assumptions'!B5*'⚙ Config & Assumptions'!B12*'⚙ Config & Assumptions'!B21,0) -> 16604 | X12: =IF(W12="","",W12-V12) | Y12: =IF(OR(W12="",V12=0),"",(W12-V12)/V12) | Z12: =ROUND('⚙ Config & Assumptions'!B5*'⚙ Config & Assumptions'!B13*'⚙ Config & Assumptions'!B21,0) -> 17478 | AB12: =IF(AA12="","",AA12-Z12) | AC12: =IF(OR(AA12="",Z12=0),"",(AA12-Z12)/Z12) | AD12: =ROUND('⚙ Config & Assumptions'!B5*'⚙ Config & Assumptions'!B14*'⚙ Config & Assumptions'!B21,0) -> 16604 | AF12: =IF(AE12="","",AE12-AD12) | AG12: =IF(OR(AE12="",AD12=0),"",(AE12-AD12)/AD12) | AH12: =ROUND('⚙ Config & Assumptions'!B5*'⚙ Config & Assumptions'!B15*'⚙ Config & Assumptions'!B21,0) -> 15731 | AJ12: =IF(AI12="","",AI12-AH12) | AK12: =IF(OR(AI12="",AH12=0),"",(AI12-AH12)/AH12) | AL12: =ROUND('⚙ Config & Assumptions'!B5*'⚙ Config & Assumptions'!B16*'⚙ Config & Assumptions'!B21,0) -> 15731 | AN12: =IF(AM12="","",AM12-AL12) | AO12: =IF(OR(AM12="",AL12=0),"",(AM12-AL12)/AL12) | AP12: =ROUND('⚙ Config & Assumptions'!B5*'⚙ Config & Assumptions'!B17*'⚙ Config & Assumptions'!B21,0) -> 14857 | AR12: =IF(AQ12="","",AQ12-AP12) | AS12: =IF(OR(AQ12="",AP12=0),"",(AQ12-AP12)/AP12) | AT12: =ROUND('⚙ Config & Assumptions'!B5*'⚙ Config & Assumptions'!B18*'⚙ Config & Assumptions'!B21,0) -> 12235 | AV12: =IF(AU12="","",AU12-AT12) | AW12: =IF(OR(AU12="",AT12=0),"",(AU12-AT12)/AT12) | AX12: =CHOOSE('⚙ Config & Assumptions'!B41,B12,F12,J12,N12,R12,V12,Z12,AD12,AH12,AL12,AP12,AT12) -> 12235 | AY12: =IF(CHOOSE('⚙ Config & Assumptions'!B41,C12,G12,K12,O12,S12,W12,AA12,AE12,AI12,AM12,AQ12,AU12)="","",CHOOSE('⚙ Config & Assumptions'!B41,C12,G12,K12,O12,S12,W12,AA12,AE12,AI12,AM12,AQ12,AU12)) | AZ12: =IF(AY12="","",AY12-AX12) | BA12: =IF(OR(AY12="",AX12=0),"",(AY12-AX12)/AX12) | BB12: =IF('⚙ Config & Assumptions'!B41>=1,B12,0)+IF('⚙ Config & Assumptions'!B41>=2,F12,0)+IF('⚙ Config & Assumptions'!B41>=3,J12,0)+IF('⚙ Config & Assumptions'!B41>=4,N12,0)+IF('⚙ Config & Assumptions'!B41>=5,R12,0)+IF('⚙ Config & Assumptions'!B41>=6,V12,0)+IF('⚙ Config & Assumptions'!B41>=7,Z12,0)+IF('⚙ Config & Assumptions'!B41>=8,AD12,0)+IF('⚙ Config & Assumptions'!B41>=9,AH12,0)+IF('⚙ Config & Assumptions'!B41>=10,AL12,0)+IF('⚙ Config & Assumptions'!B41>=11,AP12,0)+IF('⚙ Config & Assumptions'!B41>=12,AT12,0) -> 12235 | BC12: =IF(AND('⚙ Config & Assumptions'!B41>=1,C12<>""),C12,0)+IF(AND('⚙ Config & Assumptions'!B41>=2,G12<>""),G12,0)+IF(AND('⚙ Config & Assumptions'!B41>=3,K12<>""),K12,0)+IF(AND('⚙ Config & Assumptions'!B41>=4,O12<>""),O12,0)+IF(AND('⚙ Config & Assumptions'!B41>=5,S12<>""),S12,0)+IF(AND('⚙ Config & Assumptions'!B41>=6,W12<>""),W12,0)+IF(AND('⚙ Config & Assumptions'!B41>=7,AA12<>""),AA12,0)+IF(AND('⚙ Config & Assumptions'!B41>=8,AE12<>""),AE12,0)+IF(AND('⚙ Config & Assumptions'!B41>=9,AI12<>""),AI12,0)+IF(AND('⚙ Config & Assumptions'!B41>=10,AM12<>""),AM12,0)+IF(AND('⚙ Config & Assumptions'!B41>=11,AQ12<>""),AQ12,0)+IF(AND('⚙ Config & Assumptions'!B41>=12,AU12<>""),AU12,0) -> 0 | BD12: =IF(BC12=0,"",BC12-BB12) | BE12: =IF(OR(BC12=0,BB12=0),"",(BC12-BB12)/BB12)
A13: (-) Returns & Refunds (₹) | B13: =ROUND('⚙ Config & Assumptions'!B5*'⚙ Config & Assumptions'!B7*'⚙ Config & Assumptions'!B22*'⚙ Config & Assumptions'!B21,0) -> 970 | D13: =IF(C13="","",C13-B13) | E13: =IF(OR(C13="",B13=0),"",(C13-B13)/B13) | F13: =ROUND('⚙ Config & Assumptions'!B5*'⚙ Config & Assumptions'!B8*'⚙ Config & Assumptions'!B22*'⚙ Config & Assumptions'!B21,0) -> 1040 | H13: =IF(G13="","",G13-F13) | I13: =IF(OR(G13="",F13=0),"",(G13-F13)/F13) | J13: =ROUND('⚙ Config & Assumptions'!B5*'⚙ Config & Assumptions'!B9*'⚙ Config & Assumptions'!B22*'⚙ Config & Assumptions'!B21,0) -> 901 | L13: =IF(K13="","",K13-J13) | M13: =IF(OR(K13="",J13=0),"",(K13-J13)/J13) | N13: =ROUND('⚙ Config & Assumptions'!B5*'⚙ Config & Assumptions'!B10*'⚙ Config & Assumptions'!B22*'⚙ Config & Assumptions'!B21,0) -> 1040 | P13: =IF(O13="","",O13-N13) | Q13: =IF(OR(O13="",N13=0),"",(O13-N13)/N13) | R13: =ROUND('⚙ Config & Assumptions'!B5*'⚙ Config & Assumptions'!B11*'⚙ Config & Assumptions'!B22*'⚙ Config & Assumptions'!B21,0) -> 1247 | T13: =IF(S13="","",S13-R13) | U13: =IF(OR(S13="",R13=0),"",(S13-R13)/R13) | V13: =ROUND('⚙ Config & Assumptions'!B5*'⚙ Config & Assumptions'!B12*'⚙ Config & Assumptions'!B22*'⚙ Config & Assumptions'!B21,0) -> 1317 | X13: =IF(W13="","",W13-V13) | Y13: =IF(OR(W13="",V13=0),"",(W13-V13)/V13) | Z13: =ROUND('⚙ Config & Assumptions'!B5*'⚙ Config & Assumptions'!B13*'⚙ Config & Assumptions'!B22*'⚙ Config & Assumptions'!B21,0) -> 1386 | AB13: =IF(AA13="","",AA13-Z13) | AC13: =IF(OR(AA13="",Z13=0),"",(AA13-Z13)/Z13) | AD13: =ROUND('⚙ Config & Assumptions'!B5*'⚙ Config & Assumptions'!B14*'⚙ Config & Assumptions'!B22*'⚙ Config & Assumptions'!B21,0) -> 1317 | AF13: =IF(AE13="","",AE13-AD13) | AG13: =IF(OR(AE13="",AD13=0),"",(AE13-AD13)/AD13) | AH13: =ROUND('⚙ Config & Assumptions'!B5*'⚙ Config & Assumptions'!B15*'⚙ Config & Assumptions'!B22*'⚙ Config & Assumptions'!B21,0) -> 1247 | AJ13: =IF(AI13="","",AI13-AH13) | AK13: =IF(OR(AI13="",AH13=0),"",(AI13-AH13)/AH13) | AL13: =ROUND('⚙ Config & Assumptions'!B5*'⚙ Config & Assumptions'!B16*'⚙ Config & Assumptions'!B22*'⚙ Config & Assumptions'!B21,0) -> 1247 | AN13: =IF(AM13="","",AM13-AL13) | AO13: =IF(OR(AM13="",AL13=0),"",(AM13-AL13)/AL13) | AP13: =ROUND('⚙ Config & Assumptions'!B5*'⚙ Config & Assumptions'!B17*'⚙ Config & Assumptions'!B22*'⚙ Config & Assumptions'!B21,0) -> 1178 | AR13: =IF(AQ13="","",AQ13-AP13) | AS13: =IF(OR(AQ13="",AP13=0),"",(AQ13-AP13)/AP13) | AT13: =ROUND('⚙ Config & Assumptions'!B5*'⚙ Config & Assumptions'!B18*'⚙ Config & Assumptions'!B22*'⚙ Config & Assumptions'!B21,0) -> 970 | AV13: =IF(AU13="","",AU13-AT13) | AW13: =IF(OR(AU13="",AT13=0),"",(AU13-AT13)/AT13) | AX13: =CHOOSE('⚙ Config & Assumptions'!B41,B13,F13,J13,N13,R13,V13,Z13,AD13,AH13,AL13,AP13,AT13) -> 970 | AY13: =IF(CHOOSE('⚙ Config & Assumptions'!B41,C13,G13,K13,O13,S13,W13,AA13,AE13,AI13,AM13,AQ13,AU13)="","",CHOOSE('⚙ Config & Assumptions'!B41,C13,G13,K13,O13,S13,W13,AA13,AE13,AI13,AM13,AQ13,AU13)) | AZ13: =IF(AY13="","",AY13-AX13) | BA13: =IF(OR(AY13="",AX13=0),"",(AY13-AX13)/AX13) | BB13: =IF('⚙ Config & Assumptions'!B41>=1,B13,0)+IF('⚙ Config & Assumptions'!B41>=2,F13,0)+IF('⚙ Config & Assumptions'!B41>=3,J13,0)+IF('⚙ Config & Assumptions'!B41>=4,N13,0)+IF('⚙ Config & Assumptions'!B41>=5,R13,0)+IF('⚙ Config & Assumptions'!B41>=6,V13,0)+IF('⚙ Config & Assumptions'!B41>=7,Z13,0)+IF('⚙ Config & Assumptions'!B41>=8,AD13,0)+IF('⚙ Config & Assumptions'!B41>=9,AH13,0)+IF('⚙ Config & Assumptions'!B41>=10,AL13,0)+IF('⚙ Config & Assumptions'!B41>=11,AP13,0)+IF('⚙ Config & Assumptions'!B41>=12,AT13,0) -> 970 | BC13: =IF(AND('⚙ Config & Assumptions'!B41>=1,C13<>""),C13,0)+IF(AND('⚙ Config & Assumptions'!B41>=2,G13<>""),G13,0)+IF(AND('⚙ Config & Assumptions'!B41>=3,K13<>""),K13,0)+IF(AND('⚙ Config & Assumptions'!B41>=4,O13<>""),O13,0)+IF(AND('⚙ Config & Assumptions'!B41>=5,S13<>""),S13,0)+IF(AND('⚙ Config & Assumptions'!B41>=6,W13<>""),W13,0)+IF(AND('⚙ Config & Assumptions'!B41>=7,AA13<>""),AA13,0)+IF(AND('⚙ Config & Assumptions'!B41>=8,AE13<>""),AE13,0)+IF(AND('⚙ Config & Assumptions'!B41>=9,AI13<>""),AI13,0)+IF(AND('⚙ Config & Assumptions'!B41>=10,AM13<>""),AM13,0)+IF(AND('⚙ Config & Assumptions'!B41>=11,AQ13<>""),AQ13,0)+IF(AND('⚙ Config & Assumptions'!B41>=12,AU13<>""),AU13,0) -> 0 | BD13: =IF(BC13=0,"",BC13-BB13) | BE13: =IF(OR(BC13=0,BB13=0),"",(BC13-BB13)/BB13)
A14: ⇒ Net Revenue (₹) | B14: =ROUND('⚙ Config & Assumptions'!B5*'⚙ Config & Assumptions'!B7*(1-'⚙ Config & Assumptions'!B22)*'⚙ Config & Assumptions'!B21,0) -> 11265 | D14: =IF(C14="","",C14-B14) | E14: =IF(OR(C14="",B14=0),"",(C14-B14)/B14) | F14: =ROUND('⚙ Config & Assumptions'!B5*'⚙ Config & Assumptions'!B8*(1-'⚙ Config & Assumptions'!B22)*'⚙ Config & Assumptions'!B21,0) -> 12069 | H14: =IF(G14="","",G14-F14) | I14: =IF(OR(G14="",F14=0),"",(G14-F14)/F14) | J14: =ROUND('⚙ Config & Assumptions'!B5*'⚙ Config & Assumptions'!B9*(1-'⚙ Config & Assumptions'!B22)*'⚙ Config & Assumptions'!B21,0) -> 10460 | L14: =IF(K14="","",K14-J14) | M14: =IF(OR(K14="",J14=0),"",(K14-J14)/J14) | N14: =ROUND('⚙ Config & Assumptions'!B5*'⚙ Config & Assumptions'!B10*(1-'⚙ Config & Assumptions'!B22)*'⚙ Config & Assumptions'!B21,0) -> 12069 | P14: =IF(O14="","",O14-N14) | Q14: =IF(OR(O14="",N14=0),"",(O14-N14)/N14) | R14: =ROUND('⚙ Config & Assumptions'!B5*'⚙ Config & Assumptions'!B11*(1-'⚙ Config & Assumptions'!B22)*'⚙ Config & Assumptions'!B21,0) -> 14483 | T14: =IF(S14="","",S14-R14) | U14: =IF(OR(S14="",R14=0),"",(S14-R14)/R14) | V14: =ROUND('⚙ Config & Assumptions'!B5*'⚙ Config & Assumptions'!B12*(1-'⚙ Config & Assumptions'!B22)*'⚙ Config & Assumptions'!B21,0) -> 15288 | X14: =IF(W14="","",W14-V14) | Y14: =IF(OR(W14="",V14=0),"",(W14-V14)/V14) | Z14: =ROUND('⚙ Config & Assumptions'!B5*'⚙ Config & Assumptions'!B13*(1-'⚙ Config & Assumptions'!B22)*'⚙ Config & Assumptions'!B21,0) -> 16092 | AB14: =IF(AA14="","",AA14-Z14) | AC14: =IF(OR(AA14="",Z14=0),"",(AA14-Z14)/Z14) | AD14: =ROUND('⚙ Config & Assumptions'!B5*'⚙ Config & Assumptions'!B14*(1-'⚙ Config & Assumptions'!B22)*'⚙ Config & Assumptions'!B21,0) -> 15288 | AF14: =IF(AE14="","",AE14-AD14) | AG14: =IF(OR(AE14="",AD14=0),"",(AE14-AD14)/AD14) | AH14: =ROUND('⚙ Config & Assumptions'!B5*'⚙ Config & Assumptions'!B15*(1-'⚙ Config & Assumptions'!B22)*'⚙ Config & Assumptions'!B21,0) -> 14483 | AJ14: =IF(AI14="","",AI14-AH14) | AK14: =IF(OR(AI14="",AH14=0),"",(AI14-AH14)/AH14) | AL14: =ROUND('⚙ Config & Assumptions'!B5*'⚙ Config & Assumptions'!B16*(1-'⚙ Config & Assumptions'!B22)*'⚙ Config & Assumptions'!B21,0) -> 14483 | AN14: =IF(AM14="","",AM14-AL14) | AO14: =IF(OR(AM14="",AL14=0),"",(AM14-AL14)/AL14) | AP14: =ROUND('⚙ Config & Assumptions'!B5*'⚙ Config & Assumptions'!B17*(1-'⚙ Config & Assumptions'!B22)*'⚙ Config & Assumptions'!B21,0) -> 13678 | AR14: =IF(AQ14="","",AQ14-AP14) | AS14: =IF(OR(AQ14="",AP14=0),"",(AQ14-AP14)/AP14) | AT14: =ROUND('⚙ Config & Assumptions'!B5*'⚙ Config & Assumptions'!B18*(1-'⚙ Config & Assumptions'!B22)*'⚙ Config & Assumptions'!B21,0) -> 11265 | AV14: =IF(AU14="","",AU14-AT14) | AW14: =IF(OR(AU14="",AT14=0),"",(AU14-AT14)/AT14) | AX14: =CHOOSE('⚙ Config & Assumptions'!B41,B14,F14,J14,N14,R14,V14,Z14,AD14,AH14,AL14,AP14,AT14) -> 11265 | AY14: =IF(CHOOSE('⚙ Config & Assumptions'!B41,C14,G14,K14,O14,S14,W14,AA14,AE14,AI14,AM14,AQ14,AU14)="","",CHOOSE('⚙ Config & Assumptions'!B41,C14,G14,K14,O14,S14,W14,AA14,AE14,AI14,AM14,AQ14,AU14)) | AZ14: =IF(AY14="","",AY14-AX14) | BA14: =IF(OR(AY14="",AX14=0),"",(AY14-AX14)/AX14) | BB14: =IF('⚙ Config & Assumptions'!B41>=1,B14,0)+IF('⚙ Config & Assumptions'!B41>=2,F14,0)+IF('⚙ Config & Assumptions'!B41>=3,J14,0)+IF('⚙ Config & Assumptions'!B41>=4,N14,0)+IF('⚙ Config & Assumptions'!B41>=5,R14,0)+IF('⚙ Config & Assumptions'!B41>=6,V14,0)+IF('⚙ Config & Assumptions'!B41>=7,Z14,0)+IF('⚙ Config & Assumptions'!B41>=8,AD14,0)+IF('⚙ Config & Assumptions'!B41>=9,AH14,0)+IF('⚙ Config & Assumptions'!B41>=10,AL14,0)+IF('⚙ Config & Assumptions'!B41>=11,AP14,0)+IF('⚙ Config & Assumptions'!B41>=12,AT14,0) -> 11265 | BC14: =IF(AND('⚙ Config & Assumptions'!B41>=1,C14<>""),C14,0)+IF(AND('⚙ Config & Assumptions'!B41>=2,G14<>""),G14,0)+IF(AND('⚙ Config & Assumptions'!B41>=3,K14<>""),K14,0)+IF(AND('⚙ Config & Assumptions'!B41>=4,O14<>""),O14,0)+IF(AND('⚙ Config & Assumptions'!B41>=5,S14<>""),S14,0)+IF(AND('⚙ Config & Assumptions'!B41>=6,W14<>""),W14,0)+IF(AND('⚙ Config & Assumptions'!B41>=7,AA14<>""),AA14,0)+IF(AND('⚙ Config & Assumptions'!B41>=8,AE14<>""),AE14,0)+IF(AND('⚙ Config & Assumptions'!B41>=9,AI14<>""),AI14,0)+IF(AND('⚙ Config & Assumptions'!B41>=10,AM14<>""),AM14,0)+IF(AND('⚙ Config & Assumptions'!B41>=11,AQ14<>""),AQ14,0)+IF(AND('⚙ Config & Assumptions'!B41>=12,AU14<>""),AU14,0) -> 0 | BD14: =IF(BC14=0,"",BC14-BB14) | BE14: =IF(OR(BC14=0,BB14=0),"",(BC14-BB14)/BB14)
A15: ③ COGS
A16: Total COGS (₹) | B16: =ROUND('⚙ Config & Assumptions'!B5*'⚙ Config & Assumptions'!B7*(1-'⚙ Config & Assumptions'!B22)*'⚙ Config & Assumptions'!B24,0) -> 6633 | D16: =IF(C16="","",C16-B16) | E16: =IF(OR(C16="",B16=0),"",(C16-B16)/B16) | F16: =ROUND('⚙ Config & Assumptions'!B5*'⚙ Config & Assumptions'!B8*(1-'⚙ Config & Assumptions'!B22)*'⚙ Config & Assumptions'!B24,0) -> 7107 | H16: =IF(G16="","",G16-F16) | I16: =IF(OR(G16="",F16=0),"",(G16-F16)/F16) | J16: =ROUND('⚙ Config & Assumptions'!B5*'⚙ Config & Assumptions'!B9*(1-'⚙ Config & Assumptions'!B22)*'⚙ Config & Assumptions'!B24,0) -> 6159 | L16: =IF(K16="","",K16-J16) | M16: =IF(OR(K16="",J16=0),"",(K16-J16)/J16) | N16: =ROUND('⚙ Config & Assumptions'!B5*'⚙ Config & Assumptions'!B10*(1-'⚙ Config & Assumptions'!B22)*'⚙ Config & Assumptions'!B24,0) -> 7107 | P16: =IF(O16="","",O16-N16) | Q16: =IF(OR(O16="",N16=0),"",(O16-N16)/N16) | R16: =ROUND('⚙ Config & Assumptions'!B5*'⚙ Config & Assumptions'!B11*(1-'⚙ Config & Assumptions'!B22)*'⚙ Config & Assumptions'!B24,0) -> 8529 | T16: =IF(S16="","",S16-R16) | U16: =IF(OR(S16="",R16=0),"",(S16-R16)/R16) | V16: =ROUND('⚙ Config & Assumptions'!B5*'⚙ Config & Assumptions'!B12*(1-'⚙ Config & Assumptions'!B22)*'⚙ Config & Assumptions'!B24,0) -> 9002 | X16: =IF(W16="","",W16-V16) | Y16: =IF(OR(W16="",V16=0),"",(W16-V16)/V16) | Z16: =ROUND('⚙ Config & Assumptions'!B5*'⚙ Config & Assumptions'!B13*(1-'⚙ Config & Assumptions'!B22)*'⚙ Config & Assumptions'!B24,0) -> 9476 | AB16: =IF(AA16="","",AA16-Z16) | AC16: =IF(OR(AA16="",Z16=0),"",(AA16-Z16)/Z16) | AD16: =ROUND('⚙ Config & Assumptions'!B5*'⚙ Config & Assumptions'!B14*(1-'⚙ Config & Assumptions'!B22)*'⚙ Config & Assumptions'!B24,0) -> 9002 | AF16: =IF(AE16="","",AE16-AD16) | AG16: =IF(OR(AE16="",AD16=0),"",(AE16-AD16)/AD16) | AH16: =ROUND('⚙ Config & Assumptions'!B5*'⚙ Config & Assumptions'!B15*(1-'⚙ Config & Assumptions'!B22)*'⚙ Config & Assumptions'!B24,0) -> 8529 | AJ16: =IF(AI16="","",AI16-AH16) | AK16: =IF(OR(AI16="",AH16=0),"",(AI16-AH16)/AH16) | AL16: =ROUND('⚙ Config & Assumptions'!B5*'⚙ Config & Assumptions'!B16*(1-'⚙ Config & Assumptions'!B22)*'⚙ Config & Assumptions'!B24,0) -> 8529 | AN16: =IF(AM16="","",AM16-AL16) | AO16: =IF(OR(AM16="",AL16=0),"",(AM16-AL16)/AL16) | AP16: =ROUND('⚙ Config & Assumptions'!B5*'⚙ Config & Assumptions'!B17*(1-'⚙ Config & Assumptions'!B22)*'⚙ Config & Assumptions'!B24,0) -> 8055 | AR16: =IF(AQ16="","",AQ16-AP16) | AS16: =IF(OR(AQ16="",AP16=0),"",(AQ16-AP16)/AP16) | AT16: =ROUND('⚙ Config & Assumptions'!B5*'⚙ Config & Assumptions'!B18*(1-'⚙ Config & Assumptions'!B22)*'⚙ Config & Assumptions'!B24,0) -> 6633 | AV16: =IF(AU16="","",AU16-AT16) | AW16: =IF(OR(AU16="",AT16=0),"",(AU16-AT16)/AT16) | AX16: =CHOOSE('⚙ Config & Assumptions'!B41,B16,F16,J16,N16,R16,V16,Z16,AD16,AH16,AL16,AP16,AT16) -> 6633 | AY16: =IF(CHOOSE('⚙ Config & Assumptions'!B41,C16,G16,K16,O16,S16,W16,AA16,AE16,AI16,AM16,AQ16,AU16)="","",CHOOSE('⚙ Config & Assumptions'!B41,C16,G16,K16,O16,S16,W16,AA16,AE16,AI16,AM16,AQ16,AU16)) | AZ16: =IF(AY16="","",AY16-AX16) | BA16: =IF(OR(AY16="",AX16=0),"",(AY16-AX16)/AX16) | BB16: =IF('⚙ Config & Assumptions'!B41>=1,B16,0)+IF('⚙ Config & Assumptions'!B41>=2,F16,0)+IF('⚙ Config & Assumptions'!B41>=3,J16,0)+IF('⚙ Config & Assumptions'!B41>=4,N16,0)+IF('⚙ Config & Assumptions'!B41>=5,R16,0)+IF('⚙ Config & Assumptions'!B41>=6,V16,0)+IF('⚙ Config & Assumptions'!B41>=7,Z16,0)+IF('⚙ Config & Assumptions'!B41>=8,AD16,0)+IF('⚙ Config & Assumptions'!B41>=9,AH16,0)+IF('⚙ Config & Assumptions'!B41>=10,AL16,0)+IF('⚙ Config & Assumptions'!B41>=11,AP16,0)+IF('⚙ Config & Assumptions'!B41>=12,AT16,0) -> 6633 | BC16: =IF(AND('⚙ Config & Assumptions'!B41>=1,C16<>""),C16,0)+IF(AND('⚙ Config & Assumptions'!B41>=2,G16<>""),G16,0)+IF(AND('⚙ Config & Assumptions'!B41>=3,K16<>""),K16,0)+IF(AND('⚙ Config & Assumptions'!B41>=4,O16<>""),O16,0)+IF(AND('⚙ Config & Assumptions'!B41>=5,S16<>""),S16,0)+IF(AND('⚙ Config & Assumptions'!B41>=6,W16<>""),W16,0)+IF(AND('⚙ Config & Assumptions'!B41>=7,AA16<>""),AA16,0)+IF(AND('⚙ Config & Assumptions'!B41>=8,AE16<>""),AE16,0)+IF(AND('⚙ Config & Assumptions'!B41>=9,AI16<>""),AI16,0)+IF(AND('⚙ Config & Assumptions'!B41>=10,AM16<>""),AM16,0)+IF(AND('⚙ Config & Assumptions'!B41>=11,AQ16<>""),AQ16,0)+IF(AND('⚙ Config & Assumptions'!B41>=12,AU16<>""),AU16,0) -> 0 | BD16: =IF(BC16=0,"",BC16-BB16) | BE16: =IF(OR(BC16=0,BB16=0),"",(BC16-BB16)/BB16)
A17: ④ GROSS PROFIT
A18: ⇒ Gross Profit (₹) | B18: =ROUND('⚙ Config & Assumptions'!B5*'⚙ Config & Assumptions'!B7*(1-'⚙ Config & Assumptions'!B22)*('⚙ Config & Assumptions'!B21-'⚙ Config & Assumptions'!B24),0) -> 4631 | D18: =IF(C18="","",C18-B18) | E18: =IF(OR(C18="",B18=0),"",(C18-B18)/B18) | F18: =ROUND('⚙ Config & Assumptions'!B5*'⚙ Config & Assumptions'!B8*(1-'⚙ Config & Assumptions'!B22)*('⚙ Config & Assumptions'!B21-'⚙ Config & Assumptions'!B24),0) -> 4962 | H18: =IF(G18="","",G18-F18) | I18: =IF(OR(G18="",F18=0),"",(G18-F18)/F18) | J18: =ROUND('⚙ Config & Assumptions'!B5*'⚙ Config & Assumptions'!B9*(1-'⚙ Config & Assumptions'!B22)*('⚙ Config & Assumptions'!B21-'⚙ Config & Assumptions'!B24),0) -> 4301 | L18: =IF(K18="","",K18-J18) | M18: =IF(OR(K18="",J18=0),"",(K18-J18)/J18) | N18: =ROUND('⚙ Config & Assumptions'!B5*'⚙ Config & Assumptions'!B10*(1-'⚙ Config & Assumptions'!B22)*('⚙ Config & Assumptions'!B21-'⚙ Config & Assumptions'!B24),0) -> 4962 | P18: =IF(O18="","",O18-N18) | Q18: =IF(OR(O18="",N18=0),"",(O18-N18)/N18) | R18: =ROUND('⚙ Config & Assumptions'!B5*'⚙ Config & Assumptions'!B11*(1-'⚙ Config & Assumptions'!B22)*('⚙ Config & Assumptions'!B21-'⚙ Config & Assumptions'!B24),0) -> 5955 | T18: =IF(S18="","",S18-R18) | U18: =IF(OR(S18="",R18=0),"",(S18-R18)/R18) | V18: =ROUND('⚙ Config & Assumptions'!B5*'⚙ Config & Assumptions'!B12*(1-'⚙ Config & Assumptions'!B22)*('⚙ Config & Assumptions'!B21-'⚙ Config & Assumptions'!B24),0) -> 6285 | X18: =IF(W18="","",W18-V18) | Y18: =IF(OR(W18="",V18=0),"",(W18-V18)/V18) | Z18: =ROUND('⚙ Config & Assumptions'!B5*'⚙ Config & Assumptions'!B13*(1-'⚙ Config & Assumptions'!B22)*('⚙ Config & Assumptions'!B21-'⚙ Config & Assumptions'!B24),0) -> 6616 | AB18: =IF(AA18="","",AA18-Z18) | AC18: =IF(OR(AA18="",Z18=0),"",(AA18-Z18)/Z18) | AD18: =ROUND('⚙ Config & Assumptions'!B5*'⚙ Config & Assumptions'!B14*(1-'⚙ Config & Assumptions'!B22)*('⚙ Config & Assumptions'!B21-'⚙ Config & Assumptions'!B24),0) -> 6285 | AF18: =IF(AE18="","",AE18-AD18) | AG18: =IF(OR(AE18="",AD18=0),"",(AE18-AD18)/AD18) | AH18: =ROUND('⚙ Config & Assumptions'!B5*'⚙ Config & Assumptions'!B15*(1-'⚙ Config & Assumptions'!B22)*('⚙ Config & Assumptions'!B21-'⚙ Config & Assumptions'!B24),0) -> 5955 | AJ18: =IF(AI18="","",AI18-AH18) | AK18: =IF(OR(AI18="",AH18=0),"",(AI18-AH18)/AH18) | AL18: =ROUND('⚙ Config & Assumptions'!B5*'⚙ Config & Assumptions'!B16*(1-'⚙ Config & Assumptions'!B22)*('⚙ Config & Assumptions'!B21-'⚙ Config & Assumptions'!B24),0) -> 5955 | AN18: =IF(AM18="","",AM18-AL18) | AO18: =IF(OR(AM18="",AL18=0),"",(AM18-AL18)/AL18) | AP18: =ROUND('⚙ Config & Assumptions'!B5*'⚙ Config & Assumptions'!B17*(1-'⚙ Config & Assumptions'!B22)*('⚙ Config & Assumptions'!B21-'⚙ Config & Assumptions'!B24),0) -> 5624 | AR18: =IF(AQ18="","",AQ18-AP18) | AS18: =IF(OR(AQ18="",AP18=0),"",(AQ18-AP18)/AP18) | AT18: =ROUND('⚙ Config & Assumptions'!B5*'⚙ Config & Assumptions'!B18*(1-'⚙ Config & Assumptions'!B22)*('⚙ Config & Assumptions'!B21-'⚙ Config & Assumptions'!B24),0) -> 4631 | AV18: =IF(AU18="","",AU18-AT18) | AW18: =IF(OR(AU18="",AT18=0),"",(AU18-AT18)/AT18) | AX18: =CHOOSE('⚙ Config & Assumptions'!B41,B18,F18,J18,N18,R18,V18,Z18,AD18,AH18,AL18,AP18,AT18) -> 4631 | AY18: =IF(CHOOSE('⚙ Config & Assumptions'!B41,C18,G18,K18,O18,S18,W18,AA18,AE18,AI18,AM18,AQ18,AU18)="","",CHOOSE('⚙ Config & Assumptions'!B41,C18,G18,K18,O18,S18,W18,AA18,AE18,AI18,AM18,AQ18,AU18)) | AZ18: =IF(AY18="","",AY18-AX18) | BA18: =IF(OR(AY18="",AX18=0),"",(AY18-AX18)/AX18) | BB18: =IF('⚙ Config & Assumptions'!B41>=1,B18,0)+IF('⚙ Config & Assumptions'!B41>=2,F18,0)+IF('⚙ Config & Assumptions'!B41>=3,J18,0)+IF('⚙ Config & Assumptions'!B41>=4,N18,0)+IF('⚙ Config & Assumptions'!B41>=5,R18,0)+IF('⚙ Config & Assumptions'!B41>=6,V18,0)+IF('⚙ Config & Assumptions'!B41>=7,Z18,0)+IF('⚙ Config & Assumptions'!B41>=8,AD18,0)+IF('⚙ Config & Assumptions'!B41>=9,AH18,0)+IF('⚙ Config & Assumptions'!B41>=10,AL18,0)+IF('⚙ Config & Assumptions'!B41>=11,AP18,0)+IF('⚙ Config & Assumptions'!B41>=12,AT18,0) -> 4631 | BC18: =IF(AND('⚙ Config & Assumptions'!B41>=1,C18<>""),C18,0)+IF(AND('⚙ Config & Assumptions'!B41>=2,G18<>""),G18,0)+IF(AND('⚙ Config & Assumptions'!B41>=3,K18<>""),K18,0)+IF(AND('⚙ Config & Assumptions'!B41>=4,O18<>""),O18,0)+IF(AND('⚙ Config & Assumptions'!B41>=5,S18<>""),S18,0)+IF(AND('⚙ Config & Assumptions'!B41>=6,W18<>""),W18,0)+IF(AND('⚙ Config & Assumptions'!B41>=7,AA18<>""),AA18,0)+IF(AND('⚙ Config & Assumptions'!B41>=8,AE18<>""),AE18,0)+IF(AND('⚙ Config & Assumptions'!B41>=9,AI18<>""),AI18,0)+IF(AND('⚙ Config & Assumptions'!B41>=10,AM18<>""),AM18,0)+IF(AND('⚙ Config & Assumptions'!B41>=11,AQ18<>""),AQ18,0)+IF(AND('⚙ Config & Assumptions'!B41>=12,AU18<>""),AU18,0) -> 0 | BD18: =IF(BC18=0,"",BC18-BB18) | BE18: =IF(OR(BC18=0,BB18=0),"",(BC18-BB18)/BB18)
A19: Gross Margin (%) | B19: =IF(B18=0,0,B18/B14) -> 0.41109632 | D19: =IF(C19="","",C19-B19) | E19: =IF(OR(C19="",B19=0),"",(C19-B19)/B19) | F19: =IF(F18=0,0,F18/F14) -> 0.41113597 | H19: =IF(G19="","",G19-F19) | I19: =IF(OR(G19="",F19=0),"",(G19-F19)/F19) | J19: =IF(J18=0,0,J18/J14) -> 0.41118547 | L19: =IF(K19="","",K19-J19) | M19: =IF(OR(K19="",J19=0),"",(K19-J19)/J19) | N19: =IF(N18=0,0,N18/N14) -> 0.41113597 | P19: =IF(O19="","",O19-N19) | Q19: =IF(OR(O19="",N19=0),"",(O19-N19)/N19) | R19: =IF(R18=0,0,R18/R14) -> 0.41117172 | T19: =IF(S19="","",S19-R19) | U19: =IF(OR(S19="",R19=0),"",(S19-R19)/R19) | V19: =IF(V18=0,0,V18/V14) -> 0.41110675 | X19: =IF(W19="","",W19-V19) | Y19: =IF(OR(W19="",V19=0),"",(W19-V19)/V19) | Z19: =IF(Z18=0,0,Z18/Z14) -> 0.41113597 | AB19: =IF(AA19="","",AA19-Z19) | AC19: =IF(OR(AA19="",Z19=0),"",(AA19-Z19)/Z19) | AD19: =IF(AD18=0,0,AD18/AD14) -> 0.41110675 | AF19: =IF(AE19="","",AE19-AD19) | AG19: =IF(OR(AE19="",AD19=0),"",(AE19-AD19)/AD19) | AH19: =IF(AH18=0,0,AH18/AH14) -> 0.41117172 | AJ19: =IF(AI19="","",AI19-AH19) | AK19: =IF(OR(AI19="",AH19=0),"",(AI19-AH19)/AH19) | AL19: =IF(AL18=0,0,AL18/AL14) -> 0.41117172 | AN19: =IF(AM19="","",AM19-AL19) | AO19: =IF(OR(AM19="",AL19=0),"",(AM19-AL19)/AL19) | AP19: =IF(AP18=0,0,AP18/AP14) -> 0.41117122 | AR19: =IF(AQ19="","",AQ19-AP19) | AS19: =IF(OR(AQ19="",AP19=0),"",(AQ19-AP19)/AP19) | AT19: =IF(AT18=0,0,AT18/AT14) -> 0.41109632 | AV19: =IF(AU19="","",AU19-AT19) | AW19: =IF(OR(AU19="",AT19=0),"",(AU19-AT19)/AT19) | AX19: =CHOOSE('⚙ Config & Assumptions'!B41,B19,F19,J19,N19,R19,V19,Z19,AD19,AH19,AL19,AP19,AT19) -> 0.41109632 | AY19: =IF(CHOOSE('⚙ Config & Assumptions'!B41,C19,G19,K19,O19,S19,W19,AA19,AE19,AI19,AM19,AQ19,AU19)="","",CHOOSE('⚙ Config & Assumptions'!B41,C19,G19,K19,O19,S19,W19,AA19,AE19,AI19,AM19,AQ19,AU19)) | AZ19: =IF(AY19="","",AY19-AX19) | BA19: =IF(OR(AY19="",AX19=0),"",(AY19-AX19)/AX19) | BB19: =IF('⚙ Config & Assumptions'!B41>=1,B19,0)+IF('⚙ Config & Assumptions'!B41>=2,F19,0)+IF('⚙ Config & Assumptions'!B41>=3,J19,0)+IF('⚙ Config & Assumptions'!B41>=4,N19,0)+IF('⚙ Config & Assumptions'!B41>=5,R19,0)+IF('⚙ Config & Assumptions'!B41>=6,V19,0)+IF('⚙ Config & Assumptions'!B41>=7,Z19,0)+IF('⚙ Config & Assumptions'!B41>=8,AD19,0)+IF('⚙ Config & Assumptions'!B41>=9,AH19,0)+IF('⚙ Config & Assumptions'!B41>=10,AL19,0)+IF('⚙ Config & Assumptions'!B41>=11,AP19,0)+IF('⚙ Config & Assumptions'!B41>=12,AT19,0) -> 0.41109632 | BC19: =IF(AND('⚙ Config & Assumptions'!B41>=1,C19<>""),C19,0)+IF(AND('⚙ Config & Assumptions'!B41>=2,G19<>""),G19,0)+IF(AND('⚙ Config & Assumptions'!B41>=3,K19<>""),K19,0)+IF(AND('⚙ Config & Assumptions'!B41>=4,O19<>""),O19,0)+IF(AND('⚙ Config & Assumptions'!B41>=5,S19<>""),S19,0)+IF(AND('⚙ Config & Assumptions'!B41>=6,W19<>""),W19,0)+IF(AND('⚙ Config & Assumptions'!B41>=7,AA19<>""),AA19,0)+IF(AND('⚙ Config & Assumptions'!B41>=8,AE19<>""),AE19,0)+IF(AND('⚙ Config & Assumptions'!B41>=9,AI19<>""),AI19,0)+IF(AND('⚙ Config & Assumptions'!B41>=10,AM19<>""),AM19,0)+IF(AND('⚙ Config & Assumptions'!B41>=11,AQ19<>""),AQ19,0)+IF(AND('⚙ Config & Assumptions'!B41>=12,AU19<>""),AU19,0) -> 0 | BD19: =IF(BC19=0,"",BC19-BB19) | BE19: =IF(OR(BC19=0,BB19=0),"",(BC19-BB19)/BB19)
A20: ⑤ OPERATING EXPENSES
A21: Marketplace Fees (₹) | B21: =ROUND('⚙ Config & Assumptions'!B5*'⚙ Config & Assumptions'!B7*(1-'⚙ Config & Assumptions'!B22)*'⚙ Config & Assumptions'!B25,0) -> 656 | D21: =IF(C21="","",C21-B21) | E21: =IF(OR(C21="",B21=0),"",(C21-B21)/B21) | F21: =ROUND('⚙ Config & Assumptions'!B5*'⚙ Config & Assumptions'!B8*(1-'⚙ Config & Assumptions'!B22)*'⚙ Config & Assumptions'!B25,0) -> 703 | H21: =IF(G21="","",G21-F21) | I21: =IF(OR(G21="",F21=0),"",(G21-F21)/F21) | J21: =ROUND('⚙ Config & Assumptions'!B5*'⚙ Config & Assumptions'!B9*(1-'⚙ Config & Assumptions'!B22)*'⚙ Config & Assumptions'!B25,0) -> 609 | L21: =IF(K21="","",K21-J21) | M21: =IF(OR(K21="",J21=0),"",(K21-J21)/J21) | N21: =ROUND('⚙ Config & Assumptions'!B5*'⚙ Config & Assumptions'!B10*(1-'⚙ Config & Assumptions'!B22)*'⚙ Config & Assumptions'!B25,0) -> 703 | P21: =IF(O21="","",O21-N21) | Q21: =IF(OR(O21="",N21=0),"",(O21-N21)/N21) | R21: =ROUND('⚙ Config & Assumptions'!B5*'⚙ Config & Assumptions'!B11*(1-'⚙ Config & Assumptions'!B22)*'⚙ Config & Assumptions'!B25,0) -> 843 | T21: =IF(S21="","",S21-R21) | U21: =IF(OR(S21="",R21=0),"",(S21-R21)/R21) | V21: =ROUND('⚙ Config & Assumptions'!B5*'⚙ Config & Assumptions'!B12*(1-'⚙ Config & Assumptions'!B22)*'⚙ Config & Assumptions'!B25,0) -> 890 | X21: =IF(W21="","",W21-V21) | Y21: =IF(OR(W21="",V21=0),"",(W21-V21)/V21) | Z21: =ROUND('⚙ Config & Assumptions'!B5*'⚙ Config & Assumptions'!B13*(1-'⚙ Config & Assumptions'!B22)*'⚙ Config & Assumptions'!B25,0) -> 937 | AB21: =IF(AA21="","",AA21-Z21) | AC21: =IF(OR(AA21="",Z21=0),"",(AA21-Z21)/Z21) | AD21: =ROUND('⚙ Config & Assumptions'!B5*'⚙ Config & Assumptions'!B14*(1-'⚙ Config & Assumptions'!B22)*'⚙ Config & Assumptions'!B25,0) -> 890 | AF21: =IF(AE21="","",AE21-AD21) | AG21: =IF(OR(AE21="",AD21=0),"",(AE21-AD21)/AD21) | AH21: =ROUND('⚙ Config & Assumptions'!B5*'⚙ Config & Assumptions'!B15*(1-'⚙ Config & Assumptions'!B22)*'⚙ Config & Assumptions'!B25,0) -> 843 | AJ21: =IF(AI21="","",AI21-AH21) | AK21: =IF(OR(AI21="",AH21=0),"",(AI21-AH21)/AH21) | AL21: =ROUND('⚙ Config & Assumptions'!B5*'⚙ Config & Assumptions'!B16*(1-'⚙ Config & Assumptions'!B22)*'⚙ Config & Assumptions'!B25,0) -> 843 | AN21: =IF(AM21="","",AM21-AL21) | AO21: =IF(OR(AM21="",AL21=0),"",(AM21-AL21)/AL21) | AP21: =ROUND('⚙ Config & Assumptions'!B5*'⚙ Config & Assumptions'!B17*(1-'⚙ Config & Assumptions'!B22)*'⚙ Config & Assumptions'!B25,0) -> 796 | AR21: =IF(AQ21="","",AQ21-AP21) | AS21: =IF(OR(AQ21="",AP21=0),"",(AQ21-AP21)/AP21) | AT21: =ROUND('⚙ Config & Assumptions'!B5*'⚙ Config & Assumptions'!B18*(1-'⚙ Config & Assumptions'!B22)*'⚙ Config & Assumptions'!B25,0) -> 656 | AV21: =IF(AU21="","",AU21-AT21) | AW21: =IF(OR(AU21="",AT21=0),"",(AU21-AT21)/AT21) | AX21: =CHOOSE('⚙ Config & Assumptions'!B41,B21,F21,J21,N21,R21,V21,Z21,AD21,AH21,AL21,AP21,AT21) -> 656 | AY21: =IF(CHOOSE('⚙ Config & Assumptions'!B41,C21,G21,K21,O21,S21,W21,AA21,AE21,AI21,AM21,AQ21,AU21)="","",CHOOSE('⚙ Config & Assumptions'!B41,C21,G21,K21,O21,S21,W21,AA21,AE21,AI21,AM21,AQ21,AU21)) | AZ21: =IF(AY21="","",AY21-AX21) | BA21: =IF(OR(AY21="",AX21=0),"",(AY21-AX21)/AX21) | BB21: =IF('⚙ Config & Assumptions'!B41>=1,B21,0)+IF('⚙ Config & Assumptions'!B41>=2,F21,0)+IF('⚙ Config & Assumptions'!B41>=3,J21,0)+IF('⚙ Config & Assumptions'!B41>=4,N21,0)+IF('⚙ Config & Assumptions'!B41>=5,R21,0)+IF('⚙ Config & Assumptions'!B41>=6,V21,0)+IF('⚙ Config & Assumptions'!B41>=7,Z21,0)+IF('⚙ Config & Assumptions'!B41>=8,AD21,0)+IF('⚙ Config & Assumptions'!B41>=9,AH21,0)+IF('⚙ Config & Assumptions'!B41>=10,AL21,0)+IF('⚙ Config & Assumptions'!B41>=11,AP21,0)+IF('⚙ Config & Assumptions'!B41>=12,AT21,0) -> 656 | BC21: =IF(AND('⚙ Config & Assumptions'!B41>=1,C21<>""),C21,0)+IF(AND('⚙ Config & Assumptions'!B41>=2,G21<>""),G21,0)+IF(AND('⚙ Config & Assumptions'!B41>=3,K21<>""),K21,0)+IF(AND('⚙ Config & Assumptions'!B41>=4,O21<>""),O21,0)+IF(AND('⚙ Config & Assumptions'!B41>=5,S21<>""),S21,0)+IF(AND('⚙ Config & Assumptions'!B41>=6,W21<>""),W21,0)+IF(AND('⚙ Config & Assumptions'!B41>=7,AA21<>""),AA21,0)+IF(AND('⚙ Config & Assumptions'!B41>=8,AE21<>""),AE21,0)+IF(AND('⚙ Config & Assumptions'!B41>=9,AI21<>""),AI21,0)+IF(AND('⚙ Config & Assumptions'!B41>=10,AM21<>""),AM21,0)+IF(AND('⚙ Config & Assumptions'!B41>=11,AQ21<>""),AQ21,0)+IF(AND('⚙ Config & Assumptions'!B41>=12,AU21<>""),AU21,0) -> 0 | BD21: =IF(BC21=0,"",BC21-BB21) | BE21: =IF(OR(BC21=0,BB21=0),"",(BC21-BB21)/BB21)
A22: Logistics — Returns (₹) | B22: =ROUND('⚙ Config & Assumptions'!B5*'⚙ Config & Assumptions'!B7*(1-'⚙ Config & Assumptions'!B22)*'⚙ Config & Assumptions'!B26,0) -> 323 | D22: =IF(C22="","",C22-B22) | E22: =IF(OR(C22="",B22=0),"",(C22-B22)/B22) | F22: =ROUND('⚙ Config & Assumptions'!B5*'⚙ Config & Assumptions'!B8*(1-'⚙ Config & Assumptions'!B22)*'⚙ Config & Assumptions'!B26,0) -> 346 | H22: =IF(G22="","",G22-F22) | I22: =IF(OR(G22="",F22=0),"",(G22-F22)/F22) | J22: =ROUND('⚙ Config & Assumptions'!B5*'⚙ Config & Assumptions'!B9*(1-'⚙ Config & Assumptions'!B22)*'⚙ Config & Assumptions'!B26,0) -> 300 | L22: =IF(K22="","",K22-J22) | M22: =IF(OR(K22="",J22=0),"",(K22-J22)/J22) | N22: =ROUND('⚙ Config & Assumptions'!B5*'⚙ Config & Assumptions'!B10*(1-'⚙ Config & Assumptions'!B22)*'⚙ Config & Assumptions'!B26,0) -> 346 | P22: =IF(O22="","",O22-N22) | Q22: =IF(OR(O22="",N22=0),"",(O22-N22)/N22) | R22: =ROUND('⚙ Config & Assumptions'!B5*'⚙ Config & Assumptions'!B11*(1-'⚙ Config & Assumptions'!B22)*'⚙ Config & Assumptions'!B26,0) -> 415 | T22: =IF(S22="","",S22-R22) | U22: =IF(OR(S22="",R22=0),"",(S22-R22)/R22) | V22: =ROUND('⚙ Config & Assumptions'!B5*'⚙ Config & Assumptions'!B12*(1-'⚙ Config & Assumptions'!B22)*'⚙ Config & Assumptions'!B26,0) -> 438 | X22: =IF(W22="","",W22-V22) | Y22: =IF(OR(W22="",V22=0),"",(W22-V22)/V22) | Z22: =ROUND('⚙ Config & Assumptions'!B5*'⚙ Config & Assumptions'!B13*(1-'⚙ Config & Assumptions'!B22)*'⚙ Config & Assumptions'!B26,0) -> 461 | AB22: =IF(AA22="","",AA22-Z22) | AC22: =IF(OR(AA22="",Z22=0),"",(AA22-Z22)/Z22) | AD22: =ROUND('⚙ Config & Assumptions'!B5*'⚙ Config & Assumptions'!B14*(1-'⚙ Config & Assumptions'!B22)*'⚙ Config & Assumptions'!B26,0) -> 438 | AF22: =IF(AE22="","",AE22-AD22) | AG22: =IF(OR(AE22="",AD22=0),"",(AE22-AD22)/AD22) | AH22: =ROUND('⚙ Config & Assumptions'!B5*'⚙ Config & Assumptions'!B15*(1-'⚙ Config & Assumptions'!B22)*'⚙ Config & Assumptions'!B26,0) -> 415 | AJ22: =IF(AI22="","",AI22-AH22) | AK22: =IF(OR(AI22="",AH22=0),"",(AI22-AH22)/AH22) | AL22: =ROUND('⚙ Config & Assumptions'!B5*'⚙ Config & Assumptions'!B16*(1-'⚙ Config & Assumptions'!B22)*'⚙ Config & Assumptions'!B26,0) -> 415 | AN22: =IF(AM22="","",AM22-AL22) | AO22: =IF(OR(AM22="",AL22=0),"",(AM22-AL22)/AL22) | AP22: =ROUND('⚙ Config & Assumptions'!B5*'⚙ Config & Assumptions'!B17*(1-'⚙ Config & Assumptions'!B22)*'⚙ Config & Assumptions'!B26,0) -> 392 | AR22: =IF(AQ22="","",AQ22-AP22) | AS22: =IF(OR(AQ22="",AP22=0),"",(AQ22-AP22)/AP22) | AT22: =ROUND('⚙ Config & Assumptions'!B5*'⚙ Config & Assumptions'!B18*(1-'⚙ Config & Assumptions'!B22)*'⚙ Config & Assumptions'!B26,0) -> 323 | AV22: =IF(AU22="","",AU22-AT22) | AW22: =IF(OR(AU22="",AT22=0),"",(AU22-AT22)/AT22) | AX22: =CHOOSE('⚙ Config & Assumptions'!B41,B22,F22,J22,N22,R22,V22,Z22,AD22,AH22,AL22,AP22,AT22) -> 323 | AY22: =IF(CHOOSE('⚙ Config & Assumptions'!B41,C22,G22,K22,O22,S22,W22,AA22,AE22,AI22,AM22,AQ22,AU22)="","",CHOOSE('⚙ Config & Assumptions'!B41,C22,G22,K22,O22,S22,W22,AA22,AE22,AI22,AM22,AQ22,AU22)) | AZ22: =IF(AY22="","",AY22-AX22) | BA22: =IF(OR(AY22="",AX22=0),"",(AY22-AX22)/AX22) | BB22: =IF('⚙ Config & Assumptions'!B41>=1,B22,0)+IF('⚙ Config & Assumptions'!B41>=2,F22,0)+IF('⚙ Config & Assumptions'!B41>=3,J22,0)+IF('⚙ Config & Assumptions'!B41>=4,N22,0)+IF('⚙ Config & Assumptions'!B41>=5,R22,0)+IF('⚙ Config & Assumptions'!B41>=6,V22,0)+IF('⚙ Config & Assumptions'!B41>=7,Z22,0)+IF('⚙ Config & Assumptions'!B41>=8,AD22,0)+IF('⚙ Config & Assumptions'!B41>=9,AH22,0)+IF('⚙ Config & Assumptions'!B41>=10,AL22,0)+IF('⚙ Config & Assumptions'!B41>=11,AP22,0)+IF('⚙ Config & Assumptions'!B41>=12,AT22,0) -> 323 | BC22: =IF(AND('⚙ Config & Assumptions'!B41>=1,C22<>""),C22,0)+IF(AND('⚙ Config & Assumptions'!B41>=2,G22<>""),G22,0)+IF(AND('⚙ Config & Assumptions'!B41>=3,K22<>""),K22,0)+IF(AND('⚙ Config & Assumptions'!B41>=4,O22<>""),O22,0)+IF(AND('⚙ Config & Assumptions'!B41>=5,S22<>""),S22,0)+IF(AND('⚙ Config & Assumptions'!B41>=6,W22<>""),W22,0)+IF(AND('⚙ Config & Assumptions'!B41>=7,AA22<>""),AA22,0)+IF(AND('⚙ Config & Assumptions'!B41>=8,AE22<>""),AE22,0)+IF(AND('⚙ Config & Assumptions'!B41>=9,AI22<>""),AI22,0)+IF(AND('⚙ Config & Assumptions'!B41>=10,AM22<>""),AM22,0)+IF(AND('⚙ Config & Assumptions'!B41>=11,AQ22<>""),AQ22,0)+IF(AND('⚙ Config & Assumptions'!B41>=12,AU22<>""),AU22,0) -> 0 | BD22: =IF(BC22=0,"",BC22-BB22) | BE22: =IF(OR(BC22=0,BB22=0),"",(BC22-BB22)/BB22)
A23: Ad Spend (₹) | B23: =ROUND('⚙ Config & Assumptions'!B28/12,0) -> 1475 | D23: =IF(C23="","",C23-B23) | E23: =IF(OR(C23="",B23=0),"",(C23-B23)/B23) | F23: =ROUND('⚙ Config & Assumptions'!B28/12,0) -> 1475 | H23: =IF(G23="","",G23-F23) | I23: =IF(OR(G23="",F23=0),"",(G23-F23)/F23) | J23: =ROUND('⚙ Config & Assumptions'!B28/12,0) -> 1475 | L23: =IF(K23="","",K23-J23) | M23: =IF(OR(K23="",J23=0),"",(K23-J23)/J23) | N23: =ROUND('⚙ Config & Assumptions'!B28/12,0) -> 1475 | P23: =IF(O23="","",O23-N23) | Q23: =IF(OR(O23="",N23=0),"",(O23-N23)/N23) | R23: =ROUND('⚙ Config & Assumptions'!B28/12,0) -> 1475 | T23: =IF(S23="","",S23-R23) | U23: =IF(OR(S23="",R23=0),"",(S23-R23)/R23) | V23: =ROUND('⚙ Config & Assumptions'!B28/12,0) -> 1475 | X23: =IF(W23="","",W23-V23) | Y23: =IF(OR(W23="",V23=0),"",(W23-V23)/V23) | Z23: =ROUND('⚙ Config & Assumptions'!B28/12,0) -> 1475 | AB23: =IF(AA23="","",AA23-Z23) | AC23: =IF(OR(AA23="",Z23=0),"",(AA23-Z23)/Z23) | AD23: =ROUND('⚙ Config & Assumptions'!B28/12,0) -> 1475 | AF23: =IF(AE23="","",AE23-AD23) | AG23: =IF(OR(AE23="",AD23=0),"",(AE23-AD23)/AD23) | AH23: =ROUND('⚙ Config & Assumptions'!B28/12,0) -> 1475 | AJ23: =IF(AI23="","",AI23-AH23) | AK23: =IF(OR(AI23="",AH23=0),"",(AI23-AH23)/AH23) | AL23: =ROUND('⚙ Config & Assumptions'!B28/12,0) -> 1475 | AN23: =IF(AM23="","",AM23-AL23) | AO23: =IF(OR(AM23="",AL23=0),"",(AM23-AL23)/AL23) | AP23: =ROUND('⚙ Config & Assumptions'!B28/12,0) -> 1475 | AR23: =IF(AQ23="","",AQ23-AP23) | AS23: =IF(OR(AQ23="",AP23=0),"",(AQ23-AP23)/AP23) | AT23: =ROUND('⚙ Config & Assumptions'!B28/12,0) -> 1475 | AV23: =IF(AU23="","",AU23-AT23) | AW23: =IF(OR(AU23="",AT23=0),"",(AU23-AT23)/AT23) | AX23: =CHOOSE('⚙ Config & Assumptions'!B41,B23,F23,J23,N23,R23,V23,Z23,AD23,AH23,AL23,AP23,AT23) -> 1475 | AY23: =IF(CHOOSE('⚙ Config & Assumptions'!B41,C23,G23,K23,O23,S23,W23,AA23,AE23,AI23,AM23,AQ23,AU23)="","",CHOOSE('⚙ Config & Assumptions'!B41,C23,G23,K23,O23,S23,W23,AA23,AE23,AI23,AM23,AQ23,AU23)) | AZ23: =IF(AY23="","",AY23-AX23) | BA23: =IF(OR(AY23="",AX23=0),"",(AY23-AX23)/AX23) | BB23: =IF('⚙ Config & Assumptions'!B41>=1,B23,0)+IF('⚙ Config & Assumptions'!B41>=2,F23,0)+IF('⚙ Config & Assumptions'!B41>=3,J23,0)+IF('⚙ Config & Assumptions'!B41>=4,N23,0)+IF('⚙ Config & Assumptions'!B41>=5,R23,0)+IF('⚙ Config & Assumptions'!B41>=6,V23,0)+IF('⚙ Config & Assumptions'!B41>=7,Z23,0)+IF('⚙ Config & Assumptions'!B41>=8,AD23,0)+IF('⚙ Config & Assumptions'!B41>=9,AH23,0)+IF('⚙ Config & Assumptions'!B41>=10,AL23,0)+IF('⚙ Config & Assumptions'!B41>=11,AP23,0)+IF('⚙ Config & Assumptions'!B41>=12,AT23,0) -> 1475 | BC23: =IF(AND('⚙ Config & Assumptions'!B41>=1,C23<>""),C23,0)+IF(AND('⚙ Config & Assumptions'!B41>=2,G23<>""),G23,0)+IF(AND('⚙ Config & Assumptions'!B41>=3,K23<>""),K23,0)+IF(AND('⚙ Config & Assumptions'!B41>=4,O23<>""),O23,0)+IF(AND('⚙ Config & Assumptions'!B41>=5,S23<>""),S23,0)+IF(AND('⚙ Config & Assumptions'!B41>=6,W23<>""),W23,0)+IF(AND('⚙ Config & Assumptions'!B41>=7,AA23<>""),AA23,0)+IF(AND('⚙ Config & Assumptions'!B41>=8,AE23<>""),AE23,0)+IF(AND('⚙ Config & Assumptions'!B41>=9,AI23<>""),AI23,0)+IF(AND('⚙ Config & Assumptions'!B41>=10,AM23<>""),AM23,0)+IF(AND('⚙ Config & Assumptions'!B41>=11,AQ23<>""),AQ23,0)+IF(AND('⚙ Config & Assumptions'!B41>=12,AU23<>""),AU23,0) -> 0 | BD23: =IF(BC23=0,"",BC23-BB23) | BE23: =IF(OR(BC23=0,BB23=0),"",(BC23-BB23)/BB23)
A24: Taxes — TCS + GST (₹) | B24: =ROUND('⚙ Config & Assumptions'!B5*'⚙ Config & Assumptions'!B7*(1-'⚙ Config & Assumptions'!B22)*('⚙ Config & Assumptions'!B21*'⚙ Config & Assumptions'!B31+'⚙ Config & Assumptions'!B25*'⚙ Config & Assumptions'!B33),0) -> 231 | D24: =IF(C24="","",C24-B24) | E24: =IF(OR(C24="",B24=0),"",(C24-B24)/B24) | F24: =ROUND('⚙ Config & Assumptions'!B5*'⚙ Config & Assumptions'!B8*(1-'⚙ Config & Assumptions'!B22)*('⚙ Config & Assumptions'!B21*'⚙ Config & Assumptions'!B31+'⚙ Config & Assumptions'!B25*'⚙ Config & Assumptions'!B33),0) -> 247 | H24: =IF(G24="","",G24-F24) | I24: =IF(OR(G24="",F24=0),"",(G24-F24)/F24) | J24: =ROUND('⚙ Config & Assumptions'!B5*'⚙ Config & Assumptions'!B9*(1-'⚙ Config & Assumptions'!B22)*('⚙ Config & Assumptions'!B21*'⚙ Config & Assumptions'!B31+'⚙ Config & Assumptions'!B25*'⚙ Config & Assumptions'!B33),0) -> 214 | L24: =IF(K24="","",K24-J24) | M24: =IF(OR(K24="",J24=0),"",(K24-J24)/J24) | N24: =ROUND('⚙ Config & Assumptions'!B5*'⚙ Config & Assumptions'!B10*(1-'⚙ Config & Assumptions'!B22)*('⚙ Config & Assumptions'!B21*'⚙ Config & Assumptions'!B31+'⚙ Config & Assumptions'!B25*'⚙ Config & Assumptions'!B33),0) -> 247 | P24: =IF(O24="","",O24-N24) | Q24: =IF(OR(O24="",N24=0),"",(O24-N24)/N24) | R24: =ROUND('⚙ Config & Assumptions'!B5*'⚙ Config & Assumptions'!B11*(1-'⚙ Config & Assumptions'!B22)*('⚙ Config & Assumptions'!B21*'⚙ Config & Assumptions'!B31+'⚙ Config & Assumptions'!B25*'⚙ Config & Assumptions'!B33),0) -> 297 | T24: =IF(S24="","",S24-R24) | U24: =IF(OR(S24="",R24=0),"",(S24-R24)/R24) | V24: =ROUND('⚙ Config & Assumptions'!B5*'⚙ Config & Assumptions'!B12*(1-'⚙ Config & Assumptions'!B22)*('⚙ Config & Assumptions'!B21*'⚙ Config & Assumptions'!B31+'⚙ Config & Assumptions'!B25*'⚙ Config & Assumptions'!B33),0) -> 313 | X24: =IF(W24="","",W24-V24) | Y24: =IF(OR(W24="",V24=0),"",(W24-V24)/V24) | Z24: =ROUND('⚙ Config & Assumptions'!B5*'⚙ Config & Assumptions'!B13*(1-'⚙ Config & Assumptions'!B22)*('⚙ Config & Assumptions'!B21*'⚙ Config & Assumptions'!B31+'⚙ Config & Assumptions'!B25*'⚙ Config & Assumptions'!B33),0) -> 330 | AB24: =IF(AA24="","",AA24-Z24) | AC24: =IF(OR(AA24="",Z24=0),"",(AA24-Z24)/Z24) | AD24: =ROUND('⚙ Config & Assumptions'!B5*'⚙ Config & Assumptions'!B14*(1-'⚙ Config & Assumptions'!B22)*('⚙ Config & Assumptions'!B21*'⚙ Config & Assumptions'!B31+'⚙ Config & Assumptions'!B25*'⚙ Config & Assumptions'!B33),0) -> 313 | AF24: =IF(AE24="","",AE24-AD24) | AG24: =IF(OR(AE24="",AD24=0),"",(AE24-AD24)/AD24) | AH24: =ROUND('⚙ Config & Assumptions'!B5*'⚙ Config & Assumptions'!B15*(1-'⚙ Config & Assumptions'!B22)*('⚙ Config & Assumptions'!B21*'⚙ Config & Assumptions'!B31+'⚙ Config & Assumptions'!B25*'⚙ Config & Assumptions'!B33),0) -> 297 | AJ24: =IF(AI24="","",AI24-AH24) | AK24: =IF(OR(AI24="",AH24=0),"",(AI24-AH24)/AH24) | AL24: =ROUND('⚙ Config & Assumptions'!B5*'⚙ Config & Assumptions'!B16*(1-'⚙ Config & Assumptions'!B22)*('⚙ Config & Assumptions'!B21*'⚙ Config & Assumptions'!B31+'⚙ Config & Assumptions'!B25*'⚙ Config & Assumptions'!B33),0) -> 297 | AN24: =IF(AM24="","",AM24-AL24) | AO24: =IF(OR(AM24="",AL24=0),"",(AM24-AL24)/AL24) | AP24: =ROUND('⚙ Config & Assumptions'!B5*'⚙ Config & Assumptions'!B17*(1-'⚙ Config & Assumptions'!B22)*('⚙ Config & Assumptions'!B21*'⚙ Config & Assumptions'!B31+'⚙ Config & Assumptions'!B25*'⚙ Config & Assumptions'!B33),0) -> 280 | AR24: =IF(AQ24="","",AQ24-AP24) | AS24: =IF(OR(AQ24="",AP24=0),"",(AQ24-AP24)/AP24) | AT24: =ROUND('⚙ Config & Assumptions'!B5*'⚙ Config & Assumptions'!B18*(1-'⚙ Config & Assumptions'!B22)*('⚙ Config & Assumptions'!B21*'⚙ Config & Assumptions'!B31+'⚙ Config & Assumptions'!B25*'⚙ Config & Assumptions'!B33),0) -> 231 | AV24: =IF(AU24="","",AU24-AT24) | AW24: =IF(OR(AU24="",AT24=0),"",(AU24-AT24)/AT24) | AX24: =CHOOSE('⚙ Config & Assumptions'!B41,B24,F24,J24,N24,R24,V24,Z24,AD24,AH24,AL24,AP24,AT24) -> 231 | AY24: =IF(CHOOSE('⚙ Config & Assumptions'!B41,C24,G24,K24,O24,S24,W24,AA24,AE24,AI24,AM24,AQ24,AU24)="","",CHOOSE('⚙ Config & Assumptions'!B41,C24,G24,K24,O24,S24,W24,AA24,AE24,AI24,AM24,AQ24,AU24)) | AZ24: =IF(AY24="","",AY24-AX24) | BA24: =IF(OR(AY24="",AX24=0),"",(AY24-AX24)/AX24) | BB24: =IF('⚙ Config & Assumptions'!B41>=1,B24,0)+IF('⚙ Config & Assumptions'!B41>=2,F24,0)+IF('⚙ Config & Assumptions'!B41>=3,J24,0)+IF('⚙ Config & Assumptions'!B41>=4,N24,0)+IF('⚙ Config & Assumptions'!B41>=5,R24,0)+IF('⚙ Config & Assumptions'!B41>=6,V24,0)+IF('⚙ Config & Assumptions'!B41>=7,Z24,0)+IF('⚙ Config & Assumptions'!B41>=8,AD24,0)+IF('⚙ Config & Assumptions'!B41>=9,AH24,0)+IF('⚙ Config & Assumptions'!B41>=10,AL24,0)+IF('⚙ Config & Assumptions'!B41>=11,AP24,0)+IF('⚙ Config & Assumptions'!B41>=12,AT24,0) -> 231 | BC24: =IF(AND('⚙ Config & Assumptions'!B41>=1,C24<>""),C24,0)+IF(AND('⚙ Config & Assumptions'!B41>=2,G24<>""),G24,0)+IF(AND('⚙ Config & Assumptions'!B41>=3,K24<>""),K24,0)+IF(AND('⚙ Config & Assumptions'!B41>=4,O24<>""),O24,0)+IF(AND('⚙ Config & Assumptions'!B41>=5,S24<>""),S24,0)+IF(AND('⚙ Config & Assumptions'!B41>=6,W24<>""),W24,0)+IF(AND('⚙ Config & Assumptions'!B41>=7,AA24<>""),AA24,0)+IF(AND('⚙ Config & Assumptions'!B41>=8,AE24<>""),AE24,0)+IF(AND('⚙ Config & Assumptions'!B41>=9,AI24<>""),AI24,0)+IF(AND('⚙ Config & Assumptions'!B41>=10,AM24<>""),AM24,0)+IF(AND('⚙ Config & Assumptions'!B41>=11,AQ24<>""),AQ24,0)+IF(AND('⚙ Config & Assumptions'!B41>=12,AU24<>""),AU24,0) -> 0 | BD24: =IF(BC24=0,"",BC24-BB24) | BE24: =IF(OR(BC24=0,BB24=0),"",(BC24-BB24)/BB24)
A25: ⇒ Total Variable Cost excl. COGS (₹) | B25: =B21+B22+B23+B24 -> 2685 | D25: =IF(C25="","",C25-B25) | E25: =IF(OR(C25="",B25=0),"",(C25-B25)/B25) | F25: =F21+F22+F23+F24 -> 2771 | H25: =IF(G25="","",G25-F25) | I25: =IF(OR(G25="",F25=0),"",(G25-F25)/F25) | J25: =J21+J22+J23+J24 -> 2598 | L25: =IF(K25="","",K25-J25) | M25: =IF(OR(K25="",J25=0),"",(K25-J25)/J25) | N25: =N21+N22+N23+N24 -> 2771 | P25: =IF(O25="","",O25-N25) | Q25: =IF(OR(O25="",N25=0),"",(O25-N25)/N25) | R25: =R21+R22+R23+R24 -> 3030 | T25: =IF(S25="","",S25-R25) | U25: =IF(OR(S25="",R25=0),"",(S25-R25)/R25) | V25: =V21+V22+V23+V24 -> 3116 | X25: =IF(W25="","",W25-V25) | Y25: =IF(OR(W25="",V25=0),"",(W25-V25)/V25) | Z25: =Z21+Z22+Z23+Z24 -> 3203 | AB25: =IF(AA25="","",AA25-Z25) | AC25: =IF(OR(AA25="",Z25=0),"",(AA25-Z25)/Z25) | AD25: =AD21+AD22+AD23+AD24 -> 3116 | AF25: =IF(AE25="","",AE25-AD25) | AG25: =IF(OR(AE25="",AD25=0),"",(AE25-AD25)/AD25) | AH25: =AH21+AH22+AH23+AH24 -> 3030 | AJ25: =IF(AI25="","",AI25-AH25) | AK25: =IF(OR(AI25="",AH25=0),"",(AI25-AH25)/AH25) | AL25: =AL21+AL22+AL23+AL24 -> 3030 | AN25: =IF(AM25="","",AM25-AL25) | AO25: =IF(OR(AM25="",AL25=0),"",(AM25-AL25)/AL25) | AP25: =AP21+AP22+AP23+AP24 -> 2943 | AR25: =IF(AQ25="","",AQ25-AP25) | AS25: =IF(OR(AQ25="",AP25=0),"",(AQ25-AP25)/AP25) | AT25: =AT21+AT22+AT23+AT24 -> 2685 | AV25: =IF(AU25="","",AU25-AT25) | AW25: =IF(OR(AU25="",AT25=0),"",(AU25-AT25)/AT25) | AX25: =CHOOSE('⚙ Config & Assumptions'!B41,B25,F25,J25,N25,R25,V25,Z25,AD25,AH25,AL25,AP25,AT25) -> 2685 | AY25: =IF(CHOOSE('⚙ Config & Assumptions'!B41,C25,G25,K25,O25,S25,W25,AA25,AE25,AI25,AM25,AQ25,AU25)="","",CHOOSE('⚙ Config & Assumptions'!B41,C25,G25,K25,O25,S25,W25,AA25,AE25,AI25,AM25,AQ25,AU25)) | AZ25: =IF(AY25="","",AY25-AX25) | BA25: =IF(OR(AY25="",AX25=0),"",(AY25-AX25)/AX25) | BB25: =IF('⚙ Config & Assumptions'!B41>=1,B25,0)+IF('⚙ Config & Assumptions'!B41>=2,F25,0)+IF('⚙ Config & Assumptions'!B41>=3,J25,0)+IF('⚙ Config & Assumptions'!B41>=4,N25,0)+IF('⚙ Config & Assumptions'!B41>=5,R25,0)+IF('⚙ Config & Assumptions'!B41>=6,V25,0)+IF('⚙ Config & Assumptions'!B41>=7,Z25,0)+IF('⚙ Config & Assumptions'!B41>=8,AD25,0)+IF('⚙ Config & Assumptions'!B41>=9,AH25,0)+IF('⚙ Config & Assumptions'!B41>=10,AL25,0)+IF('⚙ Config & Assumptions'!B41>=11,AP25,0)+IF('⚙ Config & Assumptions'!B41>=12,AT25,0) -> 2685 | BC25: =IF(AND('⚙ Config & Assumptions'!B41>=1,C25<>""),C25,0)+IF(AND('⚙ Config & Assumptions'!B41>=2,G25<>""),G25,0)+IF(AND('⚙ Config & Assumptions'!B41>=3,K25<>""),K25,0)+IF(AND('⚙ Config & Assumptions'!B41>=4,O25<>""),O25,0)+IF(AND('⚙ Config & Assumptions'!B41>=5,S25<>""),S25,0)+IF(AND('⚙ Config & Assumptions'!B41>=6,W25<>""),W25,0)+IF(AND('⚙ Config & Assumptions'!B41>=7,AA25<>""),AA25,0)+IF(AND('⚙ Config & Assumptions'!B41>=8,AE25<>""),AE25,0)+IF(AND('⚙ Config & Assumptions'!B41>=9,AI25<>""),AI25,0)+IF(AND('⚙ Config & Assumptions'!B41>=10,AM25<>""),AM25,0)+IF(AND('⚙ Config & Assumptions'!B41>=11,AQ25<>""),AQ25,0)+IF(AND('⚙ Config & Assumptions'!B41>=12,AU25<>""),AU25,0) -> 0 | BD25: =IF(BC25=0,"",BC25-BB25) | BE25: =IF(OR(BC25=0,BB25=0),"",(BC25-BB25)/BB25)
A26: ⑥ OPERATING PROFIT / (LOSS)
A27: ⇒ Operating Profit / (Loss) (₹) | B27: =B18-B25 -> 1946 | D27: =IF(C27="","",C27-B27) | E27: =IF(OR(C27="",B27=0),"",(C27-B27)/B27) | F27: =F18-F25 -> 2191 | H27: =IF(G27="","",G27-F27) | I27: =IF(OR(G27="",F27=0),"",(G27-F27)/F27) | J27: =J18-J25 -> 1703 | L27: =IF(K27="","",K27-J27) | M27: =IF(OR(K27="",J27=0),"",(K27-J27)/J27) | N27: =N18-N25 -> 2191 | P27: =IF(O27="","",O27-N27) | Q27: =IF(OR(O27="",N27=0),"",(O27-N27)/N27) | R27: =R18-R25 -> 2925 | T27: =IF(S27="","",S27-R27) | U27: =IF(OR(S27="",R27=0),"",(S27-R27)/R27) | V27: =V18-V25 -> 3169 | X27: =IF(W27="","",W27-V27) | Y27: =IF(OR(W27="",V27=0),"",(W27-V27)/V27) | Z27: =Z18-Z25 -> 3413 | AB27: =IF(AA27="","",AA27-Z27) | AC27: =IF(OR(AA27="",Z27=0),"",(AA27-Z27)/Z27) | AD27: =AD18-AD25 -> 3169 | AF27: =IF(AE27="","",AE27-AD27) | AG27: =IF(OR(AE27="",AD27=0),"",(AE27-AD27)/AD27) | AH27: =AH18-AH25 -> 2925 | AJ27: =IF(AI27="","",AI27-AH27) | AK27: =IF(OR(AI27="",AH27=0),"",(AI27-AH27)/AH27) | AL27: =AL18-AL25 -> 2925 | AN27: =IF(AM27="","",AM27-AL27) | AO27: =IF(OR(AM27="",AL27=0),"",(AM27-AL27)/AL27) | AP27: =AP18-AP25 -> 2681 | AR27: =IF(AQ27="","",AQ27-AP27) | AS27: =IF(OR(AQ27="",AP27=0),"",(AQ27-AP27)/AP27) | AT27: =AT18-AT25 -> 1946 | AV27: =IF(AU27="","",AU27-AT27) | AW27: =IF(OR(AU27="",AT27=0),"",(AU27-AT27)/AT27) | AX27: =CHOOSE('⚙ Config & Assumptions'!B41,B27,F27,J27,N27,R27,V27,Z27,AD27,AH27,AL27,AP27,AT27) -> 1946 | AY27: =IF(CHOOSE('⚙ Config & Assumptions'!B41,C27,G27,K27,O27,S27,W27,AA27,AE27,AI27,AM27,AQ27,AU27)="","",CHOOSE('⚙ Config & Assumptions'!B41,C27,G27,K27,O27,S27,W27,AA27,AE27,AI27,AM27,AQ27,AU27)) | AZ27: =IF(AY27="","",AY27-AX27) | BA27: =IF(OR(AY27="",AX27=0),"",(AY27-AX27)/AX27) | BB27: =IF('⚙ Config & Assumptions'!B41>=1,B27,0)+IF('⚙ Config & Assumptions'!B41>=2,F27,0)+IF('⚙ Config & Assumptions'!B41>=3,J27,0)+IF('⚙ Config & Assumptions'!B41>=4,N27,0)+IF('⚙ Config & Assumptions'!B41>=5,R27,0)+IF('⚙ Config & Assumptions'!B41>=6,V27,0)+IF('⚙ Config & Assumptions'!B41>=7,Z27,0)+IF('⚙ Config & Assumptions'!B41>=8,AD27,0)+IF('⚙ Config & Assumptions'!B41>=9,AH27,0)+IF('⚙ Config & Assumptions'!B41>=10,AL27,0)+IF('⚙ Config & Assumptions'!B41>=11,AP27,0)+IF('⚙ Config & Assumptions'!B41>=12,AT27,0) -> 1946 | BC27: =IF(AND('⚙ Config & Assumptions'!B41>=1,C27<>""),C27,0)+IF(AND('⚙ Config & Assumptions'!B41>=2,G27<>""),G27,0)+IF(AND('⚙ Config & Assumptions'!B41>=3,K27<>""),K27,0)+IF(AND('⚙ Config & Assumptions'!B41>=4,O27<>""),O27,0)+IF(AND('⚙ Config & Assumptions'!B41>=5,S27<>""),S27,0)+IF(AND('⚙ Config & Assumptions'!B41>=6,W27<>""),W27,0)+IF(AND('⚙ Config & Assumptions'!B41>=7,AA27<>""),AA27,0)+IF(AND('⚙ Config & Assumptions'!B41>=8,AE27<>""),AE27,0)+IF(AND('⚙ Config & Assumptions'!B41>=9,AI27<>""),AI27,0)+IF(AND('⚙ Config & Assumptions'!B41>=10,AM27<>""),AM27,0)+IF(AND('⚙ Config & Assumptions'!B41>=11,AQ27<>""),AQ27,0)+IF(AND('⚙ Config & Assumptions'!B41>=12,AU27<>""),AU27,0) -> 0 | BD27: =IF(BC27=0,"",BC27-BB27) | BE27: =IF(OR(BC27=0,BB27=0),"",(BC27-BB27)/BB27)
A28: Operating Margin (%) | B28: =IF(B14=0,0,B27/B14) -> 0.17274745 | D28: =IF(C28="","",C28-B28) | E28: =IF(OR(C28="",B28=0),"",(C28-B28)/B28) | F28: =IF(F14=0,0,F27/F14) -> 0.18153948 | H28: =IF(G28="","",G28-F28) | I28: =IF(OR(G28="",F28=0),"",(G28-F28)/F28) | J28: =IF(J14=0,0,J27/J14) -> 0.16281071 | L28: =IF(K28="","",K28-J28) | M28: =IF(OR(K28="",J28=0),"",(K28-J28)/J28) | N28: =IF(N14=0,0,N27/N14) -> 0.18153948 | P28: =IF(O28="","",O28-N28) | Q28: =IF(OR(O28="",N28=0),"",(O28-N28)/N28) | R28: =IF(R14=0,0,R27/R14) -> 0.20196092 | T28: =IF(S28="","",S28-R28) | U28: =IF(OR(S28="",R28=0),"",(S28-R28)/R28) | V28: =IF(V14=0,0,V27/V14) -> 0.20728676 | X28: =IF(W28="","",W28-V28) | Y28: =IF(OR(W28="",V28=0),"",(W28-V28)/V28) | Z28: =IF(Z14=0,0,Z27/Z14) -> 0.21209297 | AB28: =IF(AA28="","",AA28-Z28) | AC28: =IF(OR(AA28="",Z28=0),"",(AA28-Z28)/Z28) | AD28: =IF(AD14=0,0,AD27/AD14) -> 0.20728676 | AF28: =IF(AE28="","",AE28-AD28) | AG28: =IF(OR(AE28="",AD28=0),"",(AE28-AD28)/AD28) | AH28: =IF(AH14=0,0,AH27/AH14) -> 0.20196092 | AJ28: =IF(AI28="","",AI28-AH28) | AK28: =IF(OR(AI28="",AH28=0),"",(AI28-AH28)/AH28) | AL28: =IF(AL14=0,0,AL27/AL14) -> 0.20196092 | AN28: =IF(AM28="","",AM28-AL28) | AO28: =IF(OR(AM28="",AL28=0),"",(AM28-AL28)/AL28) | AP28: =IF(AP14=0,0,AP27/AP14) -> 0.19600819 | AR28: =IF(AQ28="","",AQ28-AP28) | AS28: =IF(OR(AQ28="",AP28=0),"",(AQ28-AP28)/AP28) | AT28: =IF(AT14=0,0,AT27/AT14) -> 0.17274745 | AV28: =IF(AU28="","",AU28-AT28) | AW28: =IF(OR(AU28="",AT28=0),"",(AU28-AT28)/AT28) | AX28: =CHOOSE('⚙ Config & Assumptions'!B41,B28,F28,J28,N28,R28,V28,Z28,AD28,AH28,AL28,AP28,AT28) -> 0.17274745 | AY28: =IF(CHOOSE('⚙ Config & Assumptions'!B41,C28,G28,K28,O28,S28,W28,AA28,AE28,AI28,AM28,AQ28,AU28)="","",CHOOSE('⚙ Config & Assumptions'!B41,C28,G28,K28,O28,S28,W28,AA28,AE28,AI28,AM28,AQ28,AU28)) | AZ28: =IF(AY28="","",AY28-AX28) | BA28: =IF(OR(AY28="",AX28=0),"",(AY28-AX28)/AX28) | BB28: =IF('⚙ Config & Assumptions'!B41>=1,B28,0)+IF('⚙ Config & Assumptions'!B41>=2,F28,0)+IF('⚙ Config & Assumptions'!B41>=3,J28,0)+IF('⚙ Config & Assumptions'!B41>=4,N28,0)+IF('⚙ Config & Assumptions'!B41>=5,R28,0)+IF('⚙ Config & Assumptions'!B41>=6,V28,0)+IF('⚙ Config & Assumptions'!B41>=7,Z28,0)+IF('⚙ Config & Assumptions'!B41>=8,AD28,0)+IF('⚙ Config & Assumptions'!B41>=9,AH28,0)+IF('⚙ Config & Assumptions'!B41>=10,AL28,0)+IF('⚙ Config & Assumptions'!B41>=11,AP28,0)+IF('⚙ Config & Assumptions'!B41>=12,AT28,0) -> 0.17274745 | BC28: =IF(AND('⚙ Config & Assumptions'!B41>=1,C28<>""),C28,0)+IF(AND('⚙ Config & Assumptions'!B41>=2,G28<>""),G28,0)+IF(AND('⚙ Config & Assumptions'!B41>=3,K28<>""),K28,0)+IF(AND('⚙ Config & Assumptions'!B41>=4,O28<>""),O28,0)+IF(AND('⚙ Config & Assumptions'!B41>=5,S28<>""),S28,0)+IF(AND('⚙ Config & Assumptions'!B41>=6,W28<>""),W28,0)+IF(AND('⚙ Config & Assumptions'!B41>=7,AA28<>""),AA28,0)+IF(AND('⚙ Config & Assumptions'!B41>=8,AE28<>""),AE28,0)+IF(AND('⚙ Config & Assumptions'!B41>=9,AI28<>""),AI28,0)+IF(AND('⚙ Config & Assumptions'!B41>=10,AM28<>""),AM28,0)+IF(AND('⚙ Config & Assumptions'!B41>=11,AQ28<>""),AQ28,0)+IF(AND('⚙ Config & Assumptions'!B41>=12,AU28<>""),AU28,0) -> 0 | BD28: =IF(BC28=0,"",BC28-BB28) | BE28: =IF(OR(BC28=0,BB28=0),"",(BC28-BB28)/BB28)
A29: ⑦ TDS (Recoverable)
A30: TDS Deducted (₹) | B30: =ROUND('⚙ Config & Assumptions'!B5*'⚙ Config & Assumptions'!B7*(1-'⚙ Config & Assumptions'!B22)*'⚙ Config & Assumptions'!B21*'⚙ Config & Assumptions'!B32,0) -> 11 | D30: =IF(C30="","",C30-B30) | E30: =IF(OR(C30="",B30=0),"",(C30-B30)/B30) | F30: =ROUND('⚙ Config & Assumptions'!B5*'⚙ Config & Assumptions'!B8*(1-'⚙ Config & Assumptions'!B22)*'⚙ Config & Assumptions'!B21*'⚙ Config & Assumptions'!B32,0) -> 12 | H30: =IF(G30="","",G30-F30) | I30: =IF(OR(G30="",F30=0),"",(G30-F30)/F30) | J30: =ROUND('⚙ Config & Assumptions'!B5*'⚙ Config & Assumptions'!B9*(1-'⚙ Config & Assumptions'!B22)*'⚙ Config & Assumptions'!B21*'⚙ Config & Assumptions'!B32,0) -> 10 | L30: =IF(K30="","",K30-J30) | M30: =IF(OR(K30="",J30=0),"",(K30-J30)/J30) | N30: =ROUND('⚙ Config & Assumptions'!B5*'⚙ Config & Assumptions'!B10*(1-'⚙ Config & Assumptions'!B22)*'⚙ Config & Assumptions'!B21*'⚙ Config & Assumptions'!B32,0) -> 12 | P30: =IF(O30="","",O30-N30) | Q30: =IF(OR(O30="",N30=0),"",(O30-N30)/N30) | R30: =ROUND('⚙ Config & Assumptions'!B5*'⚙ Config & Assumptions'!B11*(1-'⚙ Config & Assumptions'!B22)*'⚙ Config & Assumptions'!B21*'⚙ Config & Assumptions'!B32,0) -> 14 | T30: =IF(S30="","",S30-R30) | U30: =IF(OR(S30="",R30=0),"",(S30-R30)/R30) | V30: =ROUND('⚙ Config & Assumptions'!B5*'⚙ Config & Assumptions'!B12*(1-'⚙ Config & Assumptions'!B22)*'⚙ Config & Assumptions'!B21*'⚙ Config & Assumptions'!B32,0) -> 15 | X30: =IF(W30="","",W30-V30) | Y30: =IF(OR(W30="",V30=0),"",(W30-V30)/V30) | Z30: =ROUND('⚙ Config & Assumptions'!B5*'⚙ Config & Assumptions'!B13*(1-'⚙ Config & Assumptions'!B22)*'⚙ Config & Assumptions'!B21*'⚙ Config & Assumptions'!B32,0) -> 16 | AB30: =IF(AA30="","",AA30-Z30) | AC30: =IF(OR(AA30="",Z30=0),"",(AA30-Z30)/Z30) | AD30: =ROUND('⚙ Config & Assumptions'!B5*'⚙ Config & Assumptions'!B14*(1-'⚙ Config & Assumptions'!B22)*'⚙ Config & Assumptions'!B21*'⚙ Config & Assumptions'!B32,0) -> 15 | AF30: =IF(AE30="","",AE30-AD30) | AG30: =IF(OR(AE30="",AD30=0),"",(AE30-AD30)/AD30) | AH30: =ROUND('⚙ Config & Assumptions'!B5*'⚙ Config & Assumptions'!B15*(1-'⚙ Config & Assumptions'!B22)*'⚙ Config & Assumptions'!B21*'⚙ Config & Assumptions'!B32,0) -> 14 | AJ30: =IF(AI30="","",AI30-AH30) | AK30: =IF(OR(AI30="",AH30=0),"",(AI30-AH30)/AH30) | AL30: =ROUND('⚙ Config & Assumptions'!B5*'⚙ Config & Assumptions'!B16*(1-'⚙ Config & Assumptions'!B22)*'⚙ Config & Assumptions'!B21*'⚙ Config & Assumptions'!B32,0) -> 14 | AN30: =IF(AM30="","",AM30-AL30) | AO30: =IF(OR(AM30="",AL30=0),"",(AM30-AL30)/AL30) | AP30: =ROUND('⚙ Config & Assumptions'!B5*'⚙ Config & Assumptions'!B17*(1-'⚙ Config & Assumptions'!B22)*'⚙ Config & Assumptions'!B21*'⚙ Config & Assumptions'!B32,0) -> 14 | AR30: =IF(AQ30="","",AQ30-AP30) | AS30: =IF(OR(AQ30="",AP30=0),"",(AQ30-AP30)/AP30) | AT30: =ROUND('⚙ Config & Assumptions'!B5*'⚙ Config & Assumptions'!B18*(1-'⚙ Config & Assumptions'!B22)*'⚙ Config & Assumptions'!B21*'⚙ Config & Assumptions'!B32,0) -> 11 | AV30: =IF(AU30="","",AU30-AT30) | AW30: =IF(OR(AU30="",AT30=0),"",(AU30-AT30)/AT30) | AX30: =CHOOSE('⚙ Config & Assumptions'!B41,B30,F30,J30,N30,R30,V30,Z30,AD30,AH30,AL30,AP30,AT30) -> 11 | AY30: =IF(CHOOSE('⚙ Config & Assumptions'!B41,C30,G30,K30,O30,S30,W30,AA30,AE30,AI30,AM30,AQ30,AU30)="","",CHOOSE('⚙ Config & Assumptions'!B41,C30,G30,K30,O30,S30,W30,AA30,AE30,AI30,AM30,AQ30,AU30)) | AZ30: =IF(AY30="","",AY30-AX30) | BA30: =IF(OR(AY30="",AX30=0),"",(AY30-AX30)/AX30) | BB30: =IF('⚙ Config & Assumptions'!B41>=1,B30,0)+IF('⚙ Config & Assumptions'!B41>=2,F30,0)+IF('⚙ Config & Assumptions'!B41>=3,J30,0)+IF('⚙ Config & Assumptions'!B41>=4,N30,0)+IF('⚙ Config & Assumptions'!B41>=5,R30,0)+IF('⚙ Config & Assumptions'!B41>=6,V30,0)+IF('⚙ Config & Assumptions'!B41>=7,Z30,0)+IF('⚙ Config & Assumptions'!B41>=8,AD30,0)+IF('⚙ Config & Assumptions'!B41>=9,AH30,0)+IF('⚙ Config & Assumptions'!B41>=10,AL30,0)+IF('⚙ Config & Assumptions'!B41>=11,AP30,0)+IF('⚙ Config & Assumptions'!B41>=12,AT30,0) -> 11 | BC30: =IF(AND('⚙ Config & Assumptions'!B41>=1,C30<>""),C30,0)+IF(AND('⚙ Config & Assumptions'!B41>=2,G30<>""),G30,0)+IF(AND('⚙ Config & Assumptions'!B41>=3,K30<>""),K30,0)+IF(AND('⚙ Config & Assumptions'!B41>=4,O30<>""),O30,0)+IF(AND('⚙ Config & Assumptions'!B41>=5,S30<>""),S30,0)+IF(AND('⚙ Config & Assumptions'!B41>=6,W30<>""),W30,0)+IF(AND('⚙ Config & Assumptions'!B41>=7,AA30<>""),AA30,0)+IF(AND('⚙ Config & Assumptions'!B41>=8,AE30<>""),AE30,0)+IF(AND('⚙ Config & Assumptions'!B41>=9,AI30<>""),AI30,0)+IF(AND('⚙ Config & Assumptions'!B41>=10,AM30<>""),AM30,0)+IF(AND('⚙ Config & Assumptions'!B41>=11,AQ30<>""),AQ30,0)+IF(AND('⚙ Config & Assumptions'!B41>=12,AU30<>""),AU30,0) -> 0 | BD30: =IF(BC30=0,"",BC30-BB30) | BE30: =IF(OR(BC30=0,BB30=0),"",(BC30-BB30)/BB30)
A31: ⑧ NET PROFIT
A32: ⇒ Net Profit / (Loss) (₹) | B32: =B27-B30 -> 1935 | D32: =IF(C32="","",C32-B32) | E32: =IF(OR(C32="",B32=0),"",(C32-B32)/B32) | F32: =F27-F30 -> 2179 | H32: =IF(G32="","",G32-F32) | I32: =IF(OR(G32="",F32=0),"",(G32-F32)/F32) | J32: =J27-J30 -> 1693 | L32: =IF(K32="","",K32-J32) | M32: =IF(OR(K32="",J32=0),"",(K32-J32)/J32) | N32: =N27-N30 -> 2179 | P32: =IF(O32="","",O32-N32) | Q32: =IF(OR(O32="",N32=0),"",(O32-N32)/N32) | R32: =R27-R30 -> 2911 | T32: =IF(S32="","",S32-R32) | U32: =IF(OR(S32="",R32=0),"",(S32-R32)/R32) | V32: =V27-V30 -> 3154 | X32: =IF(W32="","",W32-V32) | Y32: =IF(OR(W32="",V32=0),"",(W32-V32)/V32) | Z32: =Z27-Z30 -> 3397 | AB32: =IF(AA32="","",AA32-Z32) | AC32: =IF(OR(AA32="",Z32=0),"",(AA32-Z32)/Z32) | AD32: =AD27-AD30 -> 3154 | AF32: =IF(AE32="","",AE32-AD32) | AG32: =IF(OR(AE32="",AD32=0),"",(AE32-AD32)/AD32) | AH32: =AH27-AH30 -> 2911 | AJ32: =IF(AI32="","",AI32-AH32) | AK32: =IF(OR(AI32="",AH32=0),"",(AI32-AH32)/AH32) | AL32: =AL27-AL30 -> 2911 | AN32: =IF(AM32="","",AM32-AL32) | AO32: =IF(OR(AM32="",AL32=0),"",(AM32-AL32)/AL32) | AP32: =AP27-AP30 -> 2667 | AR32: =IF(AQ32="","",AQ32-AP32) | AS32: =IF(OR(AQ32="",AP32=0),"",(AQ32-AP32)/AP32) | AT32: =AT27-AT30 -> 1935 | AV32: =IF(AU32="","",AU32-AT32) | AW32: =IF(OR(AU32="",AT32=0),"",(AU32-AT32)/AT32) | AX32: =CHOOSE('⚙ Config & Assumptions'!B41,B32,F32,J32,N32,R32,V32,Z32,AD32,AH32,AL32,AP32,AT32) -> 1935 | AY32: =IF(CHOOSE('⚙ Config & Assumptions'!B41,C32,G32,K32,O32,S32,W32,AA32,AE32,AI32,AM32,AQ32,AU32)="","",CHOOSE('⚙ Config & Assumptions'!B41,C32,G32,K32,O32,S32,W32,AA32,AE32,AI32,AM32,AQ32,AU32)) | AZ32: =IF(AY32="","",AY32-AX32) | BA32: =IF(OR(AY32="",AX32=0),"",(AY32-AX32)/AX32) | BB32: =IF('⚙ Config & Assumptions'!B41>=1,B32,0)+IF('⚙ Config & Assumptions'!B41>=2,F32,0)+IF('⚙ Config & Assumptions'!B41>=3,J32,0)+IF('⚙ Config & Assumptions'!B41>=4,N32,0)+IF('⚙ Config & Assumptions'!B41>=5,R32,0)+IF('⚙ Config & Assumptions'!B41>=6,V32,0)+IF('⚙ Config & Assumptions'!B41>=7,Z32,0)+IF('⚙ Config & Assumptions'!B41>=8,AD32,0)+IF('⚙ Config & Assumptions'!B41>=9,AH32,0)+IF('⚙ Config & Assumptions'!B41>=10,AL32,0)+IF('⚙ Config & Assumptions'!B41>=11,AP32,0)+IF('⚙ Config & Assumptions'!B41>=12,AT32,0) -> 1935 | BC32: =IF(AND('⚙ Config & Assumptions'!B41>=1,C32<>""),C32,0)+IF(AND('⚙ Config & Assumptions'!B41>=2,G32<>""),G32,0)+IF(AND('⚙ Config & Assumptions'!B41>=3,K32<>""),K32,0)+IF(AND('⚙ Config & Assumptions'!B41>=4,O32<>""),O32,0)+IF(AND('⚙ Config & Assumptions'!B41>=5,S32<>""),S32,0)+IF(AND('⚙ Config & Assumptions'!B41>=6,W32<>""),W32,0)+IF(AND('⚙ Config & Assumptions'!B41>=7,AA32<>""),AA32,0)+IF(AND('⚙ Config & Assumptions'!B41>=8,AE32<>""),AE32,0)+IF(AND('⚙ Config & Assumptions'!B41>=9,AI32<>""),AI32,0)+IF(AND('⚙ Config & Assumptions'!B41>=10,AM32<>""),AM32,0)+IF(AND('⚙ Config & Assumptions'!B41>=11,AQ32<>""),AQ32,0)+IF(AND('⚙ Config & Assumptions'!B41>=12,AU32<>""),AU32,0) -> 0 | BD32: =IF(BC32=0,"",BC32-BB32) | BE32: =IF(OR(BC32=0,BB32=0),"",(BC32-BB32)/BB32)
A33: Net Margin (%) | B33: =IF(B14=0,0,B32/B14) -> 0.17177097 | D33: =IF(C33="","",C33-B33) | E33: =IF(OR(C33="",B33=0),"",(C33-B33)/B33) | F33: =IF(F14=0,0,F32/F14) -> 0.1805452 | H33: =IF(G33="","",G33-F33) | I33: =IF(OR(G33="",F33=0),"",(G33-F33)/F33) | J33: =IF(J14=0,0,J32/J14) -> 0.16185468 | L33: =IF(K33="","",K33-J33) | M33: =IF(OR(K33="",J33=0),"",(K33-J33)/J33) | N33: =IF(N14=0,0,N32/N14) -> 0.1805452 | P33: =IF(O33="","",O33-N33) | Q33: =IF(OR(O33="",N33=0),"",(O33-N33)/N33) | R33: =IF(R14=0,0,R32/R14) -> 0.20099427 | T33: =IF(S33="","",S33-R33) | U33: =IF(OR(S33="",R33=0),"",(S33-R33)/R33) | V33: =IF(V14=0,0,V32/V14) -> 0.2063056 | X33: =IF(W33="","",W33-V33) | Y33: =IF(OR(W33="",V33=0),"",(W33-V33)/V33) | Z33: =IF(Z14=0,0,Z32/Z14) -> 0.21109868 | AB33: =IF(AA33="","",AA33-Z33) | AC33: =IF(OR(AA33="",Z33=0),"",(AA33-Z33)/Z33) | AD33: =IF(AD14=0,0,AD32/AD14) -> 0.2063056 | AF33: =IF(AE33="","",AE33-AD33) | AG33: =IF(OR(AE33="",AD33=0),"",(AE33-AD33)/AD33) | AH33: =IF(AH14=0,0,AH32/AH14) -> 0.20099427 | AJ33: =IF(AI33="","",AI33-AH33) | AK33: =IF(OR(AI33="",AH33=0),"",(AI33-AH33)/AH33) | AL33: =IF(AL14=0,0,AL32/AL14) -> 0.20099427 | AN33: =IF(AM33="","",AM33-AL33) | AO33: =IF(OR(AM33="",AL33=0),"",(AM33-AL33)/AL33) | AP33: =IF(AP14=0,0,AP32/AP14) -> 0.19498465 | AR33: =IF(AQ33="","",AQ33-AP33) | AS33: =IF(OR(AQ33="",AP33=0),"",(AQ33-AP33)/AP33) | AT33: =IF(AT14=0,0,AT32/AT14) -> 0.17177097 | AV33: =IF(AU33="","",AU33-AT33) | AW33: =IF(OR(AU33="",AT33=0),"",(AU33-AT33)/AT33) | AX33: =CHOOSE('⚙ Config & Assumptions'!B41,B33,F33,J33,N33,R33,V33,Z33,AD33,AH33,AL33,AP33,AT33) -> 0.17177097 | AY33: =IF(CHOOSE('⚙ Config & Assumptions'!B41,C33,G33,K33,O33,S33,W33,AA33,AE33,AI33,AM33,AQ33,AU33)="","",CHOOSE('⚙ Config & Assumptions'!B41,C33,G33,K33,O33,S33,W33,AA33,AE33,AI33,AM33,AQ33,AU33)) | AZ33: =IF(AY33="","",AY33-AX33) | BA33: =IF(OR(AY33="",AX33=0),"",(AY33-AX33)/AX33) | BB33: =IF('⚙ Config & Assumptions'!B41>=1,B33,0)+IF('⚙ Config & Assumptions'!B41>=2,F33,0)+IF('⚙ Config & Assumptions'!B41>=3,J33,0)+IF('⚙ Config & Assumptions'!B41>=4,N33,0)+IF('⚙ Config & Assumptions'!B41>=5,R33,0)+IF('⚙ Config & Assumptions'!B41>=6,V33,0)+IF('⚙ Config & Assumptions'!B41>=7,Z33,0)+IF('⚙ Config & Assumptions'!B41>=8,AD33,0)+IF('⚙ Config & Assumptions'!B41>=9,AH33,0)+IF('⚙ Config & Assumptions'!B41>=10,AL33,0)+IF('⚙ Config & Assumptions'!B41>=11,AP33,0)+IF('⚙ Config & Assumptions'!B41>=12,AT33,0) -> 0.17177097 | BC33: =IF(AND('⚙ Config & Assumptions'!B41>=1,C33<>""),C33,0)+IF(AND('⚙ Config & Assumptions'!B41>=2,G33<>""),G33,0)+IF(AND('⚙ Config & Assumptions'!B41>=3,K33<>""),K33,0)+IF(AND('⚙ Config & Assumptions'!B41>=4,O33<>""),O33,0)+IF(AND('⚙ Config & Assumptions'!B41>=5,S33<>""),S33,0)+IF(AND('⚙ Config & Assumptions'!B41>=6,W33<>""),W33,0)+IF(AND('⚙ Config & Assumptions'!B41>=7,AA33<>""),AA33,0)+IF(AND('⚙ Config & Assumptions'!B41>=8,AE33<>""),AE33,0)+IF(AND('⚙ Config & Assumptions'!B41>=9,AI33<>""),AI33,0)+IF(AND('⚙ Config & Assumptions'!B41>=10,AM33<>""),AM33,0)+IF(AND('⚙ Config & Assumptions'!B41>=11,AQ33<>""),AQ33,0)+IF(AND('⚙ Config & Assumptions'!B41>=12,AU33<>""),AU33,0) -> 0 | BD33: =IF(BC33=0,"",BC33-BB33) | BE33: =IF(OR(BC33=0,BB33=0),"",(BC33-BB33)/BB33)
A34: ⑨ FIXED OVERHEADS
A35: Fixed Overheads (₹) | B35: =ROUND('⚙ Config & Assumptions'!B39/12,0) -> 0 | D35: =IF(C35="","",C35-B35) | E35: =IF(OR(C35="",B35=0),"",(C35-B35)/B35) | F35: =ROUND('⚙ Config & Assumptions'!B39/12,0) -> 0 | H35: =IF(G35="","",G35-F35) | I35: =IF(OR(G35="",F35=0),"",(G35-F35)/F35) | J35: =ROUND('⚙ Config & Assumptions'!B39/12,0) -> 0 | L35: =IF(K35="","",K35-J35) | M35: =IF(OR(K35="",J35=0),"",(K35-J35)/J35) | N35: =ROUND('⚙ Config & Assumptions'!B39/12,0) -> 0 | P35: =IF(O35="","",O35-N35) | Q35: =IF(OR(O35="",N35=0),"",(O35-N35)/N35) | R35: =ROUND('⚙ Config & Assumptions'!B39/12,0) -> 0 | T35: =IF(S35="","",S35-R35) | U35: =IF(OR(S35="",R35=0),"",(S35-R35)/R35) | V35: =ROUND('⚙ Config & Assumptions'!B39/12,0) -> 0 | X35: =IF(W35="","",W35-V35) | Y35: =IF(OR(W35="",V35=0),"",(W35-V35)/V35) | Z35: =ROUND('⚙ Config & Assumptions'!B39/12,0) -> 0 | AB35: =IF(AA35="","",AA35-Z35) | AC35: =IF(OR(AA35="",Z35=0),"",(AA35-Z35)/Z35) | AD35: =ROUND('⚙ Config & Assumptions'!B39/12,0) -> 0 | AF35: =IF(AE35="","",AE35-AD35) | AG35: =IF(OR(AE35="",AD35=0),"",(AE35-AD35)/AD35) | AH35: =ROUND('⚙ Config & Assumptions'!B39/12,0) -> 0 | AJ35: =IF(AI35="","",AI35-AH35) | AK35: =IF(OR(AI35="",AH35=0),"",(AI35-AH35)/AH35) | AL35: =ROUND('⚙ Config & Assumptions'!B39/12,0) -> 0 | AN35: =IF(AM35="","",AM35-AL35) | AO35: =IF(OR(AM35="",AL35=0),"",(AM35-AL35)/AL35) | AP35: =ROUND('⚙ Config & Assumptions'!B39/12,0) -> 0 | AR35: =IF(AQ35="","",AQ35-AP35) | AS35: =IF(OR(AQ35="",AP35=0),"",(AQ35-AP35)/AP35) | AT35: =ROUND('⚙ Config & Assumptions'!B39/12,0) -> 0 | AV35: =IF(AU35="","",AU35-AT35) | AW35: =IF(OR(AU35="",AT35=0),"",(AU35-AT35)/AT35) | AX35: =CHOOSE('⚙ Config & Assumptions'!B41,B35,F35,J35,N35,R35,V35,Z35,AD35,AH35,AL35,AP35,AT35) -> 0 | AY35: =IF(CHOOSE('⚙ Config & Assumptions'!B41,C35,G35,K35,O35,S35,W35,AA35,AE35,AI35,AM35,AQ35,AU35)="","",CHOOSE('⚙ Config & Assumptions'!B41,C35,G35,K35,O35,S35,W35,AA35,AE35,AI35,AM35,AQ35,AU35)) | AZ35: =IF(AY35="","",AY35-AX35) | BA35: =IF(OR(AY35="",AX35=0),"",(AY35-AX35)/AX35) | BB35: =IF('⚙ Config & Assumptions'!B41>=1,B35,0)+IF('⚙ Config & Assumptions'!B41>=2,F35,0)+IF('⚙ Config & Assumptions'!B41>=3,J35,0)+IF('⚙ Config & Assumptions'!B41>=4,N35,0)+IF('⚙ Config & Assumptions'!B41>=5,R35,0)+IF('⚙ Config & Assumptions'!B41>=6,V35,0)+IF('⚙ Config & Assumptions'!B41>=7,Z35,0)+IF('⚙ Config & Assumptions'!B41>=8,AD35,0)+IF('⚙ Config & Assumptions'!B41>=9,AH35,0)+IF('⚙ Config & Assumptions'!B41>=10,AL35,0)+IF('⚙ Config & Assumptions'!B41>=11,AP35,0)+IF('⚙ Config & Assumptions'!B41>=12,AT35,0) -> 0 | BC35: =IF(AND('⚙ Config & Assumptions'!B41>=1,C35<>""),C35,0)+IF(AND('⚙ Config & Assumptions'!B41>=2,G35<>""),G35,0)+IF(AND('⚙ Config & Assumptions'!B41>=3,K35<>""),K35,0)+IF(AND('⚙ Config & Assumptions'!B41>=4,O35<>""),O35,0)+IF(AND('⚙ Config & Assumptions'!B41>=5,S35<>""),S35,0)+IF(AND('⚙ Config & Assumptions'!B41>=6,W35<>""),W35,0)+IF(AND('⚙ Config & Assumptions'!B41>=7,AA35<>""),AA35,0)+IF(AND('⚙ Config & Assumptions'!B41>=8,AE35<>""),AE35,0)+IF(AND('⚙ Config & Assumptions'!B41>=9,AI35<>""),AI35,0)+IF(AND('⚙ Config & Assumptions'!B41>=10,AM35<>""),AM35,0)+IF(AND('⚙ Config & Assumptions'!B41>=11,AQ35<>""),AQ35,0)+IF(AND('⚙ Config & Assumptions'!B41>=12,AU35<>""),AU35,0) -> 0 | BD35: =IF(BC35=0,"",BC35-BB35) | BE35: =IF(OR(BC35=0,BB35=0),"",(BC35-BB35)/BB35)
A36: ⇒ Net Profit after Fixed OH (₹) | B36: =B32-B35 -> 1935 | D36: =IF(C36="","",C36-B36) | E36: =IF(OR(C36="",B36=0),"",(C36-B36)/B36) | F36: =F32-F35 -> 2179 | H36: =IF(G36="","",G36-F36) | I36: =IF(OR(G36="",F36=0),"",(G36-F36)/F36) | J36: =J32-J35 -> 1693 | L36: =IF(K36="","",K36-J36) | M36: =IF(OR(K36="",J36=0),"",(K36-J36)/J36) | N36: =N32-N35 -> 2179 | P36: =IF(O36="","",O36-N36) | Q36: =IF(OR(O36="",N36=0),"",(O36-N36)/N36) | R36: =R32-R35 -> 2911 | T36: =IF(S36="","",S36-R36) | U36: =IF(OR(S36="",R36=0),"",(S36-R36)/R36) | V36: =V32-V35 -> 3154 | X36: =IF(W36="","",W36-V36) | Y36: =IF(OR(W36="",V36=0),"",(W36-V36)/V36) | Z36: =Z32-Z35 -> 3397 | AB36: =IF(AA36="","",AA36-Z36) | AC36: =IF(OR(AA36="",Z36=0),"",(AA36-Z36)/Z36) | AD36: =AD32-AD35 -> 3154 | AF36: =IF(AE36="","",AE36-AD36) | AG36: =IF(OR(AE36="",AD36=0),"",(AE36-AD36)/AD36) | AH36: =AH32-AH35 -> 2911 | AJ36: =IF(AI36="","",AI36-AH36) | AK36: =IF(OR(AI36="",AH36=0),"",(AI36-AH36)/AH36) | AL36: =AL32-AL35 -> 2911 | AN36: =IF(AM36="","",AM36-AL36) | AO36: =IF(OR(AM36="",AL36=0),"",(AM36-AL36)/AL36) | AP36: =AP32-AP35 -> 2667 | AR36: =IF(AQ36="","",AQ36-AP36) | AS36: =IF(OR(AQ36="",AP36=0),"",(AQ36-AP36)/AP36) | AT36: =AT32-AT35 -> 1935 | AV36: =IF(AU36="","",AU36-AT36) | AW36: =IF(OR(AU36="",AT36=0),"",(AU36-AT36)/AT36) | AX36: =CHOOSE('⚙ Config & Assumptions'!B41,B36,F36,J36,N36,R36,V36,Z36,AD36,AH36,AL36,AP36,AT36) -> 1935 | AY36: =IF(CHOOSE('⚙ Config & Assumptions'!B41,C36,G36,K36,O36,S36,W36,AA36,AE36,AI36,AM36,AQ36,AU36)="","",CHOOSE('⚙ Config & Assumptions'!B41,C36,G36,K36,O36,S36,W36,AA36,AE36,AI36,AM36,AQ36,AU36)) | AZ36: =IF(AY36="","",AY36-AX36) | BA36: =IF(OR(AY36="",AX36=0),"",(AY36-AX36)/AX36) | BB36: =IF('⚙ Config & Assumptions'!B41>=1,B36,0)+IF('⚙ Config & Assumptions'!B41>=2,F36,0)+IF('⚙ Config & Assumptions'!B41>=3,J36,0)+IF('⚙ Config & Assumptions'!B41>=4,N36,0)+IF('⚙ Config & Assumptions'!B41>=5,R36,0)+IF('⚙ Config & Assumptions'!B41>=6,V36,0)+IF('⚙ Config & Assumptions'!B41>=7,Z36,0)+IF('⚙ Config & Assumptions'!B41>=8,AD36,0)+IF('⚙ Config & Assumptions'!B41>=9,AH36,0)+IF('⚙ Config & Assumptions'!B41>=10,AL36,0)+IF('⚙ Config & Assumptions'!B41>=11,AP36,0)+IF('⚙ Config & Assumptions'!B41>=12,AT36,0) -> 1935 | BC36: =IF(AND('⚙ Config & Assumptions'!B41>=1,C36<>""),C36,0)+IF(AND('⚙ Config & Assumptions'!B41>=2,G36<>""),G36,0)+IF(AND('⚙ Config & Assumptions'!B41>=3,K36<>""),K36,0)+IF(AND('⚙ Config & Assumptions'!B41>=4,O36<>""),O36,0)+IF(AND('⚙ Config & Assumptions'!B41>=5,S36<>""),S36,0)+IF(AND('⚙ Config & Assumptions'!B41>=6,W36<>""),W36,0)+IF(AND('⚙ Config & Assumptions'!B41>=7,AA36<>""),AA36,0)+IF(AND('⚙ Config & Assumptions'!B41>=8,AE36<>""),AE36,0)+IF(AND('⚙ Config & Assumptions'!B41>=9,AI36<>""),AI36,0)+IF(AND('⚙ Config & Assumptions'!B41>=10,AM36<>""),AM36,0)+IF(AND('⚙ Config & Assumptions'!B41>=11,AQ36<>""),AQ36,0)+IF(AND('⚙ Config & Assumptions'!B41>=12,AU36<>""),AU36,0) -> 0 | BD36: =IF(BC36=0,"",BC36-BB36) | BE36: =IF(OR(BC36=0,BB36=0),"",(BC36-BB36)/BB36)
A37: Net Margin after Fixed OH (%) | B37: =IF(B14=0,0,B36/B14) -> 0.17177097 | D37: =IF(C37="","",C37-B37) | E37: =IF(OR(C37="",B37=0),"",(C37-B37)/B37) | F37: =IF(F14=0,0,F36/F14) -> 0.1805452 | H37: =IF(G37="","",G37-F37) | I37: =IF(OR(G37="",F37=0),"",(G37-F37)/F37) | J37: =IF(J14=0,0,J36/J14) -> 0.16185468 | L37: =IF(K37="","",K37-J37) | M37: =IF(OR(K37="",J37=0),"",(K37-J37)/J37) | N37: =IF(N14=0,0,N36/N14) -> 0.1805452 | P37: =IF(O37="","",O37-N37) | Q37: =IF(OR(O37="",N37=0),"",(O37-N37)/N37) | R37: =IF(R14=0,0,R36/R14) -> 0.20099427 | T37: =IF(S37="","",S37-R37) | U37: =IF(OR(S37="",R37=0),"",(S37-R37)/R37) | V37: =IF(V14=0,0,V36/V14) -> 0.2063056 | X37: =IF(W37="","",W37-V37) | Y37: =IF(OR(W37="",V37=0),"",(W37-V37)/V37) | Z37: =IF(Z14=0,0,Z36/Z14) -> 0.21109868 | AB37: =IF(AA37="","",AA37-Z37) | AC37: =IF(OR(AA37="",Z37=0),"",(AA37-Z37)/Z37) | AD37: =IF(AD14=0,0,AD36/AD14) -> 0.2063056 | AF37: =IF(AE37="","",AE37-AD37) | AG37: =IF(OR(AE37="",AD37=0),"",(AE37-AD37)/AD37) | AH37: =IF(AH14=0,0,AH36/AH14) -> 0.20099427 | AJ37: =IF(AI37="","",AI37-AH37) | AK37: =IF(OR(AI37="",AH37=0),"",(AI37-AH37)/AH37) | AL37: =IF(AL14=0,0,AL36/AL14) -> 0.20099427 | AN37: =IF(AM37="","",AM37-AL37) | AO37: =IF(OR(AM37="",AL37=0),"",(AM37-AL37)/AL37) | AP37: =IF(AP14=0,0,AP36/AP14) -> 0.19498465 | AR37: =IF(AQ37="","",AQ37-AP37) | AS37: =IF(OR(AQ37="",AP37=0),"",(AQ37-AP37)/AP37) | AT37: =IF(AT14=0,0,AT36/AT14) -> 0.17177097 | AV37: =IF(AU37="","",AU37-AT37) | AW37: =IF(OR(AU37="",AT37=0),"",(AU37-AT37)/AT37) | AX37: =CHOOSE('⚙ Config & Assumptions'!B41,B37,F37,J37,N37,R37,V37,Z37,AD37,AH37,AL37,AP37,AT37) -> 0.17177097 | AY37: =IF(CHOOSE('⚙ Config & Assumptions'!B41,C37,G37,K37,O37,S37,W37,AA37,AE37,AI37,AM37,AQ37,AU37)="","",CHOOSE('⚙ Config & Assumptions'!B41,C37,G37,K37,O37,S37,W37,AA37,AE37,AI37,AM37,AQ37,AU37)) | AZ37: =IF(AY37="","",AY37-AX37) | BA37: =IF(OR(AY37="",AX37=0),"",(AY37-AX37)/AX37) | BB37: =IF('⚙ Config & Assumptions'!B41>=1,B37,0)+IF('⚙ Config & Assumptions'!B41>=2,F37,0)+IF('⚙ Config & Assumptions'!B41>=3,J37,0)+IF('⚙ Config & Assumptions'!B41>=4,N37,0)+IF('⚙ Config & Assumptions'!B41>=5,R37,0)+IF('⚙ Config & Assumptions'!B41>=6,V37,0)+IF('⚙ Config & Assumptions'!B41>=7,Z37,0)+IF('⚙ Config & Assumptions'!B41>=8,AD37,0)+IF('⚙ Config & Assumptions'!B41>=9,AH37,0)+IF('⚙ Config & Assumptions'!B41>=10,AL37,0)+IF('⚙ Config & Assumptions'!B41>=11,AP37,0)+IF('⚙ Config & Assumptions'!B41>=12,AT37,0) -> 0.17177097 | BC37: =IF(AND('⚙ Config & Assumptions'!B41>=1,C37<>""),C37,0)+IF(AND('⚙ Config & Assumptions'!B41>=2,G37<>""),G37,0)+IF(AND('⚙ Config & Assumptions'!B41>=3,K37<>""),K37,0)+IF(AND('⚙ Config & Assumptions'!B41>=4,O37<>""),O37,0)+IF(AND('⚙ Config & Assumptions'!B41>=5,S37<>""),S37,0)+IF(AND('⚙ Config & Assumptions'!B41>=6,W37<>""),W37,0)+IF(AND('⚙ Config & Assumptions'!B41>=7,AA37<>""),AA37,0)+IF(AND('⚙ Config & Assumptions'!B41>=8,AE37<>""),AE37,0)+IF(AND('⚙ Config & Assumptions'!B41>=9,AI37<>""),AI37,0)+IF(AND('⚙ Config & Assumptions'!B41>=10,AM37<>""),AM37,0)+IF(AND('⚙ Config & Assumptions'!B41>=11,AQ37<>""),AQ37,0)+IF(AND('⚙ Config & Assumptions'!B41>=12,AU37<>""),AU37,0) -> 0 | BD37: =IF(BC37=0,"",BC37-BB37) | BE37: =IF(OR(BC37=0,BB37=0),"",(BC37-BB37)/BB37)
A38: ⑩ CONTRIBUTION MARGIN
A39: Contribution per Unit (₹) | B39: ='⚙ Config & Assumptions'!B21-'⚙ Config & Assumptions'!B24-'⚙ Config & Assumptions'!B25-'⚙ Config & Assumptions'!B26-'⚙ Config & Assumptions'!B21*'⚙ Config & Assumptions'!B31-'⚙ Config & Assumptions'!B25*'⚙ Config & Assumptions'!B33 -> 47.2828 | D39: =IF(C39="","",C39-B39) | E39: =IF(OR(C39="",B39=0),"",(C39-B39)/B39) | F39: ='⚙ Config & Assumptions'!B21-'⚙ Config & Assumptions'!B24-'⚙ Config & Assumptions'!B25-'⚙ Config & Assumptions'!B26-'⚙ Config & Assumptions'!B21*'⚙ Config & Assumptions'!B31-'⚙ Config & Assumptions'!B25*'⚙ Config & Assumptions'!B33 -> 47.2828 | H39: =IF(G39="","",G39-F39) | I39: =IF(OR(G39="",F39=0),"",(G39-F39)/F39) | J39: ='⚙ Config & Assumptions'!B21-'⚙ Config & Assumptions'!B24-'⚙ Config & Assumptions'!B25-'⚙ Config & Assumptions'!B26-'⚙ Config & Assumptions'!B21*'⚙ Config & Assumptions'!B31-'⚙ Config & Assumptions'!B25*'⚙ Config & Assumptions'!B33 -> 47.2828 | L39: =IF(K39="","",K39-J39) | M39: =IF(OR(K39="",J39=0),"",(K39-J39)/J39) | N39: ='⚙ Config & Assumptions'!B21-'⚙ Config & Assumptions'!B24-'⚙ Config & Assumptions'!B25-'⚙ Config & Assumptions'!B26-'⚙ Config & Assumptions'!B21*'⚙ Config & Assumptions'!B31-'⚙ Config & Assumptions'!B25*'⚙ Config & Assumptions'!B33 -> 47.2828 | P39: =IF(O39="","",O39-N39) | Q39: =IF(OR(O39="",N39=0),"",(O39-N39)/N39) | R39: ='⚙ Config & Assumptions'!B21-'⚙ Config & Assumptions'!B24-'⚙ Config & Assumptions'!B25-'⚙ Config & Assumptions'!B26-'⚙ Config & Assumptions'!B21*'⚙ Config & Assumptions'!B31-'⚙ Config & Assumptions'!B25*'⚙ Config & Assumptions'!B33 -> 47.2828 | T39: =IF(S39="","",S39-R39) | U39: =IF(OR(S39="",R39=0),"",(S39-R39)/R39) | V39: ='⚙ Config & Assumptions'!B21-'⚙ Config & Assumptions'!B24-'⚙ Config & Assumptions'!B25-'⚙ Config & Assumptions'!B26-'⚙ Config & Assumptions'!B21*'⚙ Config & Assumptions'!B31-'⚙ Config & Assumptions'!B25*'⚙ Config & Assumptions'!B33 -> 47.2828 | X39: =IF(W39="","",W39-V39) | Y39: =IF(OR(W39="",V39=0),"",(W39-V39)/V39) | Z39: ='⚙ Config & Assumptions'!B21-'⚙ Config & Assumptions'!B24-'⚙ Config & Assumptions'!B25-'⚙ Config & Assumptions'!B26-'⚙ Config & Assumptions'!B21*'⚙ Config & Assumptions'!B31-'⚙ Config & Assumptions'!B25*'⚙ Config & Assumptions'!B33 -> 47.2828 | AB39: =IF(AA39="","",AA39-Z39) | AC39: =IF(OR(AA39="",Z39=0),"",(AA39-Z39)/Z39) | AD39: ='⚙ Config & Assumptions'!B21-'⚙ Config & Assumptions'!B24-'⚙ Config & Assumptions'!B25-'⚙ Config & Assumptions'!B26-'⚙ Config & Assumptions'!B21*'⚙ Config & Assumptions'!B31-'⚙ Config & Assumptions'!B25*'⚙ Config & Assumptions'!B33 -> 47.2828 | AF39: =IF(AE39="","",AE39-AD39) | AG39: =IF(OR(AE39="",AD39=0),"",(AE39-AD39)/AD39) | AH39: ='⚙ Config & Assumptions'!B21-'⚙ Config & Assumptions'!B24-'⚙ Config & Assumptions'!B25-'⚙ Config & Assumptions'!B26-'⚙ Config & Assumptions'!B21*'⚙ Config & Assumptions'!B31-'⚙ Config & Assumptions'!B25*'⚙ Config & Assumptions'!B33 -> 47.2828 | AJ39: =IF(AI39="","",AI39-AH39) | AK39: =IF(OR(AI39="",AH39=0),"",(AI39-AH39)/AH39) | AL39: ='⚙ Config & Assumptions'!B21-'⚙ Config & Assumptions'!B24-'⚙ Config & Assumptions'!B25-'⚙ Config & Assumptions'!B26-'⚙ Config & Assumptions'!B21*'⚙ Config & Assumptions'!B31-'⚙ Config & Assumptions'!B25*'⚙ Config & Assumptions'!B33 -> 47.2828 | AN39: =IF(AM39="","",AM39-AL39) | AO39: =IF(OR(AM39="",AL39=0),"",(AM39-AL39)/AL39) | AP39: ='⚙ Config & Assumptions'!B21-'⚙ Config & Assumptions'!B24-'⚙ Config & Assumptions'!B25-'⚙ Config & Assumptions'!B26-'⚙ Config & Assumptions'!B21*'⚙ Config & Assumptions'!B31-'⚙ Config & Assumptions'!B25*'⚙ Config & Assumptions'!B33 -> 47.2828 | AR39: =IF(AQ39="","",AQ39-AP39) | AS39: =IF(OR(AQ39="",AP39=0),"",(AQ39-AP39)/AP39) | AT39: ='⚙ Config & Assumptions'!B21-'⚙ Config & Assumptions'!B24-'⚙ Config & Assumptions'!B25-'⚙ Config & Assumptions'!B26-'⚙ Config & Assumptions'!B21*'⚙ Config & Assumptions'!B31-'⚙ Config & Assumptions'!B25*'⚙ Config & Assumptions'!B33 -> 47.2828 | AV39: =IF(AU39="","",AU39-AT39) | AW39: =IF(OR(AU39="",AT39=0),"",(AU39-AT39)/AT39) | AX39: =CHOOSE('⚙ Config & Assumptions'!B41,B39,F39,J39,N39,R39,V39,Z39,AD39,AH39,AL39,AP39,AT39) -> 47.2828 | AY39: =IF(CHOOSE('⚙ Config & Assumptions'!B41,C39,G39,K39,O39,S39,W39,AA39,AE39,AI39,AM39,AQ39,AU39)="","",CHOOSE('⚙ Config & Assumptions'!B41,C39,G39,K39,O39,S39,W39,AA39,AE39,AI39,AM39,AQ39,AU39)) | AZ39: =IF(AY39="","",AY39-AX39) | BA39: =IF(OR(AY39="",AX39=0),"",(AY39-AX39)/AX39) | BB39: =IF('⚙ Config & Assumptions'!B41>=1,B39,0)+IF('⚙ Config & Assumptions'!B41>=2,F39,0)+IF('⚙ Config & Assumptions'!B41>=3,J39,0)+IF('⚙ Config & Assumptions'!B41>=4,N39,0)+IF('⚙ Config & Assumptions'!B41>=5,R39,0)+IF('⚙ Config & Assumptions'!B41>=6,V39,0)+IF('⚙ Config & Assumptions'!B41>=7,Z39,0)+IF('⚙ Config & Assumptions'!B41>=8,AD39,0)+IF('⚙ Config & Assumptions'!B41>=9,AH39,0)+IF('⚙ Config & Assumptions'!B41>=10,AL39,0)+IF('⚙ Config & Assumptions'!B41>=11,AP39,0)+IF('⚙ Config & Assumptions'!B41>=12,AT39,0) -> 47.2828 | BC39: =IF(AND('⚙ Config & Assumptions'!B41>=1,C39<>""),C39,0)+IF(AND('⚙ Config & Assumptions'!B41>=2,G39<>""),G39,0)+IF(AND('⚙ Config & Assumptions'!B41>=3,K39<>""),K39,0)+IF(AND('⚙ Config & Assumptions'!B41>=4,O39<>""),O39,0)+IF(AND('⚙ Config & Assumptions'!B41>=5,S39<>""),S39,0)+IF(AND('⚙ Config & Assumptions'!B41>=6,W39<>""),W39,0)+IF(AND('⚙ Config & Assumptions'!B41>=7,AA39<>""),AA39,0)+IF(AND('⚙ Config & Assumptions'!B41>=8,AE39<>""),AE39,0)+IF(AND('⚙ Config & Assumptions'!B41>=9,AI39<>""),AI39,0)+IF(AND('⚙ Config & Assumptions'!B41>=10,AM39<>""),AM39,0)+IF(AND('⚙ Config & Assumptions'!B41>=11,AQ39<>""),AQ39,0)+IF(AND('⚙ Config & Assumptions'!B41>=12,AU39<>""),AU39,0) -> 0 | BD39: =IF(BC39=0,"",BC39-BB39) | BE39: =IF(OR(BC39=0,BB39=0),"",(BC39-BB39)/BB39)
A40: Contribution Margin (%) | B40: =IF('⚙ Config & Assumptions'!B21=0,0,B39/'⚙ Config & Assumptions'!B21) -> 0.30379594 | D40: =IF(C40="","",C40-B40) | E40: =IF(OR(C40="",B40=0),"",(C40-B40)/B40) | F40: =IF('⚙ Config & Assumptions'!B21=0,0,F39/'⚙ Config & Assumptions'!B21) -> 0.30379594 | H40: =IF(G40="","",G40-F40) | I40: =IF(OR(G40="",F40=0),"",(G40-F40)/F40) | J40: =IF('⚙ Config & Assumptions'!B21=0,0,J39/'⚙ Config & Assumptions'!B21) -> 0.30379594 | L40: =IF(K40="","",K40-J40) | M40: =IF(OR(K40="",J40=0),"",(K40-J40)/J40) | N40: =IF('⚙ Config & Assumptions'!B21=0,0,N39/'⚙ Config & Assumptions'!B21) -> 0.30379594 | P40: =IF(O40="","",O40-N40) | Q40: =IF(OR(O40="",N40=0),"",(O40-N40)/N40) | R40: =IF('⚙ Config & Assumptions'!B21=0,0,R39/'⚙ Config & Assumptions'!B21) -> 0.30379594 | T40: =IF(S40="","",S40-R40) | U40: =IF(OR(S40="",R40=0),"",(S40-R40)/R40) | V40: =IF('⚙ Config & Assumptions'!B21=0,0,V39/'⚙ Config & Assumptions'!B21) -> 0.30379594 | X40: =IF(W40="","",W40-V40) | Y40: =IF(OR(W40="",V40=0),"",(W40-V40)/V40) | Z40: =IF('⚙ Config & Assumptions'!B21=0,0,Z39/'⚙ Config & Assumptions'!B21) -> 0.30379594 | AB40: =IF(AA40="","",AA40-Z40) | AC40: =IF(OR(AA40="",Z40=0),"",(AA40-Z40)/Z40) | AD40: =IF('⚙ Config & Assumptions'!B21=0,0,AD39/'⚙ Config & Assumptions'!B21) -> 0.30379594 | AF40: =IF(AE40="","",AE40-AD40) | AG40: =IF(OR(AE40="",AD40=0),"",(AE40-AD40)/AD40) | AH40: =IF('⚙ Config & Assumptions'!B21=0,0,AH39/'⚙ Config & Assumptions'!B21) -> 0.30379594 | AJ40: =IF(AI40="","",AI40-AH40) | AK40: =IF(OR(AI40="",AH40=0),"",(AI40-AH40)/AH40) | AL40: =IF('⚙ Config & Assumptions'!B21=0,0,AL39/'⚙ Config & Assumptions'!B21) -> 0.30379594 | AN40: =IF(AM40="","",AM40-AL40) | AO40: =IF(OR(AM40="",AL40=0),"",(AM40-AL40)/AL40) | AP40: =IF('⚙ Config & Assumptions'!B21=0,0,AP39/'⚙ Config & Assumptions'!B21) -> 0.30379594 | AR40: =IF(AQ40="","",AQ40-AP40) | AS40: =IF(OR(AQ40="",AP40=0),"",(AQ40-AP40)/AP40) | AT40: =IF('⚙ Config & Assumptions'!B21=0,0,AT39/'⚙ Config & Assumptions'!B21) -> 0.30379594 | AV40: =IF(AU40="","",AU40-AT40) | AW40: =IF(OR(AU40="",AT40=0),"",(AU40-AT40)/AT40) | AX40: =CHOOSE('⚙ Config & Assumptions'!B41,B40,F40,J40,N40,R40,V40,Z40,AD40,AH40,AL40,AP40,AT40) -> 0.30379594 | AY40: =IF(CHOOSE('⚙ Config & Assumptions'!B41,C40,G40,K40,O40,S40,W40,AA40,AE40,AI40,AM40,AQ40,AU40)="","",CHOOSE('⚙ Config & Assumptions'!B41,C40,G40,K40,O40,S40,W40,AA40,AE40,AI40,AM40,AQ40,AU40)) | AZ40: =IF(AY40="","",AY40-AX40) | BA40: =IF(OR(AY40="",AX40=0),"",(AY40-AX40)/AX40) | BB40: =IF('⚙ Config & Assumptions'!B41>=1,B40,0)+IF('⚙ Config & Assumptions'!B41>=2,F40,0)+IF('⚙ Config & Assumptions'!B41>=3,J40,0)+IF('⚙ Config & Assumptions'!B41>=4,N40,0)+IF('⚙ Config & Assumptions'!B41>=5,R40,0)+IF('⚙ Config & Assumptions'!B41>=6,V40,0)+IF('⚙ Config & Assumptions'!B41>=7,Z40,0)+IF('⚙ Config & Assumptions'!B41>=8,AD40,0)+IF('⚙ Config & Assumptions'!B41>=9,AH40,0)+IF('⚙ Config & Assumptions'!B41>=10,AL40,0)+IF('⚙ Config & Assumptions'!B41>=11,AP40,0)+IF('⚙ Config & Assumptions'!B41>=12,AT40,0) -> 0.30379594 | BC40: =IF(AND('⚙ Config & Assumptions'!B41>=1,C40<>""),C40,0)+IF(AND('⚙ Config & Assumptions'!B41>=2,G40<>""),G40,0)+IF(AND('⚙ Config & Assumptions'!B41>=3,K40<>""),K40,0)+IF(AND('⚙ Config & Assumptions'!B41>=4,O40<>""),O40,0)+IF(AND('⚙ Config & Assumptions'!B41>=5,S40<>""),S40,0)+IF(AND('⚙ Config & Assumptions'!B41>=6,W40<>""),W40,0)+IF(AND('⚙ Config & Assumptions'!B41>=7,AA40<>""),AA40,0)+IF(AND('⚙ Config & Assumptions'!B41>=8,AE40<>""),AE40,0)+IF(AND('⚙ Config & Assumptions'!B41>=9,AI40<>""),AI40,0)+IF(AND('⚙ Config & Assumptions'!B41>=10,AM40<>""),AM40,0)+IF(AND('⚙ Config & Assumptions'!B41>=11,AQ40<>""),AQ40,0)+IF(AND('⚙ Config & Assumptions'!B41>=12,AU40<>""),AU40,0) -> 0 | BD40: =IF(BC40=0,"",BC40-BB40) | BE40: =IF(OR(BC40=0,BB40=0),"",(BC40-BB40)/BB40)
A41: ⑪ BANK SETTLEMENT
A42: Bank Settlement (₹) — Estimated | B42: =ROUND('⚙ Config & Assumptions'!B5*'⚙ Config & Assumptions'!B7*(1-'⚙ Config & Assumptions'!B22)*('⚙ Config & Assumptions'!B21-'⚙ Config & Assumptions'!B25-'⚙ Config & Assumptions'!B25*'⚙ Config & Assumptions'!B33-'⚙ Config & Assumptions'!B21*'⚙ Config & Assumptions'!B31-'⚙ Config & Assumptions'!B21*'⚙ Config & Assumptions'!B32),0) -> 10367 | D42: =IF(C42="","",C42-B42) | E42: =IF(OR(C42="",B42=0),"",(C42-B42)/B42) | F42: =ROUND('⚙ Config & Assumptions'!B5*'⚙ Config & Assumptions'!B8*(1-'⚙ Config & Assumptions'!B22)*('⚙ Config & Assumptions'!B21-'⚙ Config & Assumptions'!B25-'⚙ Config & Assumptions'!B25*'⚙ Config & Assumptions'!B33-'⚙ Config & Assumptions'!B21*'⚙ Config & Assumptions'!B31-'⚙ Config & Assumptions'!B21*'⚙ Config & Assumptions'!B32),0) -> 11107 | H42: =IF(G42="","",G42-F42) | I42: =IF(OR(G42="",F42=0),"",(G42-F42)/F42) | J42: =ROUND('⚙ Config & Assumptions'!B5*'⚙ Config & Assumptions'!B9*(1-'⚙ Config & Assumptions'!B22)*('⚙ Config & Assumptions'!B21-'⚙ Config & Assumptions'!B25-'⚙ Config & Assumptions'!B25*'⚙ Config & Assumptions'!B33-'⚙ Config & Assumptions'!B21*'⚙ Config & Assumptions'!B31-'⚙ Config & Assumptions'!B21*'⚙ Config & Assumptions'!B32),0) -> 9626 | L42: =IF(K42="","",K42-J42) | M42: =IF(OR(K42="",J42=0),"",(K42-J42)/J42) | N42: =ROUND('⚙ Config & Assumptions'!B5*'⚙ Config & Assumptions'!B10*(1-'⚙ Config & Assumptions'!B22)*('⚙ Config & Assumptions'!B21-'⚙ Config & Assumptions'!B25-'⚙ Config & Assumptions'!B25*'⚙ Config & Assumptions'!B33-'⚙ Config & Assumptions'!B21*'⚙ Config & Assumptions'!B31-'⚙ Config & Assumptions'!B21*'⚙ Config & Assumptions'!B32),0) -> 11107 | P42: =IF(O42="","",O42-N42) | Q42: =IF(OR(O42="",N42=0),"",(O42-N42)/N42) | R42: =ROUND('⚙ Config & Assumptions'!B5*'⚙ Config & Assumptions'!B11*(1-'⚙ Config & Assumptions'!B22)*('⚙ Config & Assumptions'!B21-'⚙ Config & Assumptions'!B25-'⚙ Config & Assumptions'!B25*'⚙ Config & Assumptions'!B33-'⚙ Config & Assumptions'!B21*'⚙ Config & Assumptions'!B31-'⚙ Config & Assumptions'!B21*'⚙ Config & Assumptions'!B32),0) -> 13329 | T42: =IF(S42="","",S42-R42) | U42: =IF(OR(S42="",R42=0),"",(S42-R42)/R42) | V42: =ROUND('⚙ Config & Assumptions'!B5*'⚙ Config & Assumptions'!B12*(1-'⚙ Config & Assumptions'!B22)*('⚙ Config & Assumptions'!B21-'⚙ Config & Assumptions'!B25-'⚙ Config & Assumptions'!B25*'⚙ Config & Assumptions'!B33-'⚙ Config & Assumptions'!B21*'⚙ Config & Assumptions'!B31-'⚙ Config & Assumptions'!B21*'⚙ Config & Assumptions'!B32),0) -> 14069 | X42: =IF(W42="","",W42-V42) | Y42: =IF(OR(W42="",V42=0),"",(W42-V42)/V42) | Z42: =ROUND('⚙ Config & Assumptions'!B5*'⚙ Config & Assumptions'!B13*(1-'⚙ Config & Assumptions'!B22)*('⚙ Config & Assumptions'!B21-'⚙ Config & Assumptions'!B25-'⚙ Config & Assumptions'!B25*'⚙ Config & Assumptions'!B33-'⚙ Config & Assumptions'!B21*'⚙ Config & Assumptions'!B31-'⚙ Config & Assumptions'!B21*'⚙ Config & Assumptions'!B32),0) -> 14810 | AB42: =IF(AA42="","",AA42-Z42) | AC42: =IF(OR(AA42="",Z42=0),"",(AA42-Z42)/Z42) | AD42: =ROUND('⚙ Config & Assumptions'!B5*'⚙ Config & Assumptions'!B14*(1-'⚙ Config & Assumptions'!B22)*('⚙ Config & Assumptions'!B21-'⚙ Config & Assumptions'!B25-'⚙ Config & Assumptions'!B25*'⚙ Config & Assumptions'!B33-'⚙ Config & Assumptions'!B21*'⚙ Config & Assumptions'!B31-'⚙ Config & Assumptions'!B21*'⚙ Config & Assumptions'!B32),0) -> 14069 | AF42: =IF(AE42="","",AE42-AD42) | AG42: =IF(OR(AE42="",AD42=0),"",(AE42-AD42)/AD42) | AH42: =ROUND('⚙ Config & Assumptions'!B5*'⚙ Config & Assumptions'!B15*(1-'⚙ Config & Assumptions'!B22)*('⚙ Config & Assumptions'!B21-'⚙ Config & Assumptions'!B25-'⚙ Config & Assumptions'!B25*'⚙ Config & Assumptions'!B33-'⚙ Config & Assumptions'!B21*'⚙ Config & Assumptions'!B31-'⚙ Config & Assumptions'!B21*'⚙ Config & Assumptions'!B32),0) -> 13329 | AJ42: =IF(AI42="","",AI42-AH42) | AK42: =IF(OR(AI42="",AH42=0),"",(AI42-AH42)/AH42) | AL42: =ROUND('⚙ Config & Assumptions'!B5*'⚙ Config & Assumptions'!B16*(1-'⚙ Config & Assumptions'!B22)*('⚙ Config & Assumptions'!B21-'⚙ Config & Assumptions'!B25-'⚙ Config & Assumptions'!B25*'⚙ Config & Assumptions'!B33-'⚙ Config & Assumptions'!B21*'⚙ Config & Assumptions'!B31-'⚙ Config & Assumptions'!B21*'⚙ Config & Assumptions'!B32),0) -> 13329 | AN42: =IF(AM42="","",AM42-AL42) | AO42: =IF(OR(AM42="",AL42=0),"",(AM42-AL42)/AL42) | AP42: =ROUND('⚙ Config & Assumptions'!B5*'⚙ Config & Assumptions'!B17*(1-'⚙ Config & Assumptions'!B22)*('⚙ Config & Assumptions'!B21-'⚙ Config & Assumptions'!B25-'⚙ Config & Assumptions'!B25*'⚙ Config & Assumptions'!B33-'⚙ Config & Assumptions'!B21*'⚙ Config & Assumptions'!B31-'⚙ Config & Assumptions'!B21*'⚙ Config & Assumptions'!B32),0) -> 12588 | AR42: =IF(AQ42="","",AQ42-AP42) | AS42: =IF(OR(AQ42="",AP42=0),"",(AQ42-AP42)/AP42) | AT42: =ROUND('⚙ Config & Assumptions'!B5*'⚙ Config & Assumptions'!B18*(1-'⚙ Config & Assumptions'!B22)*('⚙ Config & Assumptions'!B21-'⚙ Config & Assumptions'!B25-'⚙ Config & Assumptions'!B25*'⚙ Config & Assumptions'!B33-'⚙ Config & Assumptions'!B21*'⚙ Config & Assumptions'!B31-'⚙ Config & Assumptions'!B21*'⚙ Config & Assumptions'!B32),0) -> 10367 | AV42: =IF(AU42="","",AU42-AT42) | AW42: =IF(OR(AU42="",AT42=0),"",(AU42-AT42)/AT42) | AX42: =CHOOSE('⚙ Config & Assumptions'!B41,B42,F42,J42,N42,R42,V42,Z42,AD42,AH42,AL42,AP42,AT42) -> 10367 | AY42: =IF(CHOOSE('⚙ Config & Assumptions'!B41,C42,G42,K42,O42,S42,W42,AA42,AE42,AI42,AM42,AQ42,AU42)="","",CHOOSE('⚙ Config & Assumptions'!B41,C42,G42,K42,O42,S42,W42,AA42,AE42,AI42,AM42,AQ42,AU42)) | AZ42: =IF(AY42="","",AY42-AX42) | BA42: =IF(OR(AY42="",AX42=0),"",(AY42-AX42)/AX42) | BB42: =IF('⚙ Config & Assumptions'!B41>=1,B42,0)+IF('⚙ Config & Assumptions'!B41>=2,F42,0)+IF('⚙ Config & Assumptions'!B41>=3,J42,0)+IF('⚙ Config & Assumptions'!B41>=4,N42,0)+IF('⚙ Config & Assumptions'!B41>=5,R42,0)+IF('⚙ Config & Assumptions'!B41>=6,V42,0)+IF('⚙ Config & Assumptions'!B41>=7,Z42,0)+IF('⚙ Config & Assumptions'!B41>=8,AD42,0)+IF('⚙ Config & Assumptions'!B41>=9,AH42,0)+IF('⚙ Config & Assumptions'!B41>=10,AL42,0)+IF('⚙ Config & Assumptions'!B41>=11,AP42,0)+IF('⚙ Config & Assumptions'!B41>=12,AT42,0) -> 10367 | BC42: =IF(AND('⚙ Config & Assumptions'!B41>=1,C42<>""),C42,0)+IF(AND('⚙ Config & Assumptions'!B41>=2,G42<>""),G42,0)+IF(AND('⚙ Config & Assumptions'!B41>=3,K42<>""),K42,0)+IF(AND('⚙ Config & Assumptions'!B41>=4,O42<>""),O42,0)+IF(AND('⚙ Config & Assumptions'!B41>=5,S42<>""),S42,0)+IF(AND('⚙ Config & Assumptions'!B41>=6,W42<>""),W42,0)+IF(AND('⚙ Config & Assumptions'!B41>=7,AA42<>""),AA42,0)+IF(AND('⚙ Config & Assumptions'!B41>=8,AE42<>""),AE42,0)+IF(AND('⚙ Config & Assumptions'!B41>=9,AI42<>""),AI42,0)+IF(AND('⚙ Config & Assumptions'!B41>=10,AM42<>""),AM42,0)+IF(AND('⚙ Config & Assumptions'!B41>=11,AQ42<>""),AQ42,0)+IF(AND('⚙ Config & Assumptions'!B41>=12,AU42<>""),AU42,0) -> 0 | BD42: =IF(BC42=0,"",BC42-BB42) | BE42: =IF(OR(BC42=0,BB42=0),"",(BC42-BB42)/BB42)
